Workbook

Sheet PAINEL DE CONTROLE

Sheet INADIMPLENTES

Sheet PARCEIROS

Sheet EMPRESAS

Sheet CUSTOS
B5: Janeiro | F5: Fevereiro | J5: Março | N5: Abril | R5: Maio | V5: Junho | Z5: Julho | AD5: Agosto | AH5: Setembro | AL5: Outubro | AP5: Novembro | AT5: Dezembro
B8: DATA | C8: DESCRIÇÃO | D8: VALOR | F8: DATA | G8: DESCRIÇÃO | H8: VALOR | J8: DATA | K8: DESCRIÇÃO | L8: VALOR | N8: DATA | O8: DESCRIÇÃO | P8: VALOR | R8: DATA | S8: DESCRIÇÃO | T8: VALOR | V8: DATA | W8: DESCRIÇÃO | X8: VALOR | Z8: DATA | AA8: DESCRIÇÃO | AB8: VALOR | AD8: DATA | AE8: DESCRIÇÃO | AF8: VALOR | AH8: DATA | AI8: DESCRIÇÃO | AJ8: VALOR | AL8: DATA | AM8: DESCRIÇÃO | AN8: VALOR | AP8: DATA | AQ8: DESCRIÇÃO | AR8: VALOR | AT8: DATA | AU8: DESCRIÇÃO | AV8: VALOR
C48: TOTAL | D48: =SUM(D9:D47) -> 0 | G48: TOTAL | H48: =SUM(H9:H47) -> 0 | K48: TOTAL | L48: =SUM(L9:L47) -> 0 | O48: TOTAL | P48: =SUM(P9:P47) -> 0 | S48: TOTAL | T48: =SUM(T9:T47) -> 0 | W48: TOTAL | X48: =SUM(X9:X47) -> 0 | AA48: TOTAL | AB48: =SUM(AB9:AB47) -> 0 | AE48: TOTAL | AF48: =SUM(AF9:AF47) -> 0 | AI48: TOTAL | AJ48: =SUM(AJ9:AJ47) -> 0 | AM48: TOTAL | AN48: =SUM(AN9:AN47) -> 0 | AQ48: TOTAL | AR48: =SUM(AR9:AR47) -> 0 | AU48: TOTAL | AV48: =SUM(AV9:AV47) -> 0
B50: CUSTO FIXO

Sheet FLUXO DE CAIXA
B2: Janeiro | E2: Fevereiro | H2: Março | K2: Abril | N2: Maio | Q2: Junho
B5: CUSTOS | C5: =CUSTOS!D48 -> 0 | E5: CUSTOS | F5: =CUSTOS!H48 -> 0 | H5: CUSTOS | I5: =CUSTOS!L48 -> 0 | K5: CUSTOS | L5: =CUSTOS!P48 -> 0 | N5: CUSTOS | O5: =CUSTOS!T48 -> 0 | Q5: CUSTOS | R5: =CUSTOS!X48 -> 0
B6: VENDAS | C6: =SUM(CODAY:ALMEGA!AZ104:AZ105) -> 0 | E6: VENDAS | F6: =SUM(CODAY:ALMEGA!BM104:BM105) -> 171.306 | H6: VENDAS | I6: =SUM(CODAY:ALMEGA!BZ104:BZ105) -> 0 | K6: VENDAS | L6: =SUM(CODAY:ALMEGA!CM104:CM105) -> 0 | N6: VENDAS | O6: =SUM(CODAY:ALMEGA!CZ104:CZ105) -> 0 | Q6: VENDAS | R6: =SUM(CODAY:ALMEGA!DM104:DM105) -> 0
B7: SALDO | C7: =C6-C5 -> 0 | E7: SALDO | F7: =F6-F5 -> 171.306 | H7: SALDO | I7: =I6-I5 -> 0 | K7: SALDO | L7: =L6-L5 -> 0 | N7: SALDO | O7: =O6-O5 -> 0 | Q7: SALDO | R7: =R6-R5 -> 0
B10: Julho | E10: Agosto | H10: Setembro | K10: Outubro | N10: Novembro | Q10: Dezembro
B13: CUSTOS | C13: =CUSTOS!AB48 -> 0 | E13: CUSTOS | F13: =CUSTOS!AF48 -> 0 | H13: CUSTOS | I13: =CUSTOS!AJ48 -> 0 | K13: CUSTOS | L13: =CUSTOS!AN48 -> 0 | N13: CUSTOS | O13: =CUSTOS!AR48 -> 0 | Q13: CUSTOS | R13: =CUSTOS!AV48 -> 0
B14: VENDAS | C14: =SUM(CODAY:ALMEGA!DZ104:DZ105) -> 0 | E14: VENDAS | F14: =SUM(CODAY:ALMEGA!EM104:EM105) -> 0 | H14: VENDAS | I14: =SUM(CODAY:ALMEGA!EZ104:EZ105) -> 0 | K14: VENDAS | L14: =SUM(CODAY:ALMEGA!FM104:FM105) -> 0 | N14: VENDAS | O14: =SUM(CODAY:ALMEGA!FZ104:FZ105) -> 0 | Q14: VENDAS | R14: =SUM(CODAY:ALMEGA!GM104:GM105) -> 0
B15: SALDO | C15: =C14-C13 -> 0 | E15: SALDO | F15: =F14-F13 -> 0 | H15: SALDO | I15: =I14-I13 -> 0 | K15: SALDO | L15: =L14-L13 -> 0 | N15: SALDO | O15: =O14-O13 -> 0 | Q15: SALDO | R15: =R14-R13 -> 0

Sheet CODAY
B1: JUNHO | M1: Voltar ao Inicio | O1: JULHO | Z1: Voltar ao Inicio | AB1: AGOSTO | AN1: Voltar ao Inicio | AP1: Janeiro | BA1: Voltar ao Inicio | BC1: Fevereiro | BN1: Voltar ao Inicio | BP1: Março | CA1: Voltar ao Inicio | CC1: Abril | CN1: Voltar ao Inicio | CP1: Maio | DA1: Voltar ao Inicio | DC1: Junho | DN1: Voltar ao Inicio | DP1: Julho | EA1: Voltar ao Inicio | EC1: Agosto | EN1: Voltar ao Inicio | EP1: Setembro | FA1: Voltar ao Inicio | FC1: Outubro | FN1: Voltar ao Inicio | FP1: Novembro | GA1: Voltar ao Inicio | GC1: Dezembro | GN1: Voltar ao Inicio
B2: Data | D2: CLIENTE | F2: Pedido | G2: NFE | H2: Valor | J2: TABELA | K2: PRAZO | L2: Comissão | M2: Situação Pedido | O2: Data | Q2: CLIENTE | S2: Pedido | T2: NFE | U2: Valor | W2: TABELA | X2: PRAZO | Y2: Comissão | Z2: Situação Pedido | AB2: Data | AD2: CLIENTE | AF2: Pedido | AG2: FORNECEDOR | AH2: NFE | AI2: Valor | AK2: TABELA | AL2: PRAZO | AM2: Comissão | AN2: Situação Pedido | AP2: Data | AR2: CLIENTE | AT2: Pedido | AU2: NFE | AV2: Valor | AX2: TABELA | AY2: Comissão | AZ2: Vendedor | BA2: Situação Pedido | BC2: Data | BE2: CLIENTE | BG2: Pedido | BH2: NFE | BI2: Valor | BK2: TABELA | BL2: Comissão | BM2: Vendedor | BN2: Situação Pedido | BP2: Data | BR2: CLIENTE | BT2: Pedido | BU2: NFE | BV2: Valor | BX2: TABELA | BY2: Comissão | BZ2: Vendedor | CA2: Situação Pedido | CC2: Data | CE2: CLIENTE | CG2: Pedido | CH2: NFE | CI2: Valor | CK2: TABELA | CL2: Comissão | CM2: Vendedor | CN2: Situação Pedido | CP2: Data | CR2: CLIENTE | CT2: Pedido | CU2: NFE | CV2: Valor | CX2: TABELA | CY2: Comissão | CZ2: Vendedor | DA2: Situação Pedido | DC2: Data | DE2: CLIENTE | DG2: Pedido | DH2: NFE | DI2: Valor | DK2: TABELA | DL2: Comissão | DM2: Vendedor | DN2: Situação Pedido | DP2: Data | DR2: CLIENTE | DT2: Pedido | DU2: NFE | DV2: Valor | DX2: TABELA | DY2: Comissão | DZ2: Vendedor | EA2: Situação Pedido | EC2: Data | EE2: CLIENTE | EG2: Pedido | EH2: NFE | EI2: Valor | EK2: TABELA | EL2: Comissão | EM2: Vendedor | EN2: Situação Pedido | EP2: Data | ER2: CLIENTE | ET2: Pedido | EU2: NFE | EV2: Valor | EX2: TABELA | EY2: Comissão | EZ2: Vendedor | FA2: Situação Pedido | FC2: Data | FE2: CLIENTE | FG2: Pedido | FH2: NFE | FI2: Valor | FK2: TABELA | FL2: Comissão | FM2: Vendedor | FN2: Situação Pedido | FP2: Data | FR2: CLIENTE | FT2: Pedido | FU2: NFE | FV2: Valor | FX2: TABELA | FY2: Comissão | FZ2: Vendedor | GA2: Situação Pedido | GC2: Data | GE2: CLIENTE | GG2: Pedido | GH2: NFE | GI2: Valor | GK2: TABELA | GL2: Comissão | GM2: Vendedor | GN2: Situação Pedido
B3: Compra | C3: 45811 | D3: Razão | E3: DECAZZA COM | F3: 250602172053470 | G3: 1441 | H3: Compra | I3: 755.44 | J3: 2 | K3: PIX | L3: =I4*5% -> 37.772 | M3: PAGO | O3: Compra | P3: 45846 | Q3: Razão | R3: DECAZZA COM | S3: 250708135238581 | T3: 187 | U3: Compra | V3: 10891.96 | W3: 2 | X3: PIX | Y3: =V4*5% -> 544.598 | Z3: FATURADO | AB3: Compra | AD3: Razão | AI3: Compra | AL3: PIX | AN3: PAGO | AP3: Compra | AR3: Razão | AV3: Compra | AX3: 1 | AY3: =AW4*5% -> 0 | AZ3: RENAN | BA3: PAGO | BC3: Compra | BE3: Razão | BI3: Compra | BL3: =BJ4*2.5% -> 0 | BP3: Compra | BR3: Razão | BV3: Compra | BY3: =BW4*2.5% -> 0 | CC3: Compra | CE3: Razão | CI3: Compra | CL3: =CJ4*2.5% -> 0 | CP3: Compra | CR3: Razão | CV3: Compra | CY3: =CW4*2.5% -> 0 | DC3: Compra | DE3: Razão | DI3: Compra | DL3: =DJ4*2.5% -> 0 | DP3: Compra | DR3: Razão | DV3: Compra | DY3: =DW4*2.5% -> 0 | EC3: Compra | EE3: Razão | EI3: Compra | EL3: =EJ4*2.5% -> 0 | EP3: Compra | ER3: Razão | EV3: Compra | EY3: =EW4*2.5% -> 0 | FC3: Compra | FE3: Razão | FI3: Compra | FL3: =FJ4*2.5% -> 0 | FP3: Compra | FR3: Razão | FV3: Compra | FY3: =FW4*2.5% -> 0 | GC3: Compra | GE3: Razão | GI3: Compra | GL3: =GJ4*2.5% -> 0
B4: Faturamento | C4: 45812 | D4: CNPJ: | E4: 43.967.691/0001-00 | H4: Faturamento | I4: 755.44 | O4: Faturamento | P4: 45848 | Q4: CNPJ: | R4: 43.967.691/0001-00 | U4: Faturamento | V4: 10891.96 | AB4: Faturamento | AD4: CNPJ: | AI4: Faturamento | AP4: Faturamento | AR4: CNPJ: | AV4: Faturamento | BC4: Faturamento | BE4: CNPJ: | BI4: Faturamento | BP4: Faturamento | BR4: CNPJ: | BV4: Faturamento | CC4: Faturamento | CE4: CNPJ: | CI4: Faturamento | CP4: Faturamento | CR4: CNPJ: | CV4: Faturamento | DC4: Faturamento | DE4: CNPJ: | DI4: Faturamento | DP4: Faturamento | DR4: CNPJ: | DV4: Faturamento | EC4: Faturamento | EE4: CNPJ: | EI4: Faturamento | EP4: Faturamento | ER4: CNPJ: | EV4: Faturamento | FC4: Faturamento | FE4: CNPJ: | FI4: Faturamento | FP4: Faturamento | FR4: CNPJ: | FV4: Faturamento | GC4: Faturamento | GE4: CNPJ: | GI4: Faturamento
B6: Compra | C6: 45813 | D6: Razão | E6: EMBALEME | F6: 250604123701560 | G6: 1447 | H6: Compra | I6: 4110.14 | J6: 2 | K6: PRAZO | L6: =I7*5% -> 205.508 | M6: FATURADO | O6: Compra | P6: 45852 | Q6: Razão | R6: DECAZZA COM | S6: 3508 | T6: 218 | U6: Compra | V6: 71547.78 | W6: 2 | Y6: =V7*3.5% -> 2107.9968 | Z6: FATURADO | AB6: Compra | AD6: Razão | AI6: Compra | AM6: =AJ7*5% -> 0 | AN6: FATURADO | AP6: Compra | AR6: Razão | AV6: Compra | AY6: =AW7*2.5% -> 0 | BC6: Compra | BE6: Razão | BI6: Compra | BL6: =BJ7*2.5% -> 0 | BP6: Compra | BR6: Razão | BV6: Compra | BY6: =BW7*2.5% -> 0 | CC6: Compra | CE6: Razão | CI6: Compra | CL6: =CJ7*2.5% -> 0 | CP6: Compra | CR6: Razão | CV6: Compra | CY6: =CW7*2.5% -> 0 | DC6: Compra | DE6: Razão | DI6: Compra | DL6: =DJ7*2.5% -> 0 | DP6: Compra | DR6: Razão | DV6: Compra | DY6: =DW7*2.5% -> 0 | EC6: Compra | EE6: Razão | EI6: Compra | EL6: =EJ7*2.5% -> 0 | EP6: Compra | ER6: Razão | EV6: Compra | EY6: =EW7*2.5% -> 0 | FC6: Compra | FE6: Razão | FI6: Compra | FL6: =FJ7*2.5% -> 0 | FP6: Compra | FR6: Razão | FV6: Compra | FY6: =FW7*2.5% -> 0 | GC6: Compra | GE6: Razão | GI6: Compra | GL6: =GJ7*2.5% -> 0
B7: Faturamento | C7: 45817 | D7: CNPJ: | E7: 00.458.459/0001-33 | H7: Faturamento | I7: 4110.16 | O7: Faturamento | P7: 45855 | Q7: CNPJ: | R7: 43.967.691/0001-00 | U7: Faturamento | V7: 60228.48 | AB7: Faturamento | AD7: CNPJ: | AI7: Faturamento | AP7: Faturamento | AR7: CNPJ: | AV7: Faturamento | BC7: Faturamento | BE7: CNPJ: | BI7: Faturamento | BP7: Faturamento | BR7: CNPJ: | BV7: Faturamento | CC7: Faturamento | CE7: CNPJ: | CI7: Faturamento | CP7: Faturamento | CR7: CNPJ: | CV7: Faturamento | DC7: Faturamento | DE7: CNPJ: | DI7: Faturamento | DP7: Faturamento | DR7: CNPJ: | DV7: Faturamento | EC7: Faturamento | EE7: CNPJ: | EI7: Faturamento | EP7: Faturamento | ER7: CNPJ: | EV7: Faturamento | FC7: Faturamento | FE7: CNPJ: | FI7: Faturamento | FP7: Faturamento | FR7: CNPJ: | FV7: Faturamento | GC7: Faturamento | GE7: CNPJ: | GI7: Faturamento
B9: Compra | C9: 45819 | D9: Razão | E9: DECAZZA COMERCIAL | F9: 3062 | H9: Compra | I9: 7548 | J9: 2 | K9: PIX | L9: =I10*5% -> 377.4 | M9: PAGO | O9: Compra | P9: 45861 | Q9: Razão | R9: DECAZZA COM | S9: 250723143208488 | T9: 266 | U9: Compra | V9: 46645.2 | W9: 2 | Y9: =V10*4% -> 1865.808 | Z9: FATURADO | AB9: Compra | AD9: Razão | AI9: Compra | AM9: =AJ10*6% -> 0 | AN9: FATURADO | AP9: Compra | AR9: Razão | AV9: Compra | AY9: =AW10*2.5% -> 0 | BC9: Compra | BE9: Razão | BI9: Compra | BL9: =BJ10*2.5% -> 0 | BP9: Compra | BR9: Razão | BV9: Compra | BY9: =BW10*2.5% -> 0 | CC9: Compra | CE9: Razão | CI9: Compra | CL9: =CJ10*2.5% -> 0 | CP9: Compra | CR9: Razão | CV9: Compra | CY9: =CW10*2.5% -> 0 | DC9: Compra | DE9: Razão | DI9: Compra | DL9: =DJ10*2.5% -> 0 | DP9: Compra | DR9: Razão | DV9: Compra | DY9: =DW10*2.5% -> 0 | EC9: Compra | EE9: Razão | EI9: Compra | EL9: =EJ10*2.5% -> 0 | EP9: Compra | ER9: Razão | EV9: Compra | EY9: =EW10*2.5% -> 0 | FC9: Compra | FE9: Razão | FI9: Compra | FL9: =FJ10*2.5% -> 0 | FP9: Compra | FR9: Razão | FV9: Compra | FY9: =FW10*2.5% -> 0 | GC9: Compra | GE9: Razão | GI9: Compra | GL9: =GJ10*2.5% -> 0
B10: Faturamento | C10: 45820 | D10: CNPJ: | E10: 43.967.691/0001-00 | G10: 1457 | H10: Faturamento | I10: 7548 | O10: Faturamento | P10: 45862 | Q10: CNPJ: | R10: 43.967.691/0001-00 | U10: Faturamento | V10: 46645.2 | AB10: Faturamento | AD10: CNPJ: | AI10: Faturamento | AP10: Faturamento | AR10: CNPJ: | AV10: Faturamento | BC10: Faturamento | BE10: CNPJ: | BI10: Faturamento | BP10: Faturamento | BR10: CNPJ: | BV10: Faturamento | CC10: Faturamento | CE10: CNPJ: | CI10: Faturamento | CP10: Faturamento | CR10: CNPJ: | CV10: Faturamento | DC10: Faturamento | DE10: CNPJ: | DI10: Faturamento | DP10: Faturamento | DR10: CNPJ: | DV10: Faturamento | EC10: Faturamento | EE10: CNPJ: | EI10: Faturamento | EP10: Faturamento | ER10: CNPJ: | EV10: Faturamento | FC10: Faturamento | FE10: CNPJ: | FI10: Faturamento | FP10: Faturamento | FR10: CNPJ: | FV10: Faturamento | GC10: Faturamento | GE10: CNPJ: | GI10: Faturamento
B12: Compra | C12: 45813 | D12: Razão | E12: CELL SOLLUTION | F12: 250605154601006 | G12: 104 | H12: Compra | I12: 13749.56 | J12: 2 | K12: PIX | L12: =I13*5% -> 687.478 | M12: PAGO | O12: Compra | Q12: Razão | U12: Compra | Y12: =V13*5% -> 0 | AB12: Compra | AD12: Razão | AI12: Compra | AM12: =AJ13*5% -> 0 | AP12: Compra | AR12: Razão | AV12: Compra | AY12: =AW13*2.5% -> 0 | BC12: Compra | BE12: Razão | BI12: Compra | BL12: =BJ13*2.5% -> 0 | BP12: Compra | BR12: Razão | BV12: Compra | BY12: =BW13*2.5% -> 0 | CC12: Compra | CE12: Razão | CI12: Compra | CL12: =CJ13*2.5% -> 0 | CP12: Compra | CR12: Razão | CV12: Compra | CY12: =CW13*2.5% -> 0 | DC12: Compra | DE12: Razão | DI12: Compra | DL12: =DJ13*2.5% -> 0 | DP12: Compra | DR12: Razão | DV12: Compra | DY12: =DW13*2.5% -> 0 | EC12: Compra | EE12: Razão | EI12: Compra | EL12: =EJ13*2.5% -> 0 | EP12: Compra | ER12: Razão | EV12: Compra | EY12: =EW13*2.5% -> 0 | FC12: Compra | FE12: Razão | FI12: Compra | FL12: =FJ13*2.5% -> 0 | FP12: Compra | FR12: Razão | FV12: Compra | FY12: =FW13*2.5% -> 0 | GC12: Compra | GE12: Razão | GI12: Compra | GL12: =GJ13*2.5% -> 0
B13: Faturamento | C13: 45824 | D13: CNPJ: | E13: 20.963.243/0001-01 | H13: Faturamento | I13: 13749.56 | O13: Faturamento | Q13: CNPJ: | U13: Faturamento | AB13: Faturamento | AD13: CNPJ: | AI13: Faturamento | AP13: Faturamento | AR13: CNPJ: | AV13: Faturamento | BC13: Faturamento | BE13: CNPJ: | BI13: Faturamento | BP13: Faturamento | BR13: CNPJ: | BV13: Faturamento | CC13: Faturamento | CE13: CNPJ: | CI13: Faturamento | CP13: Faturamento | CR13: CNPJ: | CV13: Faturamento | DC13: Faturamento | DE13: CNPJ: | DI13: Faturamento | DP13: Faturamento | DR13: CNPJ: | DV13: Faturamento | EC13: Faturamento | EE13: CNPJ: | EI13: Faturamento | EP13: Faturamento | ER13: CNPJ: | EV13: Faturamento | FC13: Faturamento | FE13: CNPJ: | FI13: Faturamento | FP13: Faturamento | FR13: CNPJ: | FV13: Faturamento | GC13: Faturamento | GE13: CNPJ: | GI13: Faturamento
B15: Compra | C15: 45813 | D15: Razão | E15: CELL SOLLUTION | F15: 250605154107945 | G15: 1465 | H15: Compra | I15: 6256.2 | J15: 2 | K15: PIX | L15: =I16*5% -> 312.81 | M15: PAGO | O15: Compra | Q15: Razão | U15: Compra | Y15: =V16*5% -> 0 | AB15: Compra | AD15: Razão | AI15: Compra | AM15: =AJ16*5% -> 0 | AP15: Compra | AR15: Razão | AV15: Compra | AY15: =AW16*2.5% -> 0 | BC15: Compra | BE15: Razão | BI15: Compra | BL15: =BJ16*2.5% -> 0 | BP15: Compra | BR15: Razão | BV15: Compra | BY15: =BW16*2.5% -> 0 | CC15: Compra | CE15: Razão | CI15: Compra | CL15: =CJ16*2.5% -> 0 | CP15: Compra | CR15: Razão | CV15: Compra | CY15: =CW16*2.5% -> 0 | DC15: Compra | DE15: Razão | DI15: Compra | DL15: =DJ16*2.5% -> 0 | DP15: Compra | DR15: Razão | DV15: Compra | DY15: =DW16*2.5% -> 0 | EC15: Compra | EE15: Razão | EI15: Compra | EL15: =EJ16*2.5% -> 0 | EP15: Compra | ER15: Razão | EV15: Compra | EY15: =EW16*2.5% -> 0 | FC15: Compra | FE15: Razão | FI15: Compra | FL15: =FJ16*2.5% -> 0 | FP15: Compra | FR15: Razão | FV15: Compra | FY15: =FW16*2.5% -> 0 | GC15: Compra | GE15: Razão | GI15: Compra | GL15: =GJ16*2.5% -> 0
B16: Faturamento | C16: 45824 | D16: CNPJ: | E16: 20.963.243/0001-01 | H16: Faturamento | I16: 6256.2 | O16: Faturamento | Q16: CNPJ: | U16: Faturamento | AB16: Faturamento | AD16: CNPJ: | AI16: Faturamento | AP16: Faturamento | AR16: CNPJ: | AV16: Faturamento | BC16: Faturamento | BE16: CNPJ: | BI16: Faturamento | BP16: Faturamento | BR16: CNPJ: | BV16: Faturamento | CC16: Faturamento | CE16: CNPJ: | CI16: Faturamento | CP16: Faturamento | CR16: CNPJ: | CV16: Faturamento | DC16: Faturamento | DE16: CNPJ: | DI16: Faturamento | DP16: Faturamento | DR16: CNPJ: | DV16: Faturamento | EC16: Faturamento | EE16: CNPJ: | EI16: Faturamento | EP16: Faturamento | ER16: CNPJ: | EV16: Faturamento | FC16: Faturamento | FE16: CNPJ: | FI16: Faturamento | FP16: Faturamento | FR16: CNPJ: | FV16: Faturamento | GC16: Faturamento | GE16: CNPJ: | GI16: Faturamento
B18: Compra | C18: 45832 | D18: Razão | E18: COMERCIAL MARTINS E MARTINS | F18: 250624104438099 | G18: 1471 | H18: Compra | I18: 16124.42 | J18: 2 | K18: PRAZO | L18: =I19*5% -> 806.221 | M18: FATURADO | O18: Compra | Q18: Razão | U18: Compra | Y18: =V19*5% -> 0 | AB18: Compra | AD18: Razão | AI18: Compra | AM18: =AJ19*5% -> 0 | AP18: Compra | AR18: Razão | AV18: Compra | AY18: =AW19*2.5% -> 0 | BC18: Compra | BE18: Razão | BI18: Compra | BL18: =BJ19*2.5% -> 0 | BP18: Compra | BR18: Razão | BV18: Compra | BY18: =BW19*2.5% -> 0 | CC18: Compra | CE18: Razão | CI18: Compra | CL18: =CJ19*2.5% -> 0 | CP18: Compra | CR18: Razão | CV18: Compra | CY18: =CW19*2.5% -> 0 | DC18: Compra | DE18: Razão | DI18: Compra | DL18: =DJ19*2.5% -> 0 | DP18: Compra | DR18: Razão | DV18: Compra | DY18: =DW19*2.5% -> 0 | EC18: Compra | EE18: Razão | EI18: Compra | EL18: =EJ19*2.5% -> 0 | EP18: Compra | ER18: Razão | EV18: Compra | EY18: =EW19*2.5% -> 0 | FC18: Compra | FE18: Razão | FI18: Compra | FL18: =FJ19*2.5% -> 0 | FP18: Compra | FR18: Razão | FV18: Compra | FY18: =FW19*2.5% -> 0 | GC18: Compra | GE18: Razão | GI18: Compra | GL18: =GJ19*2.5% -> 0
B19: Faturamento | C19: 45833 | D19: CNPJ: | E19: 01.679.699/0001-20 | H19: Faturamento | I19: 16124.42 | O19: Faturamento | Q19: CNPJ: | U19: Faturamento | AB19: Faturamento | AD19: CNPJ: | AI19: Faturamento | AP19: Faturamento | AR19: CNPJ: | AV19: Faturamento | BC19: Faturamento | BE19: CNPJ: | BI19: Faturamento | BP19: Faturamento | BR19: CNPJ: | BV19: Faturamento | CC19: Faturamento | CE19: CNPJ: | CI19: Faturamento | CP19: Faturamento | CR19: CNPJ: | CV19: Faturamento | DC19: Faturamento | DE19: CNPJ: | DI19: Faturamento | DP19: Faturamento | DR19: CNPJ: | DV19: Faturamento | EC19: Faturamento | EE19: CNPJ: | EI19: Faturamento | EP19: Faturamento | ER19: CNPJ: | EV19: Faturamento | FC19: Faturamento | FE19: CNPJ: | FI19: Faturamento | FP19: Faturamento | FR19: CNPJ: | FV19: Faturamento | GC19: Faturamento | GE19: CNPJ: | GI19: Faturamento
B21: Compra | D21: Razão | H21: Compra | L21: =I22*5% -> 0 | O21: Compra | Q21: Razão | U21: Compra | Y21: =V22*5% -> 0 | AB21: Compra | AD21: Razão | AI21: Compra | AM21: =AJ22*5% -> 0 | AP21: Compra | AR21: Razão | AV21: Compra | AY21: =AW22*2.5% -> 0 | BC21: Compra | BE21: Razão | BI21: Compra | BL21: =BJ22*2.5% -> 0 | BP21: Compra | BR21: Razão | BV21: Compra | BY21: =BW22*2.5% -> 0 | CC21: Compra | CE21: Razão | CI21: Compra | CL21: =CJ22*2.5% -> 0 | CP21: Compra | CR21: Razão | CV21: Compra | CY21: =CW22*2.5% -> 0 | DC21: Compra | DE21: Razão | DI21: Compra | DL21: =DJ22*2.5% -> 0 | DP21: Compra | DR21: Razão | DV21: Compra | DY21: =DW22*2.5% -> 0 | EC21: Compra | EE21: Razão | EI21: Compra | EL21: =EJ22*2.5% -> 0 | EP21: Compra | ER21: Razão | EV21: Compra | EY21: =EW22*2.5% -> 0 | FC21: Compra | FE21: Razão | FI21: Compra | FL21: =FJ22*2.5% -> 0 | FP21: Compra | FR21: Razão | FV21: Compra | FY21: =FW22*2.5% -> 0 | GC21: Compra | GE21: Razão | GI21: Compra | GL21: =GJ22*2.5% -> 0
B22: Faturamento | D22: CNPJ: | H22: Faturamento | O22: Faturamento | Q22: CNPJ: | U22: Faturamento | AB22: Faturamento | AD22: CNPJ: | AI22: Faturamento | AP22: Faturamento | AR22: CNPJ: | AV22: Faturamento | BC22: Faturamento | BE22: CNPJ: | BI22: Faturamento | BP22: Faturamento | BR22: CNPJ: | BV22: Faturamento | CC22: Faturamento | CE22: CNPJ: | CI22: Faturamento | CP22: Faturamento | CR22: CNPJ: | CV22: Faturamento | DC22: Faturamento | DE22: CNPJ: | DI22: Faturamento | DP22: Faturamento | DR22: CNPJ: | DV22: Faturamento | EC22: Faturamento | EE22: CNPJ: | EI22: Faturamento | EP22: Faturamento | ER22: CNPJ: | EV22: Faturamento | FC22: Faturamento | FE22: CNPJ: | FI22: Faturamento | FP22: Faturamento | FR22: CNPJ: | FV22: Faturamento | GC22: Faturamento | GE22: CNPJ: | GI22: Faturamento
B24: Compra | D24: Razão | H24: Compra | L24: =I25*5% -> 0 | O24: Compra | Q24: Razão | U24: Compra | Y24: =V25*5% -> 0 | AB24: Compra | AD24: Razão | AI24: Compra | AM24: =AJ25*5% -> 0 | AP24: Compra | AR24: Razão | AV24: Compra | AY24: =AW25*2.5% -> 0 | BC24: Compra | BE24: Razão | BI24: Compra | BL24: =BJ25*2.5% -> 0 | BP24: Compra | BR24: Razão | BV24: Compra | BY24: =BW25*2.5% -> 0 | CC24: Compra | CE24: Razão | CI24: Compra | CL24: =CJ25*2.5% -> 0 | CP24: Compra | CR24: Razão | CV24: Compra | CY24: =CW25*2.5% -> 0 | DC24: Compra | DE24: Razão | DI24: Compra | DL24: =DJ25*2.5% -> 0 | DP24: Compra | DR24: Razão | DV24: Compra | DY24: =DW25*2.5% -> 0 | EC24: Compra | EE24: Razão | EI24: Compra | EL24: =EJ25*2.5% -> 0 | EP24: Compra | ER24: Razão | EV24: Compra | EY24: =EW25*2.5% -> 0 | FC24: Compra | FE24: Razão | FI24: Compra | FL24: =FJ25*2.5% -> 0 | FP24: Compra | FR24: Razão | FV24: Compra | FY24: =FW25*2.5% -> 0 | GC24: Compra | GE24: Razão | GI24: Compra | GL24: =GJ25*2.5% -> 0
B25: Faturamento | D25: CNPJ: | H25: Faturamento | O25: Faturamento | Q25: CNPJ: | U25: Faturamento | AB25: Faturamento | AD25: CNPJ: | AI25: Faturamento | AP25: Faturamento | AR25: CNPJ: | AV25: Faturamento | BC25: Faturamento | BE25: CNPJ: | BI25: Faturamento | BP25: Faturamento | BR25: CNPJ: | BV25: Faturamento | CC25: Faturamento | CE25: CNPJ: | CI25: Faturamento | CP25: Faturamento | CR25: CNPJ: | CV25: Faturamento | DC25: Faturamento | DE25: CNPJ: | DI25: Faturamento | DP25: Faturamento | DR25: CNPJ: | DV25: Faturamento | EC25: Faturamento | EE25: CNPJ: | EI25: Faturamento | EP25: Faturamento | ER25: CNPJ: | EV25: Faturamento | FC25: Faturamento | FE25: CNPJ: | FI25: Faturamento | FP25: Faturamento | FR25: CNPJ: | FV25: Faturamento | GC25: Faturamento | GE25: CNPJ: | GI25: Faturamento
B27: Compra | D27: Razão | H27: Compra | L27: =I28*5% -> 0 | O27: Compra | Q27: Razão | U27: Compra | Y27: =V28*5% -> 0 | AB27: Compra | AD27: Razão | AI27: Compra | AM27: =AJ28*5% -> 0 | AP27: Compra | AR27: Razão | AV27: Compra | AY27: =AW28*2.5% -> 0 | BC27: Compra | BE27: Razão | BI27: Compra | BL27: =BJ28*2.5% -> 0 | BP27: Compra | BR27: Razão | BV27: Compra | BY27: =BW28*2.5% -> 0 | CC27: Compra | CE27: Razão | CI27: Compra | CL27: =CJ28*2.5% -> 0 | CP27: Compra | CR27: Razão | CV27: Compra | CY27: =CW28*2.5% -> 0 | DC27: Compra | DE27: Razão | DI27: Compra | DL27: =DJ28*2.5% -> 0 | DP27: Compra | DR27: Razão | DV27: Compra | DY27: =DW28*2.5% -> 0 | EC27: Compra | EE27: Razão | EI27: Compra | EL27: =EJ28*2.5% -> 0 | EP27: Compra | ER27: Razão | EV27: Compra | EY27: =EW28*2.5% -> 0 | FC27: Compra | FE27: Razão | FI27: Compra | FL27: =FJ28*2.5% -> 0 | FP27: Compra | FR27: Razão | FV27: Compra | FY27: =FW28*2.5% -> 0 | GC27: Compra | GE27: Razão | GI27: Compra | GL27: =GJ28*2.5% -> 0
B28: Faturamento | D28: CNPJ: | H28: Faturamento | O28: Faturamento | Q28: CNPJ: | U28: Faturamento | AB28: Faturamento | AD28: CNPJ: | AI28: Faturamento | AP28: Faturamento | AR28: CNPJ: | AV28: Faturamento | BC28: Faturamento | BE28: CNPJ: | BI28: Faturamento | BP28: Faturamento | BR28: CNPJ: | BV28: Faturamento | CC28: Faturamento | CE28: CNPJ: | CI28: Faturamento | CP28: Faturamento | CR28: CNPJ: | CV28: Faturamento | DC28: Faturamento | DE28: CNPJ: | DI28: Faturamento | DP28: Faturamento | DR28: CNPJ: | DV28: Faturamento | EC28: Faturamento | EE28: CNPJ: | EI28: Faturamento | EP28: Faturamento | ER28: CNPJ: | EV28: Faturamento | FC28: Faturamento | FE28: CNPJ: | FI28: Faturamento | FP28: Faturamento | FR28: CNPJ: | FV28: Faturamento | GC28: Faturamento | GE28: CNPJ: | GI28: Faturamento
B30: Compra | D30: Razão | H30: Compra | L30: =I31*5% -> 0 | O30: Compra | Q30: Razão | U30: Compra | Y30: =V31*5% -> 0 | AB30: Compra | AD30: Razão | AI30: Compra | AM30: =AJ31*5% -> 0 | AP30: Compra | AR30: Razão | AV30: Compra | AY30: =AW31*2.5% -> 0 | BC30: Compra | BE30: Razão | BI30: Compra | BL30: =BJ31*2.5% -> 0 | BP30: Compra | BR30: Razão | BV30: Compra | BY30: =BW31*2.5% -> 0 | CC30: Compra | CE30: Razão | CI30: Compra | CL30: =CJ31*2.5% -> 0 | CP30: Compra | CR30: Razão | CV30: Compra | CY30: =CW31*2.5% -> 0 | DC30: Compra | DE30: Razão | DI30: Compra | DL30: =DJ31*2.5% -> 0 | DP30: Compra | DR30: Razão | DV30: Compra | DY30: =DW31*2.5% -> 0 | EC30: Compra | EE30: Razão | EI30: Compra | EL30: =EJ31*2.5% -> 0 | EP30: Compra | ER30: Razão | EV30: Compra | EY30: =EW31*2.5% -> 0 | FC30: Compra | FE30: Razão | FI30: Compra | FL30: =FJ31*2.5% -> 0 | FP30: Compra | FR30: Razão | FV30: Compra | FY30: =FW31*2.5% -> 0 | GC30: Compra | GE30: Razão | GI30: Compra | GL30: =GJ31*2.5% -> 0
B31: Faturamento | D31: CNPJ: | H31: Faturamento | O31: Faturamento | Q31: CNPJ: | U31: Faturamento | AB31: Faturamento | AD31: CNPJ: | AI31: Faturamento | AP31: Faturamento | AR31: CNPJ: | AV31: Faturamento | BC31: Faturamento | BE31: CNPJ: | BI31: Faturamento | BP31: Faturamento | BR31: CNPJ: | BV31: Faturamento | CC31: Faturamento | CE31: CNPJ: | CI31: Faturamento | CP31: Faturamento | CR31: CNPJ: | CV31: Faturamento | DC31: Faturamento | DE31: CNPJ: | DI31: Faturamento | DP31: Faturamento | DR31: CNPJ: | DV31: Faturamento | EC31: Faturamento | EE31: CNPJ: | EI31: Faturamento | EP31: Faturamento | ER31: CNPJ: | EV31: Faturamento | FC31: Faturamento | FE31: CNPJ: | FI31: Faturamento | FP31: Faturamento | FR31: CNPJ: | FV31: Faturamento | GC31: Faturamento | GE31: CNPJ: | GI31: Faturamento
B33: Compra | D33: Razão | H33: Compra | L33: =I34*5% -> 0 | O33: Compra | Q33: Razão | U33: Compra | Y33: =V34*5% -> 0 | AB33: Compra | AD33: Razão | AI33: Compra | AM33: =AJ34*5% -> 0 | AP33: Compra | AR33: Razão | AV33: Compra | AY33: =AW34*2.5% -> 0 | BC33: Compra | BE33: Razão | BI33: Compra | BL33: =BJ34*2.5% -> 0 | BP33: Compra | BR33: Razão | BV33: Compra | BY33: =BW34*2.5% -> 0 | CC33: Compra | CE33: Razão | CI33: Compra | CL33: =CJ34*2.5% -> 0 | CP33: Compra | CR33: Razão | CV33: Compra | CY33: =CW34*2.5% -> 0 | DC33: Compra | DE33: Razão | DI33: Compra | DL33: =DJ34*2.5% -> 0 | DP33: Compra | DR33: Razão | DV33: Compra | DY33: =DW34*2.5% -> 0 | EC33: Compra | EE33: Razão | EI33: Compra | EL33: =EJ34*2.5% -> 0 | EP33: Compra | ER33: Razão | EV33: Compra | EY33: =EW34*2.5% -> 0 | FC33: Compra | FE33: Razão | FI33: Compra | FL33: =FJ34*2.5% -> 0 | FP33: Compra | FR33: Razão | FV33: Compra | FY33: =FW34*2.5% -> 0 | GC33: Compra | GE33: Razão | GI33: Compra | GL33: =GJ34*2.5% -> 0
B34: Faturamento | D34: CNPJ: | H34: Faturamento | O34: Faturamento | Q34: CNPJ: | U34: Faturamento | AB34: Faturamento | AD34: CNPJ: | AI34: Faturamento | AP34: Faturamento | AR34: CNPJ: | AV34: Faturamento | BC34: Faturamento | BE34: CNPJ: | BI34: Faturamento | BP34: Faturamento | BR34: CNPJ: | BV34: Faturamento | CC34: Faturamento | CE34: CNPJ: | CI34: Faturamento | CP34: Faturamento | CR34: CNPJ: | CV34: Faturamento | DC34: Faturamento | DE34: CNPJ: | DI34: Faturamento | DP34: Faturamento | DR34: CNPJ: | DV34: Faturamento | EC34: Faturamento | EE34: CNPJ: | EI34: Faturamento | EP34: Faturamento | ER34: CNPJ: | EV34: Faturamento | FC34: Faturamento | FE34: CNPJ: | FI34: Faturamento | FP34: Faturamento | FR34: CNPJ: | FV34: Faturamento | GC34: Faturamento | GE34: CNPJ: | GI34: Faturamento
B36: Compra | D36: Razão | H36: Compra | L36: =I37*5% -> 0 | O36: Compra | Q36: Razão | U36: Compra | Y36: =V37*5% -> 0 | AB36: Compra | AD36: Razão | AI36: Compra | AM36: =AJ37*5% -> 0 | AP36: Compra | AR36: Razão | AV36: Compra | AY36: =AW37*2.5% -> 0 | BC36: Compra | BE36: Razão | BI36: Compra | BL36: =BJ37*2.5% -> 0 | BP36: Compra | BR36: Razão | BV36: Compra | BY36: =BW37*2.5% -> 0 | CC36: Compra | CE36: Razão | CI36: Compra | CL36: =CJ37*2.5% -> 0 | CP36: Compra | CR36: Razão | CV36: Compra | CY36: =CW37*2.5% -> 0 | DC36: Compra | DE36: Razão | DI36: Compra | DL36: =DJ37*2.5% -> 0 | DP36: Compra | DR36: Razão | DV36: Compra | DY36: =DW37*2.5% -> 0 | EC36: Compra | EE36: Razão | EI36: Compra | EL36: =EJ37*2.5% -> 0 | EP36: Compra | ER36: Razão | EV36: Compra | EY36: =EW37*2.5% -> 0 | FC36: Compra | FE36: Razão | FI36: Compra | FL36: =FJ37*2.5% -> 0 | FP36: Compra | FR36: Razão | FV36: Compra | FY36: =FW37*2.5% -> 0 | GC36: Compra | GE36: Razão | GI36: Compra | GL36: =GJ37*2.5% -> 0
B37: Faturamento | D37: CNPJ: | H37: Faturamento | O37: Faturamento | Q37: CNPJ: | U37: Faturamento | AB37: Faturamento | AD37: CNPJ: | AI37: Faturamento | AP37: Faturamento | AR37: CNPJ: | AV37: Faturamento | BC37: Faturamento | BE37: CNPJ: | BI37: Faturamento | BP37: Faturamento | BR37: CNPJ: | BV37: Faturamento | CC37: Faturamento | CE37: CNPJ: | CI37: Faturamento | CP37: Faturamento | CR37: CNPJ: | CV37: Faturamento | DC37: Faturamento | DE37: CNPJ: | DI37: Faturamento | DP37: Faturamento | DR37: CNPJ: | DV37: Faturamento | EC37: Faturamento | EE37: CNPJ: | EI37: Faturamento | EP37: Faturamento | ER37: CNPJ: | EV37: Faturamento | FC37: Faturamento | FE37: CNPJ: | FI37: Faturamento | FP37: Faturamento | FR37: CNPJ: | FV37: Faturamento | GC37: Faturamento | GE37: CNPJ: | GI37: Faturamento
B39: Compra | D39: Razão | H39: Compra | L39: =I40*5% -> 0 | O39: Compra | Q39: Razão | U39: Compra | Y39: =V40*5% -> 0 | AB39: Compra | AD39: Razão | AI39: Compra | AM39: =AJ40*5% -> 0 | AP39: Compra | AR39: Razão | AV39: Compra | AY39: =AW40*2.5% -> 0 | BC39: Compra | BE39: Razão | BI39: Compra | BL39: =BJ40*2.5% -> 0 | BP39: Compra | BR39: Razão | BV39: Compra | BY39: =BW40*2.5% -> 0 | CC39: Compra | CE39: Razão | CI39: Compra | CL39: =CJ40*2.5% -> 0 | CP39: Compra | CR39: Razão | CV39: Compra | CY39: =CW40*2.5% -> 0 | DC39: Compra | DE39: Razão | DI39: Compra | DL39: =DJ40*2.5% -> 0 | DP39: Compra | DR39: Razão | DV39: Compra | DY39: =DW40*2.5% -> 0 | EC39: Compra | EE39: Razão | EI39: Compra | EL39: =EJ40*2.5% -> 0 | EP39: Compra | ER39: Razão | EV39: Compra | EY39: =EW40*2.5% -> 0 | FC39: Compra | FE39: Razão | FI39: Compra | FL39: =FJ40*2.5% -> 0 | FP39: Compra | FR39: Razão | FV39: Compra | FY39: =FW40*2.5% -> 0 | GC39: Compra | GE39: Razão | GI39: Compra | GL39: =GJ40*2.5% -> 0
B40: Faturamento | D40: CNPJ: | H40: Faturamento | O40: Faturamento | Q40: CNPJ: | U40: Faturamento | AB40: Faturamento | AD40: CNPJ: | AI40: Faturamento | AP40: Faturamento | AR40: CNPJ: | AV40: Faturamento | BC40: Faturamento | BE40: CNPJ: | BI40: Faturamento | BP40: Faturamento | BR40: CNPJ: | BV40: Faturamento | CC40: Faturamento | CE40: CNPJ: | CI40: Faturamento | CP40: Faturamento | CR40: CNPJ: | CV40: Faturamento | DC40: Faturamento | DE40: CNPJ: | DI40: Faturamento | DP40: Faturamento | DR40: CNPJ: | DV40: Faturamento | EC40: Faturamento | EE40: CNPJ: | EI40: Faturamento | EP40: Faturamento | ER40: CNPJ: | EV40: Faturamento | FC40: Faturamento | FE40: CNPJ: | FI40: Faturamento | FP40: Faturamento | FR40: CNPJ: | FV40: Faturamento | GC40: Faturamento | GE40: CNPJ: | GI40: Faturamento
B42: Compra | D42: Razão | H42: Compra | L42: =I43*5% -> 0 | O42: Compra | Q42: Razão | U42: Compra | Y42: =V43*5% -> 0 | AB42: Compra | AD42: Razão | AI42: Compra | AM42: =AJ43*5% -> 0 | AP42: Compra | AR42: Razão | AV42: Compra | AY42: =AW43*2.5% -> 0 | BC42: Compra | BE42: Razão | BI42: Compra | BL42: =BJ43*2.5% -> 0 | BP42: Compra | BR42: Razão | BV42: Compra | BY42: =BW43*2.5% -> 0 | CC42: Compra | CE42: Razão | CI42: Compra | CL42: =CJ43*2.5% -> 0 | CP42: Compra | CR42: Razão | CV42: Compra | CY42: =CW43*2.5% -> 0 | DC42: Compra | DE42: Razão | DI42: Compra | DL42: =DJ43*2.5% -> 0 | DP42: Compra | DR42: Razão | DV42: Compra | DY42: =DW43*2.5% -> 0 | EC42: Compra | EE42: Razão | EI42: Compra | EL42: =EJ43*2.5% -> 0 | EP42: Compra | ER42: Razão | EV42: Compra | EY42: =EW43*2.5% -> 0 | FC42: Compra | FE42: Razão | FI42: Compra | FL42: =FJ43*2.5% -> 0 | FP42: Compra | FR42: Razão | FV42: Compra | FY42: =FW43*2.5% -> 0 | GC42: Compra | GE42: Razão | GI42: Compra | GL42: =GJ43*2.5% -> 0
B43: Faturamento | D43: CNPJ: | H43: Faturamento | O43: Faturamento | Q43: CNPJ: | U43: Faturamento | AB43: Faturamento | AD43: CNPJ: | AI43: Faturamento | AP43: Faturamento | AR43: CNPJ: | AV43: Faturamento | BC43: Faturamento | BE43: CNPJ: | BI43: Faturamento | BP43: Faturamento | BR43: CNPJ: | BV43: Faturamento | CC43: Faturamento | CE43: CNPJ: | CI43: Faturamento | CP43: Faturamento | CR43: CNPJ: | CV43: Faturamento | DC43: Faturamento | DE43: CNPJ: | DI43: Faturamento | DP43: Faturamento | DR43: CNPJ: | DV43: Faturamento | EC43: Faturamento | EE43: CNPJ: | EI43: Faturamento | EP43: Faturamento | ER43: CNPJ: | EV43: Faturamento | FC43: Faturamento | FE43: CNPJ: | FI43: Faturamento | FP43: Faturamento | FR43: CNPJ: | FV43: Faturamento | GC43: Faturamento | GE43: CNPJ: | GI43: Faturamento
B45: Compra | D45: Razão | H45: Compra | L45: =I46*5% -> 0 | O45: Compra | Q45: Razão | U45: Compra | Y45: =V46*5% -> 0 | AB45: Compra | AD45: Razão | AI45: Compra | AM45: =AJ46*5% -> 0 | AP45: Compra | AR45: Razão | AV45: Compra | AY45: =AW46*2.5% -> 0 | BC45: Compra | BE45: Razão | BI45: Compra | BL45: =BJ46*2.5% -> 0 | BP45: Compra | BR45: Razão | BV45: Compra | BY45: =BW46*2.5% -> 0 | CC45: Compra | CE45: Razão | CI45: Compra | CL45: =CJ46*2.5% -> 0 | CP45: Compra | CR45: Razão | CV45: Compra | CY45: =CW46*2.5% -> 0 | DC45: Compra | DE45: Razão | DI45: Compra | DL45: =DJ46*2.5% -> 0 | DP45: Compra | DR45: Razão | DV45: Compra | DY45: =DW46*2.5% -> 0 | EC45: Compra | EE45: Razão | EI45: Compra | EL45: =EJ46*2.5% -> 0 | EP45: Compra | ER45: Razão | EV45: Compra | EY45: =EW46*2.5% -> 0 | FC45: Compra | FE45: Razão | FI45: Compra | FL45: =FJ46*2.5% -> 0 | FP45: Compra | FR45: Razão | FV45: Compra | FY45: =FW46*2.5% -> 0 | GC45: Compra | GE45: Razão | GI45: Compra | GL45: =GJ46*2.5% -> 0
B46: Faturamento | D46: CNPJ: | H46: Faturamento | O46: Faturamento | Q46: CNPJ: | U46: Faturamento | AB46: Faturamento | AD46: CNPJ: | AI46: Faturamento | AP46: Faturamento | AR46: CNPJ: | AV46: Faturamento | BC46: Faturamento | BE46: CNPJ: | BI46: Faturamento | BP46: Faturamento | BR46: CNPJ: | BV46: Faturamento | CC46: Faturamento | CE46: CNPJ: | CI46: Faturamento | CP46: Faturamento | CR46: CNPJ: | CV46: Faturamento | DC46: Faturamento | DE46: CNPJ: | DI46: Faturamento | DP46: Faturamento | DR46: CNPJ: | DV46: Faturamento | EC46: Faturamento | EE46: CNPJ: | EI46: Faturamento | EP46: Faturamento | ER46: CNPJ: | EV46: Faturamento | FC46: Faturamento | FE46: CNPJ: | FI46: Faturamento | FP46: Faturamento | FR46: CNPJ: | FV46: Faturamento | GC46: Faturamento | GE46: CNPJ: | GI46: Faturamento
B48: Compra | D48: Razão | H48: Compra | L48: =I49*5% -> 0 | O48: Compra | Q48: Razão | U48: Compra | Y48: =V49*5% -> 0 | AB48: Compra | AD48: Razão | AI48: Compra | AM48: =AJ49*5% -> 0 | AP48: Compra | AR48: Razão | AV48: Compra | AY48: =AW49*2.5% -> 0 | BC48: Compra | BE48: Razão | BI48: Compra | BL48: =BJ49*2.5% -> 0 | BP48: Compra | BR48: Razão | BV48: Compra | BY48: =BW49*2.5% -> 0 | CC48: Compra | CE48: Razão | CI48: Compra | CL48: =CJ49*2.5% -> 0 | CP48: Compra | CR48: Razão | CV48: Compra | CY48: =CW49*2.5% -> 0 | DC48: Compra | DE48: Razão | DI48: Compra | DL48: =DJ49*2.5% -> 0 | DP48: Compra | DR48: Razão | DV48: Compra | DY48: =DW49*2.5% -> 0 | EC48: Compra | EE48: Razão | EI48: Compra | EL48: =EJ49*2.5% -> 0 | EP48: Compra | ER48: Razão | EV48: Compra | EY48: =EW49*2.5% -> 0 | FC48: Compra | FE48: Razão | FI48: Compra | FL48: =FJ49*2.5% -> 0 | FP48: Compra | FR48: Razão | FV48: Compra | FY48: =FW49*2.5% -> 0 | GC48: Compra | GE48: Razão | GI48: Compra | GL48: =GJ49*2.5% -> 0
B49: Faturamento | D49: CNPJ: | H49: Faturamento | O49: Faturamento | Q49: CNPJ: | U49: Faturamento | AB49: Faturamento | AD49: CNPJ: | AI49: Faturamento | AP49: Faturamento | AR49: CNPJ: | AV49: Faturamento | BC49: Faturamento | BE49: CNPJ: | BI49: Faturamento | BP49: Faturamento | BR49: CNPJ: | BV49: Faturamento | CC49: Faturamento | CE49: CNPJ: | CI49: Faturamento | CP49: Faturamento | CR49: CNPJ: | CV49: Faturamento | DC49: Faturamento | DE49: CNPJ: | DI49: Faturamento | DP49: Faturamento | DR49: CNPJ: | DV49: Faturamento | EC49: Faturamento | EE49: CNPJ: | EI49: Faturamento | EP49: Faturamento | ER49: CNPJ: | EV49: Faturamento | FC49: Faturamento | FE49: CNPJ: | FI49: Faturamento | FP49: Faturamento | FR49: CNPJ: | FV49: Faturamento | GC49: Faturamento | GE49: CNPJ: | GI49: Faturamento
B51: Compra | D51: Razão | H51: Compra | L51: =I52*5% -> 0 | O51: Compra | Q51: Razão | U51: Compra | Y51: =V52*5% -> 0 | AB51: Compra | AD51: Razão | AI51: Compra | AM51: =AJ52*5% -> 0 | AP51: Compra | AR51: Razão | AV51: Compra | AY51: =AW52*2.5% -> 0 | BC51: Compra | BE51: Razão | BI51: Compra | BL51: =BJ52*2.5% -> 0 | BP51: Compra | BR51: Razão | BV51: Compra | BY51: =BW52*2.5% -> 0 | CC51: Compra | CE51: Razão | CI51: Compra | CL51: =CJ52*2.5% -> 0 | CP51: Compra | CR51: Razão | CV51: Compra | CY51: =CW52*2.5% -> 0 | DC51: Compra | DE51: Razão | DI51: Compra | DL51: =DJ52*2.5% -> 0 | DP51: Compra | DR51: Razão | DV51: Compra | DY51: =DW52*2.5% -> 0 | EC51: Compra | EE51: Razão | EI51: Compra | EL51: =EJ52*2.5% -> 0 | EP51: Compra | ER51: Razão | EV51: Compra | EY51: =EW52*2.5% -> 0 | FC51: Compra | FE51: Razão | FI51: Compra | FL51: =FJ52*2.5% -> 0 | FP51: Compra | FR51: Razão | FV51: Compra | FY51: =FW52*2.5% -> 0 | GC51: Compra | GE51: Razão | GI51: Compra | GL51: =GJ52*2.5% -> 0
B52: Faturamento | D52: CNPJ: | H52: Faturamento | O52: Faturamento | Q52: CNPJ: | U52: Faturamento | AB52: Faturamento | AD52: CNPJ: | AI52: Faturamento | AP52: Faturamento | AR52: CNPJ: | AV52: Faturamento | BC52: Faturamento | BE52: CNPJ: | BI52: Faturamento | BP52: Faturamento | BR52: CNPJ: | BV52: Faturamento | CC52: Faturamento | CE52: CNPJ: | CI52: Faturamento | CP52: Faturamento | CR52: CNPJ: | CV52: Faturamento | DC52: Faturamento | DE52: CNPJ: | DI52: Faturamento | DP52: Faturamento | DR52: CNPJ: | DV52: Faturamento | EC52: Faturamento | EE52: CNPJ: | EI52: Faturamento | EP52: Faturamento | ER52: CNPJ: | EV52: Faturamento | FC52: Faturamento | FE52: CNPJ: | FI52: Faturamento | FP52: Faturamento | FR52: CNPJ: | FV52: Faturamento | GC52: Faturamento | GE52: CNPJ: | GI52: Faturamento
B54: Compra | D54: Razão | H54: Compra | L54: =I55*5% -> 0 | O54: Compra | Q54: Razão | U54: Compra | Y54: =V55*5% -> 0 | AB54: Compra | AD54: Razão | AI54: Compra | AM54: =AJ55*5% -> 0 | AP54: Compra | AR54: Razão | AV54: Compra | AY54: =AW55*2.5% -> 0 | BC54: Compra | BE54: Razão | BI54: Compra | BL54: =BJ55*2.5% -> 0 | BP54: Compra | BR54: Razão | BV54: Compra | BY54: =BW55*2.5% -> 0 | CC54: Compra | CE54: Razão | CI54: Compra | CL54: =CJ55*2.5% -> 0 | CP54: Compra | CR54: Razão | CV54: Compra | CY54: =CW55*2.5% -> 0 | DC54: Compra | DE54: Razão | DI54: Compra | DL54: =DJ55*2.5% -> 0 | DP54: Compra | DR54: Razão | DV54: Compra | DY54: =DW55*2.5% -> 0 | EC54: Compra | EE54: Razão | EI54: Compra | EL54: =EJ55*2.5% -> 0 | EP54: Compra | ER54: Razão | EV54: Compra | EY54: =EW55*2.5% -> 0 | FC54: Compra | FE54: Razão | FI54: Compra | FL54: =FJ55*2.5% -> 0 | FP54: Compra | FR54: Razão | FV54: Compra | FY54: =FW55*2.5% -> 0 | GC54: Compra | GE54: Razão | GI54: Compra | GL54: =GJ55*2.5% -> 0
B55: Faturamento | D55: CNPJ: | H55: Faturamento | O55: Faturamento | Q55: CNPJ: | U55: Faturamento | AB55: Faturamento | AD55: CNPJ: | AI55: Faturamento | AP55: Faturamento | AR55: CNPJ: | AV55: Faturamento | BC55: Faturamento | BE55: CNPJ: | BI55: Faturamento | BP55: Faturamento | BR55: CNPJ: | BV55: Faturamento | CC55: Faturamento | CE55: CNPJ: | CI55: Faturamento | CP55: Faturamento | CR55: CNPJ: | CV55: Faturamento | DC55: Faturamento | DE55: CNPJ: | DI55: Faturamento | DP55: Faturamento | DR55: CNPJ: | DV55: Faturamento | EC55: Faturamento | EE55: CNPJ: | EI55: Faturamento | EP55: Faturamento | ER55: CNPJ: | EV55: Faturamento | FC55: Faturamento | FE55: CNPJ: | FI55: Faturamento | FP55: Faturamento | FR55: CNPJ: | FV55: Faturamento | GC55: Faturamento | GE55: CNPJ: | GI55: Faturamento
B57: Compra | D57: Razão | H57: Compra | L57: =I58*5% -> 0 | O57: Compra | Q57: Razão | U57: Compra | Y57: =V58*5% -> 0 | AB57: Compra | AD57: Razão | AI57: Compra | AM57: =AJ58*5% -> 0 | AP57: Compra | AR57: Razão | AV57: Compra | AY57: =AW58*2.5% -> 0 | BC57: Compra | BE57: Razão | BI57: Compra | BL57: =BJ58*2.5% -> 0 | BP57: Compra | BR57: Razão | BV57: Compra | BY57: =BW58*2.5% -> 0 | CC57: Compra | CE57: Razão | CI57: Compra | CL57: =CJ58*2.5% -> 0 | CP57: Compra | CR57: Razão | CV57: Compra | CY57: =CW58*2.5% -> 0 | DC57: Compra | DE57: Razão | DI57: Compra | DL57: =DJ58*2.5% -> 0 | DP57: Compra | DR57: Razão | DV57: Compra | DY57: =DW58*2.5% -> 0 | EC57: Compra | EE57: Razão | EI57: Compra | EL57: =EJ58*2.5% -> 0 | EP57: Compra | ER57: Razão | EV57: Compra | EY57: =EW58*2.5% -> 0 | FC57: Compra | FE57: Razão | FI57: Compra | FL57: =FJ58*2.5% -> 0 | FP57: Compra | FR57: Razão | FV57: Compra | FY57: =FW58*2.5% -> 0 | GC57: Compra | GE57: Razão | GI57: Compra | GL57: =GJ58*2.5% -> 0
B58: Faturamento | D58: CNPJ: | H58: Faturamento | O58: Faturamento | Q58: CNPJ: | U58: Faturamento | AB58: Faturamento | AD58: CNPJ: | AI58: Faturamento | AP58: Faturamento | AR58: CNPJ: | AV58: Faturamento | BC58: Faturamento | BE58: CNPJ: | BI58: Faturamento | BP58: Faturamento | BR58: CNPJ: | BV58: Faturamento | CC58: Faturamento | CE58: CNPJ: | CI58: Faturamento | CP58: Faturamento | CR58: CNPJ: | CV58: Faturamento | DC58: Faturamento | DE58: CNPJ: | DI58: Faturamento | DP58: Faturamento | DR58: CNPJ: | DV58: Faturamento | EC58: Faturamento | EE58: CNPJ: | EI58: Faturamento | EP58: Faturamento | ER58: CNPJ: | EV58: Faturamento | FC58: Faturamento | FE58: CNPJ: | FI58: Faturamento | FP58: Faturamento | FR58: CNPJ: | FV58: Faturamento | GC58: Faturamento | GE58: CNPJ: | GI58: Faturamento
B60: Compra | D60: Razão | H60: Compra | L60: =I61*5% -> 0 | O60: Compra | Q60: Razão | U60: Compra | Y60: =V61*5% -> 0 | AB60: Compra | AD60: Razão | AI60: Compra | AM60: =AJ61*5% -> 0 | AP60: Compra | AR60: Razão | AV60: Compra | AY60: =AW61*2.5% -> 0 | BC60: Compra | BE60: Razão | BI60: Compra | BL60: =BJ61*2.5% -> 0 | BP60: Compra | BR60: Razão | BV60: Compra | BY60: =BW61*2.5% -> 0 | CC60: Compra | CE60: Razão | CI60: Compra | CL60: =CJ61*2.5% -> 0 | CP60: Compra | CR60: Razão | CV60: Compra | CY60: =CW61*2.5% -> 0 | DC60: Compra | DE60: Razão | DI60: Compra | DL60: =DJ61*2.5% -> 0 | DP60: Compra | DR60: Razão | DV60: Compra | DY60: =DW61*2.5% -> 0 | EC60: Compra | EE60: Razão | EI60: Compra | EL60: =EJ61*2.5% -> 0 | EP60: Compra | ER60: Razão | EV60: Compra | EY60: =EW61*2.5% -> 0 | FC60: Compra | FE60: Razão | FI60: Compra | FL60: =FJ61*2.5% -> 0 | FP60: Compra | FR60: Razão | FV60: Compra | FY60: =FW61*2.5% -> 0 | GC60: Compra | GE60: Razão | GI60: Compra | GL60: =GJ61*2.5% -> 0
B61: Faturamento | D61: CNPJ: | H61: Faturamento | O61: Faturamento | Q61: CNPJ: | U61: Faturamento | AB61: Faturamento | AD61: CNPJ: | AI61: Faturamento | AP61: Faturamento | AR61: CNPJ: | AV61: Faturamento | BC61: Faturamento | BE61: CNPJ: | BI61: Faturamento | BP61: Faturamento | BR61: CNPJ: | BV61: Faturamento | CC61: Faturamento | CE61: CNPJ: | CI61: Faturamento | CP61: Faturamento | CR61: CNPJ: | CV61: Faturamento | DC61: Faturamento | DE61: CNPJ: | DI61: Faturamento | DP61: Faturamento | DR61: CNPJ: | DV61: Faturamento | EC61: Faturamento | EE61: CNPJ: | EI61: Faturamento | EP61: Faturamento | ER61: CNPJ: | EV61: Faturamento | FC61: Faturamento | FE61: CNPJ: | FI61: Faturamento | FP61: Faturamento | FR61: CNPJ: | FV61: Faturamento | GC61: Faturamento | GE61: CNPJ: | GI61: Faturamento
AP63: Compra | AR63: Razão | AV63: Compra | AY63: =AW64*2.5% -> 0 | BC63: Compra | BE63: Razão | BI63: Compra | BL63: =BJ64*2.5% -> 0 | BP63: Compra | BR63: Razão | BV63: Compra | BY63: =BW64*2.5% -> 0 | CC63: Compra | CE63: Razão | CI63: Compra | CL63: =CJ64*2.5% -> 0 | CP63: Compra | CR63: Razão | CV63: Compra | CY63: =CW64*2.5% -> 0 | DC63: Compra | DE63: Razão | DI63: Compra | DL63: =DJ64*2.5% -> 0 | DP63: Compra | DR63: Razão | DV63: Compra | DY63: =DW64*2.5% -> 0 | EC63: Compra | EE63: Razão | EI63: Compra | EL63: =EJ64*2.5% -> 0 | EP63: Compra | ER63: Razão | EV63: Compra | EY63: =EW64*2.5% -> 0 | FC63: Compra | FE63: Razão | FI63: Compra | FL63: =FJ64*2.5% -> 0 | FP63: Compra | FR63: Razão | FV63: Compra | FY63: =FW64*2.5% -> 0 | GC63: Compra | GE63: Razão | GI63: Compra | GL63: =GJ64*2.5% -> 0
AP64: Faturamento | AR64: CNPJ: | AV64: Faturamento | BC64: Faturamento | BE64: CNPJ: | BI64: Faturamento | BP64: Faturamento | BR64: CNPJ: | BV64: Faturamento | CC64: Faturamento | CE64: CNPJ: | CI64: Faturamento | CP64: Faturamento | CR64: CNPJ: | CV64: Faturamento | DC64: Faturamento | DE64: CNPJ: | DI64: Faturamento | DP64: Faturamento | DR64: CNPJ: | DV64: Faturamento | EC64: Faturamento | EE64: CNPJ: | EI64: Faturamento | EP64: Faturamento | ER64: CNPJ: | EV64: Faturamento | FC64: Faturamento | FE64: CNPJ: | FI64: Faturamento | FP64: Faturamento | FR64: CNPJ: | FV64: Faturamento | GC64: Faturamento | GE64: CNPJ: | GI64: Faturamento
AP66: Compra | AR66: Razão | AV66: Compra | AY66: =AW67*2.5% -> 0 | BC66: Compra | BE66: Razão | BI66: Compra | BL66: =BJ67*2.5% -> 0 | BP66: Compra | BR66: Razão | BV66: Compra | BY66: =BW67*2.5% -> 0 | CC66: Compra | CE66: Razão | CI66: Compra | CL66: =CJ67*2.5% -> 0 | CP66: Compra | CR66: Razão | CV66: Compra | CY66: =CW67*2.5% -> 0 | DC66: Compra | DE66: Razão | DI66: Compra | DL66: =DJ67*2.5% -> 0 | DP66: Compra | DR66: Razão | DV66: Compra | DY66: =DW67*2.5% -> 0 | EC66: Compra | EE66: Razão | EI66: Compra | EL66: =EJ67*2.5% -> 0 | EP66: Compra | ER66: Razão | EV66: Compra | EY66: =EW67*2.5% -> 0 | FC66: Compra | FE66: Razão | FI66: Compra | FL66: =FJ67*2.5% -> 0 | FP66: Compra | FR66: Razão | FV66: Compra | FY66: =FW67*2.5% -> 0 | GC66: Compra | GE66: Razão | GI66: Compra | GL66: =GJ67*2.5% -> 0
AP67: Faturamento | AR67: CNPJ: | AV67: Faturamento | BC67: Faturamento | BE67: CNPJ: | BI67: Faturamento | BP67: Faturamento | BR67: CNPJ: | BV67: Faturamento | CC67: Faturamento | CE67: CNPJ: | CI67: Faturamento | CP67: Faturamento | CR67: CNPJ: | CV67: Faturamento | DC67: Faturamento | DE67: CNPJ: | DI67: Faturamento | DP67: Faturamento | DR67: CNPJ: | DV67: Faturamento | EC67: Faturamento | EE67: CNPJ: | EI67: Faturamento | EP67: Faturamento | ER67: CNPJ: | EV67: Faturamento | FC67: Faturamento | FE67: CNPJ: | FI67: Faturamento | FP67: Faturamento | FR67: CNPJ: | FV67: Faturamento | GC67: Faturamento | GE67: CNPJ: | GI67: Faturamento
AP69: Compra | AR69: Razão | AV69: Compra | AY69: =AW70*2.5% -> 0 | BC69: Compra | BE69: Razão | BI69: Compra | BL69: =BJ70*2.5% -> 0 | BP69: Compra | BR69: Razão | BV69: Compra | BY69: =BW70*2.5% -> 0 | CC69: Compra | CE69: Razão | CI69: Compra | CL69: =CJ70*2.5% -> 0 | CP69: Compra | CR69: Razão | CV69: Compra | CY69: =CW70*2.5% -> 0 | DC69: Compra | DE69: Razão | DI69: Compra | DL69: =DJ70*2.5% -> 0 | DP69: Compra | DR69: Razão | DV69: Compra | DY69: =DW70*2.5% -> 0 | EC69: Compra | EE69: Razão | EI69: Compra | EL69: =EJ70*2.5% -> 0 | EP69: Compra | ER69: Razão | EV69: Compra | EY69: =EW70*2.5% -> 0 | FC69: Compra | FE69: Razão | FI69: Compra | FL69: =FJ70*2.5% -> 0 | FP69: Compra | FR69: Razão | FV69: Compra | FY69: =FW70*2.5% -> 0 | GC69: Compra | GE69: Razão | GI69: Compra | GL69: =GJ70*2.5% -> 0
AP70: Faturamento | AR70: CNPJ: | AV70: Faturamento | BC70: Faturamento | BE70: CNPJ: | BI70: Faturamento | BP70: Faturamento | BR70: CNPJ: | BV70: Faturamento | CC70: Faturamento | CE70: CNPJ: | CI70: Faturamento | CP70: Faturamento | CR70: CNPJ: | CV70: Faturamento | DC70: Faturamento | DE70: CNPJ: | DI70: Faturamento | DP70: Faturamento | DR70: CNPJ: | DV70: Faturamento | EC70: Faturamento | EE70: CNPJ: | EI70: Faturamento | EP70: Faturamento | ER70: CNPJ: | EV70: Faturamento | FC70: Faturamento | FE70: CNPJ: | FI70: Faturamento | FP70: Faturamento | FR70: CNPJ: | FV70: Faturamento | GC70: Faturamento | GE70: CNPJ: | GI70: Faturamento
AP72: Compra | AR72: Razão | AV72: Compra | AY72: =AW73*2.5% -> 0 | BC72: Compra | BE72: Razão | BI72: Compra | BL72: =BJ73*2.5% -> 0 | BP72: Compra | BR72: Razão | BV72: Compra | BY72: =BW73*2.5% -> 0 | CC72: Compra | CE72: Razão | CI72: Compra | CL72: =CJ73*2.5% -> 0 | CP72: Compra | CR72: Razão | CV72: Compra | CY72: =CW73*2.5% -> 0 | DC72: Compra | DE72: Razão | DI72: Compra | DL72: =DJ73*2.5% -> 0 | DP72: Compra | DR72: Razão | DV72: Compra | DY72: =DW73*2.5% -> 0 | EC72: Compra | EE72: Razão | EI72: Compra | EL72: =EJ73*2.5% -> 0 | EP72: Compra | ER72: Razão | EV72: Compra | EY72: =EW73*2.5% -> 0 | FC72: Compra | FE72: Razão | FI72: Compra | FL72: =FJ73*2.5% -> 0 | FP72: Compra | FR72: Razão | FV72: Compra | FY72: =FW73*2.5% -> 0 | GC72: Compra | GE72: Razão | GI72: Compra | GL72: =GJ73*2.5% -> 0
AP73: Faturamento | AR73: CNPJ: | AV73: Faturamento | BC73: Faturamento | BE73: CNPJ: | BI73: Faturamento | BP73: Faturamento | BR73: CNPJ: | BV73: Faturamento | CC73: Faturamento | CE73: CNPJ: | CI73: Faturamento | CP73: Faturamento | CR73: CNPJ: | CV73: Faturamento | DC73: Faturamento | DE73: CNPJ: | DI73: Faturamento | DP73: Faturamento | DR73: CNPJ: | DV73: Faturamento | EC73: Faturamento | EE73: CNPJ: | EI73: Faturamento | EP73: Faturamento | ER73: CNPJ: | EV73: Faturamento | FC73: Faturamento | FE73: CNPJ: | FI73: Faturamento | FP73: Faturamento | FR73: CNPJ: | FV73: Faturamento | GC73: Faturamento | GE73: CNPJ: | GI73: Faturamento
AP75: Compra | AR75: Razão | AV75: Compra | AY75: =AW76*2.5% -> 0 | BC75: Compra | BE75: Razão | BI75: Compra | BL75: =BJ76*2.5% -> 0 | BP75: Compra | BR75: Razão | BV75: Compra | BY75: =BW76*2.5% -> 0 | CC75: Compra | CE75: Razão | CI75: Compra | CL75: =CJ76*2.5% -> 0 | CP75: Compra | CR75: Razão | CV75: Compra | CY75: =CW76*2.5% -> 0 | DC75: Compra | DE75: Razão | DI75: Compra | DL75: =DJ76*2.5% -> 0 | DP75: Compra | DR75: Razão | DV75: Compra | DY75: =DW76*2.5% -> 0 | EC75: Compra | EE75: Razão | EI75: Compra | EL75: =EJ76*2.5% -> 0 | EP75: Compra | ER75: Razão | EV75: Compra | EY75: =EW76*2.5% -> 0 | FC75: Compra | FE75: Razão | FI75: Compra | FL75: =FJ76*2.5% -> 0 | FP75: Compra | FR75: Razão | FV75: Compra | FY75: =FW76*2.5% -> 0 | GC75: Compra | GE75: Razão | GI75: Compra | GL75: =GJ76*2.5% -> 0
AP76: Faturamento | AR76: CNPJ: | AV76: Faturamento | BC76: Faturamento | BE76: CNPJ: | BI76: Faturamento | BP76: Faturamento | BR76: CNPJ: | BV76: Faturamento | CC76: Faturamento | CE76: CNPJ: | CI76: Faturamento | CP76: Faturamento | CR76: CNPJ: | CV76: Faturamento | DC76: Faturamento | DE76: CNPJ: | DI76: Faturamento | DP76: Faturamento | DR76: CNPJ: | DV76: Faturamento | EC76: Faturamento | EE76: CNPJ: | EI76: Faturamento | EP76: Faturamento | ER76: CNPJ: | EV76: Faturamento | FC76: Faturamento | FE76: CNPJ: | FI76: Faturamento | FP76: Faturamento | FR76: CNPJ: | FV76: Faturamento | GC76: Faturamento | GE76: CNPJ: | GI76: Faturamento
AP78: Compra | AR78: Razão | AV78: Compra | AY78: =AW79*2.5% -> 0 | BC78: Compra | BE78: Razão | BI78: Compra | BL78: =BJ79*2.5% -> 0 | BP78: Compra | BR78: Razão | BV78: Compra | BY78: =BW79*2.5% -> 0 | CC78: Compra | CE78: Razão | CI78: Compra | CL78: =CJ79*2.5% -> 0 | CP78: Compra | CR78: Razão | CV78: Compra | CY78: =CW79*2.5% -> 0 | DC78: Compra | DE78: Razão | DI78: Compra | DL78: =DJ79*2.5% -> 0 | DP78: Compra | DR78: Razão | DV78: Compra | DY78: =DW79*2.5% -> 0 | EC78: Compra | EE78: Razão | EI78: Compra | EL78: =EJ79*2.5% -> 0 | EP78: Compra | ER78: Razão | EV78: Compra | EY78: =EW79*2.5% -> 0 | FC78: Compra | FE78: Razão | FI78: Compra | FL78: =FJ79*2.5% -> 0 | FP78: Compra | FR78: Razão | FV78: Compra | FY78: =FW79*2.5% -> 0 | GC78: Compra | GE78: Razão | GI78: Compra | GL78: =GJ79*2.5% -> 0
AP79: Faturamento | AR79: CNPJ: | AV79: Faturamento | BC79: Faturamento | BE79: CNPJ: | BI79: Faturamento | BP79: Faturamento | BR79: CNPJ: | BV79: Faturamento | CC79: Faturamento | CE79: CNPJ: | CI79: Faturamento | CP79: Faturamento | CR79: CNPJ: | CV79: Faturamento | DC79: Faturamento | DE79: CNPJ: | DI79: Faturamento | DP79: Faturamento | DR79: CNPJ: | DV79: Faturamento | EC79: Faturamento | EE79: CNPJ: | EI79: Faturamento | EP79: Faturamento | ER79: CNPJ: | EV79: Faturamento | FC79: Faturamento | FE79: CNPJ: | FI79: Faturamento | FP79: Faturamento | FR79: CNPJ: | FV79: Faturamento | GC79: Faturamento | GE79: CNPJ: | GI79: Faturamento
AP81: Compra | AR81: Razão | AV81: Compra | AY81: =AW82*2.5% -> 0 | BC81: Compra | BE81: Razão | BI81: Compra | BL81: =BJ82*2.5% -> 0 | BP81: Compra | BR81: Razão | BV81: Compra | BY81: =BW82*2.5% -> 0 | CC81: Compra | CE81: Razão | CI81: Compra | CL81: =CJ82*2.5% -> 0 | CP81: Compra | CR81: Razão | CV81: Compra | CY81: =CW82*2.5% -> 0 | DC81: Compra | DE81: Razão | DI81: Compra | DL81: =DJ82*2.5% -> 0 | DP81: Compra | DR81: Razão | DV81: Compra | DY81: =DW82*2.5% -> 0 | EC81: Compra | EE81: Razão | EI81: Compra | EL81: =EJ82*2.5% -> 0 | EP81: Compra | ER81: Razão | EV81: Compra | EY81: =EW82*2.5% -> 0 | FC81: Compra | FE81: Razão | FI81: Compra | FL81: =FJ82*2.5% -> 0 | FP81: Compra | FR81: Razão | FV81: Compra | FY81: =FW82*2.5% -> 0 | GC81: Compra | GE81: Razão | GI81: Compra | GL81: =GJ82*2.5% -> 0
AP82: Faturamento | AR82: CNPJ: | AV82: Faturamento | BC82: Faturamento | BE82: CNPJ: | BI82: Faturamento | BP82: Faturamento | BR82: CNPJ: | BV82: Faturamento | CC82: Faturamento | CE82: CNPJ: | CI82: Faturamento | CP82: Faturamento | CR82: CNPJ: | CV82: Faturamento | DC82: Faturamento | DE82: CNPJ: | DI82: Faturamento | DP82: Faturamento | DR82: CNPJ: | DV82: Faturamento | EC82: Faturamento | EE82: CNPJ: | EI82: Faturamento | EP82: Faturamento | ER82: CNPJ: | EV82: Faturamento | FC82: Faturamento | FE82: CNPJ: | FI82: Faturamento | FP82: Faturamento | FR82: CNPJ: | FV82: Faturamento | GC82: Faturamento | GE82: CNPJ: | GI82: Faturamento
AP84: Compra | AR84: Razão | AV84: Compra | AY84: =AW85*2.5% -> 0 | BC84: Compra | BE84: Razão | BI84: Compra | BL84: =BJ85*2.5% -> 0 | BP84: Compra | BR84: Razão | BV84: Compra | BY84: =BW85*2.5% -> 0 | CC84: Compra | CE84: Razão | CI84: Compra | CL84: =CJ85*2.5% -> 0 | CP84: Compra | CR84: Razão | CV84: Compra | CY84: =CW85*2.5% -> 0 | DC84: Compra | DE84: Razão | DI84: Compra | DL84: =DJ85*2.5% -> 0 | DP84: Compra | DR84: Razão | DV84: Compra | DY84: =DW85*2.5% -> 0 | EC84: Compra | EE84: Razão | EI84: Compra | EL84: =EJ85*2.5% -> 0 | EP84: Compra | ER84: Razão | EV84: Compra | EY84: =EW85*2.5% -> 0 | FC84: Compra | FE84: Razão | FI84: Compra | FL84: =FJ85*2.5% -> 0 | FP84: Compra | FR84: Razão | FV84: Compra | FY84: =FW85*2.5% -> 0 | GC84: Compra | GE84: Razão | GI84: Compra | GL84: =GJ85*2.5% -> 0
AP85: Faturamento | AR85: CNPJ: | AV85: Faturamento | BC85: Faturamento | BE85: CNPJ: | BI85: Faturamento | BP85: Faturamento | BR85: CNPJ: | BV85: Faturamento | CC85: Faturamento | CE85: CNPJ: | CI85: Faturamento | CP85: Faturamento | CR85: CNPJ: | CV85: Faturamento | DC85: Faturamento | DE85: CNPJ: | DI85: Faturamento | DP85: Faturamento | DR85: CNPJ: | DV85: Faturamento | EC85: Faturamento | EE85: CNPJ: | EI85: Faturamento | EP85: Faturamento | ER85: CNPJ: | EV85: Faturamento | FC85: Faturamento | FE85: CNPJ: | FI85: Faturamento | FP85: Faturamento | FR85: CNPJ: | FV85: Faturamento | GC85: Faturamento | GE85: CNPJ: | GI85: Faturamento
AP87: Compra | AR87: Razão | AV87: Compra | AY87: =AW88*2.5% -> 0 | BC87: Compra | BE87: Razão | BI87: Compra | BL87: =BJ88*2.5% -> 0 | BP87: Compra | BR87: Razão | BV87: Compra | BY87: =BW88*2.5% -> 0 | CC87: Compra | CE87: Razão | CI87: Compra | CL87: =CJ88*2.5% -> 0 | CP87: Compra | CR87: Razão | CV87: Compra | CY87: =CW88*2.5% -> 0 | DC87: Compra | DE87: Razão | DI87: Compra | DL87: =DJ88*2.5% -> 0 | DP87: Compra | DR87: Razão | DV87: Compra | DY87: =DW88*2.5% -> 0 | EC87: Compra | EE87: Razão | EI87: Compra | EL87: =EJ88*2.5% -> 0 | EP87: Compra | ER87: Razão | EV87: Compra | EY87: =EW88*2.5% -> 0 | FC87: Compra | FE87: Razão | FI87: Compra | FL87: =FJ88*2.5% -> 0 | FP87: Compra | FR87: Razão | FV87: Compra | FY87: =FW88*2.5% -> 0 | GC87: Compra | GE87: Razão | GI87: Compra | GL87: =GJ88*2.5% -> 0
AP88: Faturamento | AR88: CNPJ: | AV88: Faturamento | BC88: Faturamento | BE88: CNPJ: | BI88: Faturamento | BP88: Faturamento | BR88: CNPJ: | BV88: Faturamento | CC88: Faturamento | CE88: CNPJ: | CI88: Faturamento | CP88: Faturamento | CR88: CNPJ: | CV88: Faturamento | DC88: Faturamento | DE88: CNPJ: | DI88: Faturamento | DP88: Faturamento | DR88: CNPJ: | DV88: Faturamento | EC88: Faturamento | EE88: CNPJ: | EI88: Faturamento | EP88: Faturamento | ER88: CNPJ: | EV88: Faturamento | FC88: Faturamento | FE88: CNPJ: | FI88: Faturamento | FP88: Faturamento | FR88: CNPJ: | FV88: Faturamento | GC88: Faturamento | GE88: CNPJ: | GI88: Faturamento
AP90: Compra | AR90: Razão | AV90: Compra | AY90: =AW91*2.5% -> 0 | BC90: Compra | BE90: Razão | BI90: Compra | BL90: =BJ91*2.5% -> 0 | BP90: Compra | BR90: Razão | BV90: Compra | BY90: =BW91*2.5% -> 0 | CC90: Compra | CE90: Razão | CI90: Compra | CL90: =CJ91*2.5% -> 0 | CP90: Compra | CR90: Razão | CV90: Compra | CY90: =CW91*2.5% -> 0 | DC90: Compra | DE90: Razão | DI90: Compra | DL90: =DJ91*2.5% -> 0 | DP90: Compra | DR90: Razão | DV90: Compra | DY90: =DW91*2.5% -> 0 | EC90: Compra | EE90: Razão | EI90: Compra | EL90: =EJ91*2.5% -> 0 | EP90: Compra | ER90: Razão | EV90: Compra | EY90: =EW91*2.5% -> 0 | FC90: Compra | FE90: Razão | FI90: Compra | FL90: =FJ91*2.5% -> 0 | FP90: Compra | FR90: Razão | FV90: Compra | FY90: =FW91*2.5% -> 0 | GC90: Compra | GE90: Razão | GI90: Compra | GL90: =GJ91*2.5% -> 0
AP91: Faturamento | AR91: CNPJ: | AV91: Faturamento | BC91: Faturamento | BE91: CNPJ: | BI91: Faturamento | BP91: Faturamento | BR91: CNPJ: | BV91: Faturamento | CC91: Faturamento | CE91: CNPJ: | CI91: Faturamento | CP91: Faturamento | CR91: CNPJ: | CV91: Faturamento | DC91: Faturamento | DE91: CNPJ: | DI91: Faturamento | DP91: Faturamento | DR91: CNPJ: | DV91: Faturamento | EC91: Faturamento | EE91: CNPJ: | EI91: Faturamento | EP91: Faturamento | ER91: CNPJ: | EV91: Faturamento | FC91: Faturamento | FE91: CNPJ: | FI91: Faturamento | FP91: Faturamento | FR91: CNPJ: | FV91: Faturamento | GC91: Faturamento | GE91: CNPJ: | GI91: Faturamento
AP93: Compra | AR93: Razão | AV93: Compra | AY93: =AW94*2.5% -> 0 | BC93: Compra | BE93: Razão | BI93: Compra | BL93: =BJ94*2.5% -> 0 | BP93: Compra | BR93: Razão | BV93: Compra | BY93: =BW94*2.5% -> 0 | CC93: Compra | CE93: Razão | CI93: Compra | CL93: =CJ94*2.5% -> 0 | CP93: Compra | CR93: Razão | CV93: Compra | CY93: =CW94*2.5% -> 0 | DC93: Compra | DE93: Razão | DI93: Compra | DL93: =DJ94*2.5% -> 0 | DP93: Compra | DR93: Razão | DV93: Compra | DY93: =DW94*2.5% -> 0 | EC93: Compra | EE93: Razão | EI93: Compra | EL93: =EJ94*2.5% -> 0 | EP93: Compra | ER93: Razão | EV93: Compra | EY93: =EW94*2.5% -> 0 | FC93: Compra | FE93: Razão | FI93: Compra | FL93: =FJ94*2.5% -> 0 | FP93: Compra | FR93: Razão | FV93: Compra | FY93: =FW94*2.5% -> 0 | GC93: Compra | GE93: Razão | GI93: Compra | GL93: =GJ94*2.5% -> 0
AP94: Faturamento | AR94: CNPJ: | AV94: Faturamento | BC94: Faturamento | BE94: CNPJ: | BI94: Faturamento | BP94: Faturamento | BR94: CNPJ: | BV94: Faturamento | CC94: Faturamento | CE94: CNPJ: | CI94: Faturamento | CP94: Faturamento | CR94: CNPJ: | CV94: Faturamento | DC94: Faturamento | DE94: CNPJ: | DI94: Faturamento | DP94: Faturamento | DR94: CNPJ: | DV94: Faturamento | EC94: Faturamento | EE94: CNPJ: | EI94: Faturamento | EP94: Faturamento | ER94: CNPJ: | EV94: Faturamento | FC94: Faturamento | FE94: CNPJ: | FI94: Faturamento | FP94: Faturamento | FR94: CNPJ: | FV94: Faturamento | GC94: Faturamento | GE94: CNPJ: | GI94: Faturamento
AP96: Compra | AR96: Razão | AV96: Compra | AY96: =AW97*2.5% -> 0 | BC96: Compra | BE96: Razão | BI96: Compra | BL96: =BJ97*2.5% -> 0 | BP96: Compra | BR96: Razão | BV96: Compra | BY96: =BW97*2.5% -> 0 | CC96: Compra | CE96: Razão | CI96: Compra | CL96: =CJ97*2.5% -> 0 | CP96: Compra | CR96: Razão | CV96: Compra | CY96: =CW97*2.5% -> 0 | DC96: Compra | DE96: Razão | DI96: Compra | DL96: =DJ97*2.5% -> 0 | DP96: Compra | DR96: Razão | DV96: Compra | DY96: =DW97*2.5% -> 0 | EC96: Compra | EE96: Razão | EI96: Compra | EL96: =EJ97*2.5% -> 0 | EP96: Compra | ER96: Razão | EV96: Compra | EY96: =EW97*2.5% -> 0 | FC96: Compra | FE96: Razão | FI96: Compra | FL96: =FJ97*2.5% -> 0 | FP96: Compra | FR96: Razão | FV96: Compra | FY96: =FW97*2.5% -> 0 | GC96: Compra | GE96: Razão | GI96: Compra | GL96: =GJ97*2.5% -> 0
AP97: Faturamento | AR97: CNPJ: | AV97: Faturamento | BC97: Faturamento | BE97: CNPJ: | BI97: Faturamento | BP97: Faturamento | BR97: CNPJ: | BV97: Faturamento | CC97: Faturamento | CE97: CNPJ: | CI97: Faturamento | CP97: Faturamento | CR97: CNPJ: | CV97: Faturamento | DC97: Faturamento | DE97: CNPJ: | DI97: Faturamento | DP97: Faturamento | DR97: CNPJ: | DV97: Faturamento | EC97: Faturamento | EE97: CNPJ: | EI97: Faturamento | EP97: Faturamento | ER97: CNPJ: | EV97: Faturamento | FC97: Faturamento | FE97: CNPJ: | FI97: Faturamento | FP97: Faturamento | FR97: CNPJ: | FV97: Faturamento | GC97: Faturamento | GE97: CNPJ: | GI97: Faturamento
AP99: Compra | AR99: Razão | AV99: Compra | AY99: =AW100*2.5% -> 0 | BC99: Compra | BE99: Razão | BI99: Compra | BL99: =BJ100*2.5% -> 0 | BP99: Compra | BR99: Razão | BV99: Compra | BY99: =BW100*2.5% -> 0 | CC99: Compra | CE99: Razão | CI99: Compra | CL99: =CJ100*2.5% -> 0 | CP99: Compra | CR99: Razão | CV99: Compra | CY99: =CW100*2.5% -> 0 | DC99: Compra | DE99: Razão | DI99: Compra | DL99: =DJ100*2.5% -> 0 | DP99: Compra | DR99: Razão | DV99: Compra | DY99: =DW100*2.5% -> 0 | EC99: Compra | EE99: Razão | EI99: Compra | EL99: =EJ100*2.5% -> 0 | EP99: Compra | ER99: Razão | EV99: Compra | EY99: =EW100*2.5% -> 0 | FC99: Compra | FE99: Razão | FI99: Compra | FL99: =FJ100*2.5% -> 0 | FP99: Compra | FR99: Razão | FV99: Compra | FY99: =FW100*2.5% -> 0 | GC99: Compra | GE99: Razão | GI99: Compra | GL99: =GJ100*2.5% -> 0
AP100: Faturamento | AR100: CNPJ: | AV100: Faturamento | BC100: Faturamento | BE100: CNPJ: | BI100: Faturamento | BP100: Faturamento | BR100: CNPJ: | BV100: Faturamento | CC100: Faturamento | CE100: CNPJ: | CI100: Faturamento | CP100: Faturamento | CR100: CNPJ: | CV100: Faturamento | DC100: Faturamento | DE100: CNPJ: | DI100: Faturamento | DP100: Faturamento | DR100: CNPJ: | DV100: Faturamento | EC100: Faturamento | EE100: CNPJ: | EI100: Faturamento | EP100: Faturamento | ER100: CNPJ: | EV100: Faturamento | FC100: Faturamento | FE100: CNPJ: | FI100: Faturamento | FP100: Faturamento | FR100: CNPJ: | FV100: Faturamento | GC100: Faturamento | GE100: CNPJ: | GI100: Faturamento
AT104: VALOR VENDA | AV104: =AW4+AW7+AW10+AW13+AW16+AW19+AW22+AW25+AW28+AW31+AW34+AW37+AW40+AW43+AW46+AW49+AW52+AW55+AW58+AW61+AW64+AW67+AW70+AW73+AW76+AW79+AW82+AW85+AW88+AW91+AW94+AW97+AW100 -> 0 | AX104: VALOR COMISSÃO | AZ104: =AY3+AY6+AY9+AY12+AY15+AY18+AY21+AY24+AY27+AY30+AY33+AY36+AY39+AY42+AY45+AY48+AY51+AY54+AY57+AY60+AY63+AY66+AY69+AY72+AY75+AY78+AY81+AY84+AY87+AY90+AY93+AY96+AY99 -> 0 | BG104: VALOR VENDA | BI104: =BJ4+BJ7+BJ10+BJ13+BJ16+BJ19+BJ22+BJ25+BJ28+BJ31+BJ34+BJ37+BJ40+BJ43+BJ46+BJ49+BJ52+BJ55+BJ58+BJ61+BJ64+BJ67+BJ70+BJ73+BJ76+BJ79+BJ82+BJ85+BJ88+BJ91+BJ94+BJ97+BJ100 -> 0 | BK104: VALOR COMISSÃO | BM104: =BL3+BL6+BL9+BL12+BL15+BL18+BL21+BL24+BL27+BL30+BL33+BL36+BL39+BL42+BL45+BL48+BL51+BL54+BL57+BL60+BL63+BL66+BL69+BL72+BL75+BL78+BL81+BL84+BL87+BL90+BL93+BL96+BL99 -> 0 | BT104: VALOR VENDA | BV104: =BW4+BW7+BW10+BW13+BW16+BW19+BW22+BW25+BW28+BW31+BW34+BW37+BW40+BW43+BW46+BW49+BW52+BW55+BW58+BW61+BW64+BW67+BW70+BW73+BW76+BW79+BW82+BW85+BW88+BW91+BW94+BW97+BW100 -> 0 | BX104: VALOR COMISSÃO | BZ104: =BY3+BY6+BY9+BY12+BY15+BY18+BY21+BY24+BY27+BY30+BY33+BY36+BY39+BY42+BY45+BY48+BY51+BY54+BY57+BY60+BY63+BY66+BY69+BY72+BY75+BY78+BY81+BY84+BY87+BY90+BY93+BY96+BY99 -> 0 | CG104: VALOR VENDA | CI104: =CJ4+CJ7+CJ10+CJ13+CJ16+CJ19+CJ22+CJ25+CJ28+CJ31+CJ34+CJ37+CJ40+CJ43+CJ46+CJ49+CJ52+CJ55+CJ58+CJ61+CJ64+CJ67+CJ70+CJ73+CJ76+CJ79+CJ82+CJ85+CJ88+CJ91+CJ94+CJ97+CJ100 -> 0 | CK104: VALOR COMISSÃO | CM104: =CL3+CL6+CL9+CL12+CL15+CL18+CL21+CL24+CL27+CL30+CL33+CL36+CL39+CL42+CL45+CL48+CL51+CL54+CL57+CL60+CL63+CL66+CL69+CL72+CL75+CL78+CL81+CL84+CL87+CL90+CL93+CL96+CL99 -> 0 | CT104: VALOR VENDA | CV104: =CW4+CW7+CW10+CW13+CW16+CW19+CW22+CW25+CW28+CW31+CW34+CW37+CW40+CW43+CW46+CW49+CW52+CW55+CW58+CW61+CW64+CW67+CW70+CW73+CW76+CW79+CW82+CW85+CW88+CW91+CW94+CW97+CW100 -> 0 | CX104: VALOR COMISSÃO | CZ104: =CY3+CY6+CY9+CY12+CY15+CY18+CY21+CY24+CY27+CY30+CY33+CY36+CY39+CY42+CY45+CY48+CY51+CY54+CY57+CY60+CY63+CY66+CY69+CY72+CY75+CY78+CY81+CY84+CY87+CY90+CY93+CY96+CY99 -> 0 | DG104: VALOR VENDA | DI104: =DJ4+DJ7+DJ10+DJ13+DJ16+DJ19+DJ22+DJ25+DJ28+DJ31+DJ34+DJ37+DJ40+DJ43+DJ46+DJ49+DJ52+DJ55+DJ58+DJ61+DJ64+DJ67+DJ70+DJ73+DJ76+DJ79+DJ82+DJ85+DJ88+DJ91+DJ94+DJ97+DJ100 -> 0 | DK104: VALOR COMISSÃO | DM104: =DL3+DL6+DL9+DL12+DL15+DL18+DL21+DL24+DL27+DL30+DL33+DL36+DL39+DL42+DL45+DL48+DL51+DL54+DL57+DL60+DL63+DL66+DL69+DL72+DL75+DL78+DL81+DL84+DL87+DL90+DL93+DL96+DL99 -> 0 | DT104: VALOR VENDA | DV104: =DW4+DW7+DW10+DW13+DW16+DW19+DW22+DW25+DW28+DW31+DW34+DW37+DW40+DW43+DW46+DW49+DW52+DW55+DW58+DW61+DW64+DW67+DW70+DW73+DW76+DW79+DW82+DW85+DW88+DW91+DW94+DW97+DW100 -> 0 | DX104: VALOR COMISSÃO | DZ104: =DY3+DY6+DY9+DY12+DY15+DY18+DY21+DY24+DY27+DY30+DY33+DY36+DY39+DY42+DY45+DY48+DY51+DY54+DY57+DY60+DY63+DY66+DY69+DY72+DY75+DY78+DY81+DY84+DY87+DY90+DY93+DY96+DY99 -> 0 | EG104: VALOR VENDA | EI104: =EJ4+EJ7+EJ10+EJ13+EJ16+EJ19+EJ22+EJ25+EJ28+EJ31+EJ34+EJ37+EJ40+EJ43+EJ46+EJ49+EJ52+EJ55+EJ58+EJ61+EJ64+EJ67+EJ70+EJ73+EJ76+EJ79+EJ82+EJ85+EJ88+EJ91+EJ94+EJ97+EJ100 -> 0 | EK104: VALOR COMISSÃO | EM104: =EL3+EL6+EL9+EL12+EL15+EL18+EL21+EL24+EL27+EL30+EL33+EL36+EL39+EL42+EL45+EL48+EL51+EL54+EL57+EL60+EL63+EL66+EL69+EL72+EL75+EL78+EL81+EL84+EL87+EL90+EL93+EL96+EL99 -> 0 | ET104: VALOR VENDA | EV104: =EW4+EW7+EW10+EW13+EW16+EW19+EW22+EW25+EW28+EW31+EW34+EW37+EW40+EW43+EW46+EW49+EW52+EW55+EW58+EW61+EW64+EW67+EW70+EW73+EW76+EW79+EW82+EW85+EW88+EW91+EW94+EW97+EW100 -> 0 | EX104: VALOR COMISSÃO | EZ104: =EY3+EY6+EY9+EY12+EY15+EY18+EY21+EY24+EY27+EY30+EY33+EY36+EY39+EY42+EY45+EY48+EY51+EY54+EY57+EY60+EY63+EY66+EY69+EY72+EY75+EY78+EY81+EY84+EY87+EY90+EY93+EY96+EY99 -> 0 | FG104: VALOR VENDA | FI104: =FJ4+FJ7+FJ10+FJ13+FJ16+FJ19+FJ22+FJ25+FJ28+FJ31+FJ34+FJ37+FJ40+FJ43+FJ46+FJ49+FJ52+FJ55+FJ58+FJ61+FJ64+FJ67+FJ70+FJ73+FJ76+FJ79+FJ82+FJ85+FJ88+FJ91+FJ94+FJ97+FJ100 -> 0 | FK104: VALOR COMISSÃO | FM104: =FL3+FL6+FL9+FL12+FL15+FL18+FL21+FL24+FL27+FL30+FL33+FL36+FL39+FL42+FL45+FL48+FL51+FL54+FL57+FL60+FL63+FL66+FL69+FL72+FL75+FL78+FL81+FL84+FL87+FL90+FL93+FL96+FL99 -> 0 | FT104: VALOR VENDA | FV104: =FW4+FW7+FW10+FW13+FW16+FW19+FW22+FW25+FW28+FW31+FW34+FW37+FW40+FW43+FW46+FW49+FW52+FW55+FW58+FW61+FW64+FW67+FW70+FW73+FW76+FW79+FW82+FW85+FW88+FW91+FW94+FW97+FW100 -> 0 | FX104: VALOR COMISSÃO | FZ104: =FY3+FY6+FY9+FY12+FY15+FY18+FY21+FY24+FY27+FY30+FY33+FY36+FY39+FY42+FY45+FY48+FY51+FY54+FY57+FY60+FY63+FY66+FY69+FY72+FY75+FY78+FY81+FY84+FY87+FY90+FY93+FY96+FY99 -> 0 | GG104: VALOR VENDA | GI104: =GJ4+GJ7+GJ10+GJ13+GJ16+GJ19+GJ22+GJ25+GJ28+GJ31+GJ34+GJ37+GJ40+GJ43+GJ46+GJ49+GJ52+GJ55+GJ58+GJ61+GJ64+GJ67+GJ70+GJ73+GJ76+GJ79+GJ82+GJ85+GJ88+GJ91+GJ94+GJ97+GJ100 -> 0 | GK104: VALOR COMISSÃO | GM104: =GL3+GL6+GL9+GL12+GL15+GL18+GL21+GL24+GL27+GL30+GL33+GL36+GL39+GL42+GL45+GL48+GL51+GL54+GL57+GL60+GL63+GL66+GL69+GL72+GL75+GL78+GL81+GL84+GL87+GL90+GL93+GL96+GL99 -> 0

Sheet DAGIA
B1: JUNHO | M1: Voltar ao Inicio | O1: JULHO | Z1: Voltar ao Inicio | AB1: AGOSTO | AN1: Voltar ao Inicio | AP1: Janeiro | BA1: Voltar ao Inicio | BC1: Fevereiro | BN1: Voltar ao Inicio | BP1: Março | CA1: Voltar ao Inicio | CC1: Abril | CN1: Voltar ao Inicio | CP1: Maio | DA1: Voltar ao Inicio | DC1: Junho | DN1: Voltar ao Inicio | DP1: Julho | EA1: Voltar ao Inicio | EC1: Agosto | EN1: Voltar ao Inicio | EP1: Setembro | FA1: Voltar ao Inicio | FC1: Outubro | FN1: Voltar ao Inicio | FP1: Novembro | GA1: Voltar ao Inicio | GC1: Dezembro | GN1: Voltar ao Inicio
B2: Data | D2: CLIENTE | F2: Pedido | G2: NFE | H2: Valor | J2: TABELA | K2: PRAZO | L2: Comissão | M2: Situação Pedido | O2: Data | Q2: CLIENTE | S2: Pedido | T2: NFE | U2: Valor | W2: TABELA | X2: PRAZO | Y2: Comissão | Z2: Situação Pedido | AB2: Data | AD2: CLIENTE | AF2: Pedido | AG2: FORNECEDOR | AH2: NFE | AI2: Valor | AK2: TABELA | AL2: PRAZO | AM2: Comissão | AN2: Situação Pedido | AP2: Data | AR2: CLIENTE | AT2: Pedido | AU2: NFE | AV2: Valor | AX2: TABELA | AY2: Comissão | AZ2: Vendedor | BA2: Situação Pedido | BC2: Data | BE2: CLIENTE | BG2: Pedido | BH2: NFE | BI2: Valor | BK2: TABELA | BL2: Comissão | BM2: Vendedor | BN2: Situação Pedido | BP2: Data | BR2: CLIENTE | BT2: Pedido | BU2: NFE | BV2: Valor | BX2: TABELA | BY2: Comissão | BZ2: Vendedor | CA2: Situação Pedido | CC2: Data | CE2: CLIENTE | CG2: Pedido | CH2: NFE | CI2: Valor | CK2: TABELA | CL2: Comissão | CM2: Vendedor | CN2: Situação Pedido | CP2: Data | CR2: CLIENTE | CT2: Pedido | CU2: NFE | CV2: Valor | CX2: TABELA | CY2: Comissão | CZ2: Vendedor | DA2: Situação Pedido | DC2: Data | DE2: CLIENTE | DG2: Pedido | DH2: NFE | DI2: Valor | DK2: TABELA | DL2: Comissão | DM2: Vendedor | DN2: Situação Pedido | DP2: Data | DR2: CLIENTE | DT2: Pedido | DU2: NFE | DV2: Valor | DX2: TABELA | DY2: Comissão | DZ2: Vendedor | EA2: Situação Pedido | EC2: Data | EE2: CLIENTE | EG2: Pedido | EH2: NFE | EI2: Valor | EK2: TABELA | EL2: Comissão | EM2: Vendedor | EN2: Situação Pedido | EP2: Data | ER2: CLIENTE | ET2: Pedido | EU2: NFE | EV2: Valor | EX2: TABELA | EY2: Comissão | EZ2: Vendedor | FA2: Situação Pedido | FC2: Data | FE2: CLIENTE | FG2: Pedido | FH2: NFE | FI2: Valor | FK2: TABELA | FL2: Comissão | FM2: Vendedor | FN2: Situação Pedido | FP2: Data | FR2: CLIENTE | FT2: Pedido | FU2: NFE | FV2: Valor | FX2: TABELA | FY2: Comissão | FZ2: Vendedor | GA2: Situação Pedido | GC2: Data | GE2: CLIENTE | GG2: Pedido | GH2: NFE | GI2: Valor | GK2: TABELA | GL2: Comissão | GM2: Vendedor | GN2: Situação Pedido
B3: Compra | C3: 45811 | D3: Razão | E3: DECAZZA COM | F3: 250602172053470 | G3: 1441 | H3: Compra | I3: 755.44 | J3: 2 | K3: PIX | L3: =I4*5% -> 37.772 | M3: PAGO | O3: Compra | P3: 45846 | Q3: Razão | R3: DECAZZA COM | S3: 250708135238581 | T3: 187 | U3: Compra | V3: 10891.96 | W3: 2 | X3: PIX | Y3: =V4*5% -> 544.598 | Z3: FATURADO | AB3: Compra | AD3: Razão | AI3: Compra | AL3: PIX | AN3: PAGO | AP3: Compra | AR3: Razão | AV3: Compra | AY3: =AW4*2.5% -> 0 | AZ3: RENAN | BC3: Compra | BE3: Razão | BI3: Compra | BL3: =BJ4*2.5% -> 0 | BM3: RENAN | BP3: Compra | BR3: Razão | BV3: Compra | BY3: =BW4*2.5% -> 0 | BZ3: RENAN | CC3: Compra | CE3: Razão | CI3: Compra | CL3: =CJ4*2.5% -> 0 | CM3: RENAN | CP3: Compra | CR3: Razão | CV3: Compra | CY3: =CW4*2.5% -> 0 | CZ3: RENAN | DC3: Compra | DE3: Razão | DI3: Compra | DL3: =DJ4*2.5% -> 0 | DM3: RENAN | DP3: Compra | DR3: Razão | DV3: Compra | DY3: =DW4*2.5% -> 0 | DZ3: RENAN | EC3: Compra | EE3: Razão | EI3: Compra | EL3: =EJ4*2.5% -> 0 | EM3: RENAN | EP3: Compra | ER3: Razão | EV3: Compra | EY3: =EW4*2.5% -> 0 | EZ3: RENAN | FC3: Compra | FE3: Razão | FI3: Compra | FL3: =FJ4*2.5% -> 0 | FM3: RENAN | FP3: Compra | FR3: Razão | FV3: Compra | FY3: =FW4*2.5% -> 0 | FZ3: RENAN | GC3: Compra | GE3: Razão | GI3: Compra | GL3: =GJ4*2.5% -> 0 | GM3: RENAN
B4: Faturamento | C4: 45812 | D4: CNPJ: | E4: 43.967.691/0001-00 | H4: Faturamento | I4: 755.44 | O4: Faturamento | P4: 45848 | Q4: CNPJ: | R4: 43.967.691/0001-00 | U4: Faturamento | V4: 10891.96 | AB4: Faturamento | AD4: CNPJ: | AI4: Faturamento | AP4: Faturamento | AR4: CNPJ: | AV4: Faturamento | BC4: Faturamento | BE4: CNPJ: | BI4: Faturamento | BP4: Faturamento | BR4: CNPJ: | BV4: Faturamento | CC4: Faturamento | CE4: CNPJ: | CI4: Faturamento | CP4: Faturamento | CR4: CNPJ: | CV4: Faturamento | DC4: Faturamento | DE4: CNPJ: | DI4: Faturamento | DP4: Faturamento | DR4: CNPJ: | DV4: Faturamento | EC4: Faturamento | EE4: CNPJ: | EI4: Faturamento | EP4: Faturamento | ER4: CNPJ: | EV4: Faturamento | FC4: Faturamento | FE4: CNPJ: | FI4: Faturamento | FP4: Faturamento | FR4: CNPJ: | FV4: Faturamento | GC4: Faturamento | GE4: CNPJ: | GI4: Faturamento
B6: Compra | C6: 45813 | D6: Razão | E6: EMBALEME | F6: 250604123701560 | G6: 1447 | H6: Compra | I6: 4110.14 | J6: 2 | K6: PRAZO | L6: =I7*5% -> 205.508 | M6: FATURADO | O6: Compra | P6: 45852 | Q6: Razão | R6: DECAZZA COM | S6: 3508 | T6: 218 | U6: Compra | V6: 71547.78 | W6: 2 | Y6: =V7*3.5% -> 2107.9968 | Z6: FATURADO | AB6: Compra | AD6: Razão | AI6: Compra | AM6: =AJ7*5% -> 0 | AN6: FATURADO | AP6: Compra | AR6: Razão | AV6: Compra | AY6: =AW7*2.5% -> 0 | BC6: Compra | BE6: Razão | BI6: Compra | BL6: =BJ7*2.5% -> 0 | BP6: Compra | BR6: Razão | BV6: Compra | BY6: =BW7*2.5% -> 0 | CC6: Compra | CE6: Razão | CI6: Compra | CL6: =CJ7*2.5% -> 0 | CP6: Compra | CR6: Razão | CV6: Compra | CY6: =CW7*2.5% -> 0 | DC6: Compra | DE6: Razão | DI6: Compra | DL6: =DJ7*2.5% -> 0 | DP6: Compra | DR6: Razão | DV6: Compra | DY6: =DW7*2.5% -> 0 | EC6: Compra | EE6: Razão | EI6: Compra | EL6: =EJ7*2.5% -> 0 | EP6: Compra | ER6: Razão | EV6: Compra | EY6: =EW7*2.5% -> 0 | FC6: Compra | FE6: Razão | FI6: Compra | FL6: =FJ7*2.5% -> 0 | FP6: Compra | FR6: Razão | FV6: Compra | FY6: =FW7*2.5% -> 0 | GC6: Compra | GE6: Razão | GI6: Compra | GL6: =GJ7*2.5% -> 0
B7: Faturamento | C7: 45817 | D7: CNPJ: | E7: 00.458.459/0001-33 | H7: Faturamento | I7: 4110.16 | O7: Faturamento | P7: 45855 | Q7: CNPJ: | R7: 43.967.691/0001-00 | U7: Faturamento | V7: 60228.48 | AB7: Faturamento | AD7: CNPJ: | AI7: Faturamento | AP7: Faturamento | AR7: CNPJ: | AV7: Faturamento | BC7: Faturamento | BE7: CNPJ: | BI7: Faturamento | BP7: Faturamento | BR7: CNPJ: | BV7: Faturamento | CC7: Faturamento | CE7: CNPJ: | CI7: Faturamento | CP7: Faturamento | CR7: CNPJ: | CV7: Faturamento | DC7: Faturamento | DE7: CNPJ: | DI7: Faturamento | DP7: Faturamento | DR7: CNPJ: | DV7: Faturamento | EC7: Faturamento | EE7: CNPJ: | EI7: Faturamento | EP7: Faturamento | ER7: CNPJ: | EV7: Faturamento | FC7: Faturamento | FE7: CNPJ: | FI7: Faturamento | FP7: Faturamento | FR7: CNPJ: | FV7: Faturamento | GC7: Faturamento | GE7: CNPJ: | GI7: Faturamento
B9: Compra | C9: 45819 | D9: Razão | E9: DECAZZA COMERCIAL | F9: 3062 | H9: Compra | I9: 7548 | J9: 2 | K9: PIX | L9: =I10*5% -> 377.4 | M9: PAGO | O9: Compra | P9: 45861 | Q9: Razão | R9: DECAZZA COM | S9: 250723143208488 | T9: 266 | U9: Compra | V9: 46645.2 | W9: 2 | Y9: =V10*4% -> 1865.808 | Z9: FATURADO | AB9: Compra | AD9: Razão | AI9: Compra | AM9: =AJ10*6% -> 0 | AN9: FATURADO | AP9: Compra | AR9: Razão | AV9: Compra | AY9: =AW10*2.5% -> 0 | BC9: Compra | BE9: Razão | BI9: Compra | BL9: =BJ10*2.5% -> 0 | BP9: Compra | BR9: Razão | BV9: Compra | BY9: =BW10*2.5% -> 0 | CC9: Compra | CE9: Razão | CI9: Compra | CL9: =CJ10*2.5% -> 0 | CP9: Compra | CR9: Razão | CV9: Compra | CY9: =CW10*2.5% -> 0 | DC9: Compra | DE9: Razão | DI9: Compra | DL9: =DJ10*2.5% -> 0 | DP9: Compra | DR9: Razão | DV9: Compra | DY9: =DW10*2.5% -> 0 | EC9: Compra | EE9: Razão | EI9: Compra | EL9: =EJ10*2.5% -> 0 | EP9: Compra | ER9: Razão | EV9: Compra | EY9: =EW10*2.5% -> 0 | FC9: Compra | FE9: Razão | FI9: Compra | FL9: =FJ10*2.5% -> 0 | FP9: Compra | FR9: Razão | FV9: Compra | FY9: =FW10*2.5% -> 0 | GC9: Compra | GE9: Razão | GI9: Compra | GL9: =GJ10*2.5% -> 0
B10: Faturamento | C10: 45820 | D10: CNPJ: | E10: 43.967.691/0001-00 | G10: 1457 | H10: Faturamento | I10: 7548 | O10: Faturamento | P10: 45862 | Q10: CNPJ: | R10: 43.967.691/0001-00 | U10: Faturamento | V10: 46645.2 | AB10: Faturamento | AD10: CNPJ: | AI10: Faturamento | AP10: Faturamento | AR10: CNPJ: | AV10: Faturamento | BC10: Faturamento | BE10: CNPJ: | BI10: Faturamento | BP10: Faturamento | BR10: CNPJ: | BV10: Faturamento | CC10: Faturamento | CE10: CNPJ: | CI10: Faturamento | CP10: Faturamento | CR10: CNPJ: | CV10: Faturamento | DC10: Faturamento | DE10: CNPJ: | DI10: Faturamento | DP10: Faturamento | DR10: CNPJ: | DV10: Faturamento | EC10: Faturamento | EE10: CNPJ: | EI10: Faturamento | EP10: Faturamento | ER10: CNPJ: | EV10: Faturamento | FC10: Faturamento | FE10: CNPJ: | FI10: Faturamento | FP10: Faturamento | FR10: CNPJ: | FV10: Faturamento | GC10: Faturamento | GE10: CNPJ: | GI10: Faturamento
B12: Compra | C12: 45813 | D12: Razão | E12: CELL SOLLUTION | F12: 250605154601006 | G12: 104 | H12: Compra | I12: 13749.56 | J12: 2 | K12: PIX | L12: =I13*5% -> 687.478 | M12: PAGO | O12: Compra | Q12: Razão | U12: Compra | Y12: =V13*5% -> 0 | AB12: Compra | AD12: Razão | AI12: Compra | AM12: =AJ13*5% -> 0 | AP12: Compra | AR12: Razão | AV12: Compra | AY12: =AW13*2.5% -> 0 | BC12: Compra | BE12: Razão | BI12: Compra | BL12: =BJ13*2.5% -> 0 | BP12: Compra | BR12: Razão | BV12: Compra | BY12: =BW13*2.5% -> 0 | CC12: Compra | CE12: Razão | CI12: Compra | CL12: =CJ13*2.5% -> 0 | CP12: Compra | CR12: Razão | CV12: Compra | CY12: =CW13*2.5% -> 0 | DC12: Compra | DE12: Razão | DI12: Compra | DL12: =DJ13*2.5% -> 0 | DP12: Compra | DR12: Razão | DV12: Compra | DY12: =DW13*2.5% -> 0 | EC12: Compra | EE12: Razão | EI12: Compra | EL12: =EJ13*2.5% -> 0 | EP12: Compra | ER12: Razão | EV12: Compra | EY12: =EW13*2.5% -> 0 | FC12: Compra | FE12: Razão | FI12: Compra | FL12: =FJ13*2.5% -> 0 | FP12: Compra | FR12: Razão | FV12: Compra | FY12: =FW13*2.5% -> 0 | GC12: Compra | GE12: Razão | GI12: Compra | GL12: =GJ13*2.5% -> 0
B13: Faturamento | C13: 45824 | D13: CNPJ: | E13: 20.963.243/0001-01 | H13: Faturamento | I13: 13749.56 | O13: Faturamento | Q13: CNPJ: | U13: Faturamento | AB13: Faturamento | AD13: CNPJ: | AI13: Faturamento | AP13: Faturamento | AR13: CNPJ: | AV13: Faturamento | BC13: Faturamento | BE13: CNPJ: | BI13: Faturamento | BP13: Faturamento | BR13: CNPJ: | BV13: Faturamento | CC13: Faturamento | CE13: CNPJ: | CI13: Faturamento | CP13: Faturamento | CR13: CNPJ: | CV13: Faturamento | DC13: Faturamento | DE13: CNPJ: | DI13: Faturamento | DP13: Faturamento | DR13: CNPJ: | DV13: Faturamento | EC13: Faturamento | EE13: CNPJ: | EI13: Faturamento | EP13: Faturamento | ER13: CNPJ: | EV13: Faturamento | FC13: Faturamento | FE13: CNPJ: | FI13: Faturamento | FP13: Faturamento | FR13: CNPJ: | FV13: Faturamento | GC13: Faturamento | GE13: CNPJ: | GI13: Faturamento
B15: Compra | C15: 45813 | D15: Razão | E15: CELL SOLLUTION | F15: 250605154107945 | G15: 1465 | H15: Compra | I15: 6256.2 | J15: 2 | K15: PIX | L15: =I16*5% -> 312.81 | M15: PAGO | O15: Compra | Q15: Razão | U15: Compra | Y15: =V16*5% -> 0 | AB15: Compra | AD15: Razão | AI15: Compra | AM15: =AJ16*5% -> 0 | AP15: Compra | AR15: Razão | AV15: Compra | AY15: =AW16*2.5% -> 0 | BC15: Compra | BE15: Razão | BI15: Compra | BL15: =BJ16*2.5% -> 0 | BP15: Compra | BR15: Razão | BV15: Compra | BY15: =BW16*2.5% -> 0 | CC15: Compra | CE15: Razão | CI15: Compra | CL15: =CJ16*2.5% -> 0 | CP15: Compra | CR15: Razão | CV15: Compra | CY15: =CW16*2.5% -> 0 | DC15: Compra | DE15: Razão | DI15: Compra | DL15: =DJ16*2.5% -> 0 | DP15: Compra | DR15: Razão | DV15: Compra | DY15: =DW16*2.5% -> 0 | EC15: Compra | EE15: Razão | EI15: Compra | EL15: =EJ16*2.5% -> 0 | EP15: Compra | ER15: Razão | EV15: Compra | EY15: =EW16*2.5% -> 0 | FC15: Compra | FE15: Razão | FI15: Compra | FL15: =FJ16*2.5% -> 0 | FP15: Compra | FR15: Razão | FV15: Compra | FY15: =FW16*2.5% -> 0 | GC15: Compra | GE15: Razão | GI15: Compra | GL15: =GJ16*2.5% -> 0
B16: Faturamento | C16: 45824 | D16: CNPJ: | E16: 20.963.243/0001-01 | H16: Faturamento | I16: 6256.2 | O16: Faturamento | Q16: CNPJ: | U16: Faturamento | AB16: Faturamento | AD16: CNPJ: | AI16: Faturamento | AP16: Faturamento | AR16: CNPJ: | AV16: Faturamento | BC16: Faturamento | BE16: CNPJ: | BI16: Faturamento | BP16: Faturamento | BR16: CNPJ: | BV16: Faturamento | CC16: Faturamento | CE16: CNPJ: | CI16: Faturamento | CP16: Faturamento | CR16: CNPJ: | CV16: Faturamento | DC16: Faturamento | DE16: CNPJ: | DI16: Faturamento | DP16: Faturamento | DR16: CNPJ: | DV16: Faturamento | EC16: Faturamento | EE16: CNPJ: | EI16: Faturamento | EP16: Faturamento | ER16: CNPJ: | EV16: Faturamento | FC16: Faturamento | FE16: CNPJ: | FI16: Faturamento | FP16: Faturamento | FR16: CNPJ: | FV16: Faturamento | GC16: Faturamento | GE16: CNPJ: | GI16: Faturamento
B18: Compra | C18: 45832 | D18: Razão | E18: COMERCIAL MARTINS E MARTINS | F18: 250624104438099 | G18: 1471 | H18: Compra | I18: 16124.42 | J18: 2 | K18: PRAZO | L18: =I19*5% -> 806.221 | M18: FATURADO | O18: Compra | Q18: Razão | U18: Compra | Y18: =V19*5% -> 0 | AB18: Compra | AD18: Razão | AI18: Compra | AM18: =AJ19*5% -> 0 | AP18: Compra | AR18: Razão | AV18: Compra | AY18: =AW19*2.5% -> 0 | BC18: Compra | BE18: Razão | BI18: Compra | BL18: =BJ19*2.5% -> 0 | BP18: Compra | BR18: Razão | BV18: Compra | BY18: =BW19*2.5% -> 0 | CC18: Compra | CE18: Razão | CI18: Compra | CL18: =CJ19*2.5% -> 0 | CP18: Compra | CR18: Razão | CV18: Compra | CY18: =CW19*2.5% -> 0 | DC18: Compra | DE18: Razão | DI18: Compra | DL18: =DJ19*2.5% -> 0 | DP18: Compra | DR18: Razão | DV18: Compra | DY18: =DW19*2.5% -> 0 | EC18: Compra | EE18: Razão | EI18: Compra | EL18: =EJ19*2.5% -> 0 | EP18: Compra | ER18: Razão | EV18: Compra | EY18: =EW19*2.5% -> 0 | FC18: Compra | FE18: Razão | FI18: Compra | FL18: =FJ19*2.5% -> 0 | FP18: Compra | FR18: Razão | FV18: Compra | FY18: =FW19*2.5% -> 0 | GC18: Compra | GE18: Razão | GI18: Compra | GL18: =GJ19*2.5% -> 0
B19: Faturamento | C19: 45833 | D19: CNPJ: | E19: 01.679.699/0001-20 | H19: Faturamento | I19: 16124.42 | O19: Faturamento | Q19: CNPJ: | U19: Faturamento | AB19: Faturamento | AD19: CNPJ: | AI19: Faturamento | AP19: Faturamento | AR19: CNPJ: | AV19: Faturamento | BC19: Faturamento | BE19: CNPJ: | BI19: Faturamento | BP19: Faturamento | BR19: CNPJ: | BV19: Faturamento | CC19: Faturamento | CE19: CNPJ: | CI19: Faturamento | CP19: Faturamento | CR19: CNPJ: | CV19: Faturamento | DC19: Faturamento | DE19: CNPJ: | DI19: Faturamento | DP19: Faturamento | DR19: CNPJ: | DV19: Faturamento | EC19: Faturamento | EE19: CNPJ: | EI19: Faturamento | EP19: Faturamento | ER19: CNPJ: | EV19: Faturamento | FC19: Faturamento | FE19: CNPJ: | FI19: Faturamento | FP19: Faturamento | FR19: CNPJ: | FV19: Faturamento | GC19: Faturamento | GE19: CNPJ: | GI19: Faturamento
B21: Compra | D21: Razão | H21: Compra | L21: =I22*5% -> 0 | O21: Compra | Q21: Razão | U21: Compra | Y21: =V22*5% -> 0 | AB21: Compra | AD21: Razão | AI21: Compra | AM21: =AJ22*5% -> 0 | AP21: Compra | AR21: Razão | AV21: Compra | AY21: =AW22*2.5% -> 0 | BC21: Compra | BE21: Razão | BI21: Compra | BL21: =BJ22*2.5% -> 0 | BP21: Compra | BR21: Razão | BV21: Compra | BY21: =BW22*2.5% -> 0 | CC21: Compra | CE21: Razão | CI21: Compra | CL21: =CJ22*2.5% -> 0 | CP21: Compra | CR21: Razão | CV21: Compra | CY21: =CW22*2.5% -> 0 | DC21: Compra | DE21: Razão | DI21: Compra | DL21: =DJ22*2.5% -> 0 | DP21: Compra | DR21: Razão | DV21: Compra | DY21: =DW22*2.5% -> 0 | EC21: Compra | EE21: Razão | EI21: Compra | EL21: =EJ22*2.5% -> 0 | EP21: Compra | ER21: Razão | EV21: Compra | EY21: =EW22*2.5% -> 0 | FC21: Compra | FE21: Razão | FI21: Compra | FL21: =FJ22*2.5% -> 0 | FP21: Compra | FR21: Razão | FV21: Compra | FY21: =FW22*2.5% -> 0 | GC21: Compra | GE21: Razão | GI21: Compra | GL21: =GJ22*2.5% -> 0
B22: Faturamento | D22: CNPJ: | H22: Faturamento | O22: Faturamento | Q22: CNPJ: | U22: Faturamento | AB22: Faturamento | AD22: CNPJ: | AI22: Faturamento | AP22: Faturamento | AR22: CNPJ: | AV22: Faturamento | BC22: Faturamento | BE22: CNPJ: | BI22: Faturamento | BP22: Faturamento | BR22: CNPJ: | BV22: Faturamento | CC22: Faturamento | CE22: CNPJ: | CI22: Faturamento | CP22: Faturamento | CR22: CNPJ: | CV22: Faturamento | DC22: Faturamento | DE22: CNPJ: | DI22: Faturamento | DP22: Faturamento | DR22: CNPJ: | DV22: Faturamento | EC22: Faturamento | EE22: CNPJ: | EI22: Faturamento | EP22: Faturamento | ER22: CNPJ: | EV22: Faturamento | FC22: Faturamento | FE22: CNPJ: | FI22: Faturamento | FP22: Faturamento | FR22: CNPJ: | FV22: Faturamento | GC22: Faturamento | GE22: CNPJ: | GI22: Faturamento
B24: Compra | D24: Razão | H24: Compra | L24: =I25*5% -> 0 | O24: Compra | Q24: Razão | U24: Compra | Y24: =V25*5% -> 0 | AB24: Compra | AD24: Razão | AI24: Compra | AM24: =AJ25*5% -> 0 | AP24: Compra | AR24: Razão | AV24: Compra | AY24: =AW25*2.5% -> 0 | BC24: Compra | BE24: Razão | BI24: Compra | BL24: =BJ25*2.5% -> 0 | BP24: Compra | BR24: Razão | BV24: Compra | BY24: =BW25*2.5% -> 0 | CC24: Compra | CE24: Razão | CI24: Compra | CL24: =CJ25*2.5% -> 0 | CP24: Compra | CR24: Razão | CV24: Compra | CY24: =CW25*2.5% -> 0 | DC24: Compra | DE24: Razão | DI24: Compra | DL24: =DJ25*2.5% -> 0 | DP24: Compra | DR24: Razão | DV24: Compra | DY24: =DW25*2.5% -> 0 | EC24: Compra | EE24: Razão | EI24: Compra | EL24: =EJ25*2.5% -> 0 | EP24: Compra | ER24: Razão | EV24: Compra | EY24: =EW25*2.5% -> 0 | FC24: Compra | FE24: Razão | FI24: Compra | FL24: =FJ25*2.5% -> 0 | FP24: Compra | FR24: Razão | FV24: Compra | FY24: =FW25*2.5% -> 0 | GC24: Compra | GE24: Razão | GI24: Compra | GL24: =GJ25*2.5% -> 0
B25: Faturamento | D25: CNPJ: | H25: Faturamento | O25: Faturamento | Q25: CNPJ: | U25: Faturamento | AB25: Faturamento | AD25: CNPJ: | AI25: Faturamento | AP25: Faturamento | AR25: CNPJ: | AV25: Faturamento | BC25: Faturamento | BE25: CNPJ: | BI25: Faturamento | BP25: Faturamento | BR25: CNPJ: | BV25: Faturamento | CC25: Faturamento | CE25: CNPJ: | CI25: Faturamento | CP25: Faturamento | CR25: CNPJ: | CV25: Faturamento | DC25: Faturamento | DE25: CNPJ: | DI25: Faturamento | DP25: Faturamento | DR25: CNPJ: | DV25: Faturamento | EC25: Faturamento | EE25: CNPJ: | EI25: Faturamento | EP25: Faturamento | ER25: CNPJ: | EV25: Faturamento | FC25: Faturamento | FE25: CNPJ: | FI25: Faturamento | FP25: Faturamento | FR25: CNPJ: | FV25: Faturamento | GC25: Faturamento | GE25: CNPJ: | GI25: Faturamento
B27: Compra | D27: Razão | H27: Compra | L27: =I28*5% -> 0 | O27: Compra | Q27: Razão | U27: Compra | Y27: =V28*5% -> 0 | AB27: Compra | AD27: Razão | AI27: Compra | AM27: =AJ28*5% -> 0 | AP27: Compra | AR27: Razão | AV27: Compra | AY27: =AW28*2.5% -> 0 | BC27: Compra | BE27: Razão | BI27: Compra | BL27: =BJ28*2.5% -> 0 | BP27: Compra | BR27: Razão | BV27: Compra | BY27: =BW28*2.5% -> 0 | CC27: Compra | CE27: Razão | CI27: Compra | CL27: =CJ28*2.5% -> 0 | CP27: Compra | CR27: Razão | CV27: Compra | CY27: =CW28*2.5% -> 0 | DC27: Compra | DE27: Razão | DI27: Compra | DL27: =DJ28*2.5% -> 0 | DP27: Compra | DR27: Razão | DV27: Compra | DY27: =DW28*2.5% -> 0 | EC27: Compra | EE27: Razão | EI27: Compra | EL27: =EJ28*2.5% -> 0 | EP27: Compra | ER27: Razão | EV27: Compra | EY27: =EW28*2.5% -> 0 | FC27: Compra | FE27: Razão | FI27: Compra | FL27: =FJ28*2.5% -> 0 | FP27: Compra | FR27: Razão | FV27: Compra | FY27: =FW28*2.5% -> 0 | GC27: Compra | GE27: Razão | GI27: Compra | GL27: =GJ28*2.5% -> 0
B28: Faturamento | D28: CNPJ: | H28: Faturamento | O28: Faturamento | Q28: CNPJ: | U28: Faturamento | AB28: Faturamento | AD28: CNPJ: | AI28: Faturamento | AP28: Faturamento | AR28: CNPJ: | AV28: Faturamento | BC28: Faturamento | BE28: CNPJ: | BI28: Faturamento | BP28: Faturamento | BR28: CNPJ: | BV28: Faturamento | CC28: Faturamento | CE28: CNPJ: | CI28: Faturamento | CP28: Faturamento | CR28: CNPJ: | CV28: Faturamento | DC28: Faturamento | DE28: CNPJ: | DI28: Faturamento | DP28: Faturamento | DR28: CNPJ: | DV28: Faturamento | EC28: Faturamento | EE28: CNPJ: | EI28: Faturamento | EP28: Faturamento | ER28: CNPJ: | EV28: Faturamento | FC28: Faturamento | FE28: CNPJ: | FI28: Faturamento | FP28: Faturamento | FR28: CNPJ: | FV28: Faturamento | GC28: Faturamento | GE28: CNPJ: | GI28: Faturamento
B30: Compra | D30: Razão | H30: Compra | L30: =I31*5% -> 0 | O30: Compra | Q30: Razão | U30: Compra | Y30: =V31*5% -> 0 | AB30: Compra | AD30: Razão | AI30: Compra | AM30: =AJ31*5% -> 0 | AP30: Compra | AR30: Razão | AV30: Compra | AY30: =AW31*2.5% -> 0 | BC30: Compra | BE30: Razão | BI30: Compra | BL30: =BJ31*2.5% -> 0 | BP30: Compra | BR30: Razão | BV30: Compra | BY30: =BW31*2.5% -> 0 | CC30: Compra | CE30: Razão | CI30: Compra | CL30: =CJ31*2.5% -> 0 | CP30: Compra | CR30: Razão | CV30: Compra | CY30: =CW31*2.5% -> 0 | DC30: Compra | DE30: Razão | DI30: Compra | DL30: =DJ31*2.5% -> 0 | DP30: Compra | DR30: Razão | DV30: Compra | DY30: =DW31*2.5% -> 0 | EC30: Compra | EE30: Razão | EI30: Compra | EL30: =EJ31*2.5% -> 0 | EP30: Compra | ER30: Razão | EV30: Compra | EY30: =EW31*2.5% -> 0 | FC30: Compra | FE30: Razão | FI30: Compra | FL30: =FJ31*2.5% -> 0 | FP30: Compra | FR30: Razão | FV30: Compra | FY30: =FW31*2.5% -> 0 | GC30: Compra | GE30: Razão | GI30: Compra | GL30: =GJ31*2.5% -> 0
B31: Faturamento | D31: CNPJ: | H31: Faturamento | O31: Faturamento | Q31: CNPJ: | U31: Faturamento | AB31: Faturamento | AD31: CNPJ: | AI31: Faturamento | AP31: Faturamento | AR31: CNPJ: | AV31: Faturamento | BC31: Faturamento | BE31: CNPJ: | BI31: Faturamento | BP31: Faturamento | BR31: CNPJ: | BV31: Faturamento | CC31: Faturamento | CE31: CNPJ: | CI31: Faturamento | CP31: Faturamento | CR31: CNPJ: | CV31: Faturamento | DC31: Faturamento | DE31: CNPJ: | DI31: Faturamento | DP31: Faturamento | DR31: CNPJ: | DV31: Faturamento | EC31: Faturamento | EE31: CNPJ: | EI31: Faturamento | EP31: Faturamento | ER31: CNPJ: | EV31: Faturamento | FC31: Faturamento | FE31: CNPJ: | FI31: Faturamento | FP31: Faturamento | FR31: CNPJ: | FV31: Faturamento | GC31: Faturamento | GE31: CNPJ: | GI31: Faturamento
B33: Compra | D33: Razão | H33: Compra | L33: =I34*5% -> 0 | O33: Compra | Q33: Razão | U33: Compra | Y33: =V34*5% -> 0 | AB33: Compra | AD33: Razão | AI33: Compra | AM33: =AJ34*5% -> 0 | AP33: Compra | AR33: Razão | AV33: Compra | AY33: =AW34*2.5% -> 0 | BC33: Compra | BE33: Razão | BI33: Compra | BL33: =BJ34*2.5% -> 0 | BP33: Compra | BR33: Razão | BV33: Compra | BY33: =BW34*2.5% -> 0 | CC33: Compra | CE33: Razão | CI33: Compra | CL33: =CJ34*2.5% -> 0 | CP33: Compra | CR33: Razão | CV33: Compra | CY33: =CW34*2.5% -> 0 | DC33: Compra | DE33: Razão | DI33: Compra | DL33: =DJ34*2.5% -> 0 | DP33: Compra | DR33: Razão | DV33: Compra | DY33: =DW34*2.5% -> 0 | EC33: Compra | EE33: Razão | EI33: Compra | EL33: =EJ34*2.5% -> 0 | EP33: Compra | ER33: Razão | EV33: Compra | EY33: =EW34*2.5% -> 0 | FC33: Compra | FE33: Razão | FI33: Compra | FL33: =FJ34*2.5% -> 0 | FP33: Compra | FR33: Razão | FV33: Compra | FY33: =FW34*2.5% -> 0 | GC33: Compra | GE33: Razão | GI33: Compra | GL33: =GJ34*2.5% -> 0
B34: Faturamento | D34: CNPJ: | H34: Faturamento | O34: Faturamento | Q34: CNPJ: | U34: Faturamento | AB34: Faturamento | AD34: CNPJ: | AI34: Faturamento | AP34: Faturamento | AR34: CNPJ: | AV34: Faturamento | BC34: Faturamento | BE34: CNPJ: | BI34: Faturamento | BP34: Faturamento | BR34: CNPJ: | BV34: Faturamento | CC34: Faturamento | CE34: CNPJ: | CI34: Faturamento | CP34: Faturamento | CR34: CNPJ: | CV34: Faturamento | DC34: Faturamento | DE34: CNPJ: | DI34: Faturamento | DP34: Faturamento | DR34: CNPJ: | DV34: Faturamento | EC34: Faturamento | EE34: CNPJ: | EI34: Faturamento | EP34: Faturamento | ER34: CNPJ: | EV34: Faturamento | FC34: Faturamento | FE34: CNPJ: | FI34: Faturamento | FP34: Faturamento | FR34: CNPJ: | FV34: Faturamento | GC34: Faturamento | GE34: CNPJ: | GI34: Faturamento
B36: Compra | D36: Razão | H36: Compra | L36: =I37*5% -> 0 | O36: Compra | Q36: Razão | U36: Compra | Y36: =V37*5% -> 0 | AB36: Compra | AD36: Razão | AI36: Compra | AM36: =AJ37*5% -> 0 | AP36: Compra | AR36: Razão | AV36: Compra | AY36: =AW37*2.5% -> 0 | BC36: Compra | BE36: Razão | BI36: Compra | BL36: =BJ37*2.5% -> 0 | BP36: Compra | BR36: Razão | BV36: Compra | BY36: =BW37*2.5% -> 0 | CC36: Compra | CE36: Razão | CI36: Compra | CL36: =CJ37*2.5% -> 0 | CP36: Compra | CR36: Razão | CV36: Compra | CY36: =CW37*2.5% -> 0 | DC36: Compra | DE36: Razão | DI36: Compra | DL36: =DJ37*2.5% -> 0 | DP36: Compra | DR36: Razão | DV36: Compra | DY36: =DW37*2.5% -> 0 | EC36: Compra | EE36: Razão | EI36: Compra | EL36: =EJ37*2.5% -> 0 | EP36: Compra | ER36: Razão | EV36: Compra | EY36: =EW37*2.5% -> 0 | FC36: Compra | FE36: Razão | FI36: Compra | FL36: =FJ37*2.5% -> 0 | FP36: Compra | FR36: Razão | FV36: Compra | FY36: =FW37*2.5% -> 0 | GC36: Compra | GE36: Razão | GI36: Compra | GL36: =GJ37*2.5% -> 0
B37: Faturamento | D37: CNPJ: | H37: Faturamento | O37: Faturamento | Q37: CNPJ: | U37: Faturamento | AB37: Faturamento | AD37: CNPJ: | AI37: Faturamento | AP37: Faturamento | AR37: CNPJ: | AV37: Faturamento | BC37: Faturamento | BE37: CNPJ: | BI37: Faturamento | BP37: Faturamento | BR37: CNPJ: | BV37: Faturamento | CC37: Faturamento | CE37: CNPJ: | CI37: Faturamento | CP37: Faturamento | CR37: CNPJ: | CV37: Faturamento | DC37: Faturamento | DE37: CNPJ: | DI37: Faturamento | DP37: Faturamento | DR37: CNPJ: | DV37: Faturamento | EC37: Faturamento | EE37: CNPJ: | EI37: Faturamento | EP37: Faturamento | ER37: CNPJ: | EV37: Faturamento | FC37: Faturamento | FE37: CNPJ: | FI37: Faturamento | FP37: Faturamento | FR37: CNPJ: | FV37: Faturamento | GC37: Faturamento | GE37: CNPJ: | GI37: Faturamento
B39: Compra | D39: Razão | H39: Compra | L39: =I40*5% -> 0 | O39: Compra | Q39: Razão | U39: Compra | Y39: =V40*5% -> 0 | AB39: Compra | AD39: Razão | AI39: Compra | AM39: =AJ40*5% -> 0 | AP39: Compra | AR39: Razão | AV39: Compra | AY39: =AW40*2.5% -> 0 | BC39: Compra | BE39: Razão | BI39: Compra | BL39: =BJ40*2.5% -> 0 | BP39: Compra | BR39: Razão | BV39: Compra | BY39: =BW40*2.5% -> 0 | CC39: Compra | CE39: Razão | CI39: Compra | CL39: =CJ40*2.5% -> 0 | CP39: Compra | CR39: Razão | CV39: Compra | CY39: =CW40*2.5% -> 0 | DC39: Compra | DE39: Razão | DI39: Compra | DL39: =DJ40*2.5% -> 0 | DP39: Compra | DR39: Razão | DV39: Compra | DY39: =DW40*2.5% -> 0 | EC39: Compra | EE39: Razão | EI39: Compra | EL39: =EJ40*2.5% -> 0 | EP39: Compra | ER39: Razão | EV39: Compra | EY39: =EW40*2.5% -> 0 | FC39: Compra | FE39: Razão | FI39: Compra | FL39: =FJ40*2.5% -> 0 | FP39: Compra | FR39: Razão | FV39: Compra | FY39: =FW40*2.5% -> 0 | GC39: Compra | GE39: Razão | GI39: Compra | GL39: =GJ40*2.5% -> 0
B40: Faturamento | D40: CNPJ: | H40: Faturamento | O40: Faturamento | Q40: CNPJ: | U40: Faturamento | AB40: Faturamento | AD40: CNPJ: | AI40: Faturamento | AP40: Faturamento | AR40: CNPJ: | AV40: Faturamento | BC40: Faturamento | BE40: CNPJ: | BI40: Faturamento | BP40: Faturamento | BR40: CNPJ: | BV40: Faturamento | CC40: Faturamento | CE40: CNPJ: | CI40: Faturamento | CP40: Faturamento | CR40: CNPJ: | CV40: Faturamento | DC40: Faturamento | DE40: CNPJ: | DI40: Faturamento | DP40: Faturamento | DR40: CNPJ: | DV40: Faturamento | EC40: Faturamento | EE40: CNPJ: | EI40: Faturamento | EP40: Faturamento | ER40: CNPJ: | EV40: Faturamento | FC40: Faturamento | FE40: CNPJ: | FI40: Faturamento | FP40: Faturamento | FR40: CNPJ: | FV40: Faturamento | GC40: Faturamento | GE40: CNPJ: | GI40: Faturamento
B42: Compra | D42: Razão | H42: Compra | L42: =I43*5% -> 0 | O42: Compra | Q42: Razão | U42: Compra | Y42: =V43*5% -> 0 | AB42: Compra | AD42: Razão | AI42: Compra | AM42: =AJ43*5% -> 0 | AP42: Compra | AR42: Razão | AV42: Compra | AY42: =AW43*2.5% -> 0 | BC42: Compra | BE42: Razão | BI42: Compra | BL42: =BJ43*2.5% -> 0 | BP42: Compra | BR42: Razão | BV42: Compra | BY42: =BW43*2.5% -> 0 | CC42: Compra | CE42: Razão | CI42: Compra | CL42: =CJ43*2.5% -> 0 | CP42: Compra | CR42: Razão | CV42: Compra | CY42: =CW43*2.5% -> 0 | DC42: Compra | DE42: Razão | DI42: Compra | DL42: =DJ43*2.5% -> 0 | DP42: Compra | DR42: Razão | DV42: Compra | DY42: =DW43*2.5% -> 0 | EC42: Compra | EE42: Razão | EI42: Compra | EL42: =EJ43*2.5% -> 0 | EP42: Compra | ER42: Razão | EV42: Compra | EY42: =EW43*2.5% -> 0 | FC42: Compra | FE42: Razão | FI42: Compra | FL42: =FJ43*2.5% -> 0 | FP42: Compra | FR42: Razão | FV42: Compra | FY42: =FW43*2.5% -> 0 | GC42: Compra | GE42: Razão | GI42: Compra | GL42: =GJ43*2.5% -> 0
B43: Faturamento | D43: CNPJ: | H43: Faturamento | O43: Faturamento | Q43: CNPJ: | U43: Faturamento | AB43: Faturamento | AD43: CNPJ: | AI43: Faturamento | AP43: Faturamento | AR43: CNPJ: | AV43: Faturamento | BC43: Faturamento | BE43: CNPJ: | BI43: Faturamento | BP43: Faturamento | BR43: CNPJ: | BV43: Faturamento | CC43: Faturamento | CE43: CNPJ: | CI43: Faturamento | CP43: Faturamento | CR43: CNPJ: | CV43: Faturamento | DC43: Faturamento | DE43: CNPJ: | DI43: Faturamento | DP43: Faturamento | DR43: CNPJ: | DV43: Faturamento | EC43: Faturamento | EE43: CNPJ: | EI43: Faturamento | EP43: Faturamento | ER43: CNPJ: | EV43: Faturamento | FC43: Faturamento | FE43: CNPJ: | FI43: Faturamento | FP43: Faturamento | FR43: CNPJ: | FV43: Faturamento | GC43: Faturamento | GE43: CNPJ: | GI43: Faturamento
B45: Compra | D45: Razão | H45: Compra | L45: =I46*5% -> 0 | O45: Compra | Q45: Razão | U45: Compra | Y45: =V46*5% -> 0 | AB45: Compra | AD45: Razão | AI45: Compra | AM45: =AJ46*5% -> 0 | AP45: Compra | AR45: Razão | AV45: Compra | AY45: =AW46*2.5% -> 0 | BC45: Compra | BE45: Razão | BI45: Compra | BL45: =BJ46*2.5% -> 0 | BP45: Compra | BR45: Razão | BV45: Compra | BY45: =BW46*2.5% -> 0 | CC45: Compra | CE45: Razão | CI45: Compra | CL45: =CJ46*2.5% -> 0 | CP45: Compra | CR45: Razão | CV45: Compra | CY45: =CW46*2.5% -> 0 | DC45: Compra | DE45: Razão | DI45: Compra | DL45: =DJ46*2.5% -> 0 | DP45: Compra | DR45: Razão | DV45: Compra | DY45: =DW46*2.5% -> 0 | EC45: Compra | EE45: Razão | EI45: Compra | EL45: =EJ46*2.5% -> 0 | EP45: Compra | ER45: Razão | EV45: Compra | EY45: =EW46*2.5% -> 0 | FC45: Compra | FE45: Razão | FI45: Compra | FL45: =FJ46*2.5% -> 0 | FP45: Compra | FR45: Razão | FV45: Compra | FY45: =FW46*2.5% -> 0 | GC45: Compra | GE45: Razão | GI45: Compra | GL45: =GJ46*2.5% -> 0
B46: Faturamento | D46: CNPJ: | H46: Faturamento | O46: Faturamento | Q46: CNPJ: | U46: Faturamento | AB46: Faturamento | AD46: CNPJ: | AI46: Faturamento | AP46: Faturamento | AR46: CNPJ: | AV46: Faturamento | BC46: Faturamento | BE46: CNPJ: | BI46: Faturamento | BP46: Faturamento | BR46: CNPJ: | BV46: Faturamento | CC46: Faturamento | CE46: CNPJ: | CI46: Faturamento | CP46: Faturamento | CR46: CNPJ: | CV46: Faturamento | DC46: Faturamento | DE46: CNPJ: | DI46: Faturamento | DP46: Faturamento | DR46: CNPJ: | DV46: Faturamento | EC46: Faturamento | EE46: CNPJ: | EI46: Faturamento | EP46: Faturamento | ER46: CNPJ: | EV46: Faturamento | FC46: Faturamento | FE46: CNPJ: | FI46: Faturamento | FP46: Faturamento | FR46: CNPJ: | FV46: Faturamento | GC46: Faturamento | GE46: CNPJ: | GI46: Faturamento
B48: Compra | D48: Razão | H48: Compra | L48: =I49*5% -> 0 | O48: Compra | Q48: Razão | U48: Compra | Y48: =V49*5% -> 0 | AB48: Compra | AD48: Razão | AI48: Compra | AM48: =AJ49*5% -> 0 | AP48: Compra | AR48: Razão | AV48: Compra | AY48: =AW49*2.5% -> 0 | BC48: Compra | BE48: Razão | BI48: Compra | BL48: =BJ49*2.5% -> 0 | BP48: Compra | BR48: Razão | BV48: Compra | BY48: =BW49*2.5% -> 0 | CC48: Compra | CE48: Razão | CI48: Compra | CL48: =CJ49*2.5% -> 0 | CP48: Compra | CR48: Razão | CV48: Compra | CY48: =CW49*2.5% -> 0 | DC48: Compra | DE48: Razão | DI48: Compra | DL48: =DJ49*2.5% -> 0 | DP48: Compra | DR48: Razão | DV48: Compra | DY48: =DW49*2.5% -> 0 | EC48: Compra | EE48: Razão | EI48: Compra | EL48: =EJ49*2.5% -> 0 | EP48: Compra | ER48: Razão | EV48: Compra | EY48: =EW49*2.5% -> 0 | FC48: Compra | FE48: Razão | FI48: Compra | FL48: =FJ49*2.5% -> 0 | FP48: Compra | FR48: Razão | FV48: Compra | FY48: =FW49*2.5% -> 0 | GC48: Compra | GE48: Razão | GI48: Compra | GL48: =GJ49*2.5% -> 0
B49: Faturamento | D49: CNPJ: | H49: Faturamento | O49: Faturamento | Q49: CNPJ: | U49: Faturamento | AB49: Faturamento | AD49: CNPJ: | AI49: Faturamento | AP49: Faturamento | AR49: CNPJ: | AV49: Faturamento | BC49: Faturamento | BE49: CNPJ: | BI49: Faturamento | BP49: Faturamento | BR49: CNPJ: | BV49: Faturamento | CC49: Faturamento | CE49: CNPJ: | CI49: Faturamento | CP49: Faturamento | CR49: CNPJ: | CV49: Faturamento | DC49: Faturamento | DE49: CNPJ: | DI49: Faturamento | DP49: Faturamento | DR49: CNPJ: | DV49: Faturamento | EC49: Faturamento | EE49: CNPJ: | EI49: Faturamento | EP49: Faturamento | ER49: CNPJ: | EV49: Faturamento | FC49: Faturamento | FE49: CNPJ: | FI49: Faturamento | FP49: Faturamento | FR49: CNPJ: | FV49: Faturamento | GC49: Faturamento | GE49: CNPJ: | GI49: Faturamento
B51: Compra | D51: Razão | H51: Compra | L51: =I52*5% -> 0 | O51: Compra | Q51: Razão | U51: Compra | Y51: =V52*5% -> 0 | AB51: Compra | AD51: Razão | AI51: Compra | AM51: =AJ52*5% -> 0 | AP51: Compra | AR51: Razão | AV51: Compra | AY51: =AW52*2.5% -> 0 | BC51: Compra | BE51: Razão | BI51: Compra | BL51: =BJ52*2.5% -> 0 | BP51: Compra | BR51: Razão | BV51: Compra | BY51: =BW52*2.5% -> 0 | CC51: Compra | CE51: Razão | CI51: Compra | CL51: =CJ52*2.5% -> 0 | CP51: Compra | CR51: Razão | CV51: Compra | CY51: =CW52*2.5% -> 0 | DC51: Compra | DE51: Razão | DI51: Compra | DL51: =DJ52*2.5% -> 0 | DP51: Compra | DR51: Razão | DV51: Compra | DY51: =DW52*2.5% -> 0 | EC51: Compra | EE51: Razão | EI51: Compra | EL51: =EJ52*2.5% -> 0 | EP51: Compra | ER51: Razão | EV51: Compra | EY51: =EW52*2.5% -> 0 | FC51: Compra | FE51: Razão | FI51: Compra | FL51: =FJ52*2.5% -> 0 | FP51: Compra | FR51: Razão | FV51: Compra | FY51: =FW52*2.5% -> 0 | GC51: Compra | GE51: Razão | GI51: Compra | GL51: =GJ52*2.5% -> 0
B52: Faturamento | D52: CNPJ: | H52: Faturamento | O52: Faturamento | Q52: CNPJ: | U52: Faturamento | AB52: Faturamento | AD52: CNPJ: | AI52: Faturamento | AP52: Faturamento | AR52: CNPJ: | AV52: Faturamento | BC52: Faturamento | BE52: CNPJ: | BI52: Faturamento | BP52: Faturamento | BR52: CNPJ: | BV52: Faturamento | CC52: Faturamento | CE52: CNPJ: | CI52: Faturamento | CP52: Faturamento | CR52: CNPJ: | CV52: Faturamento | DC52: Faturamento | DE52: CNPJ: | DI52: Faturamento | DP52: Faturamento | DR52: CNPJ: | DV52: Faturamento | EC52: Faturamento | EE52: CNPJ: | EI52: Faturamento | EP52: Faturamento | ER52: CNPJ: | EV52: Faturamento | FC52: Faturamento | FE52: CNPJ: | FI52: Faturamento | FP52: Faturamento | FR52: CNPJ: | FV52: Faturamento | GC52: Faturamento | GE52: CNPJ: | GI52: Faturamento
B54: Compra | D54: Razão | H54: Compra | L54: =I55*5% -> 0 | O54: Compra | Q54: Razão | U54: Compra | Y54: =V55*5% -> 0 | AB54: Compra | AD54: Razão | AI54: Compra | AM54: =AJ55*5% -> 0 | AP54: Compra | AR54: Razão | AV54: Compra | AY54: =AW55*2.5% -> 0 | BC54: Compra | BE54: Razão | BI54: Compra | BL54: =BJ55*2.5% -> 0 | BP54: Compra | BR54: Razão | BV54: Compra | BY54: =BW55*2.5% -> 0 | CC54: Compra | CE54: Razão | CI54: Compra | CL54: =CJ55*2.5% -> 0 | CP54: Compra | CR54: Razão | CV54: Compra | CY54: =CW55*2.5% -> 0 | DC54: Compra | DE54: Razão | DI54: Compra | DL54: =DJ55*2.5% -> 0 | DP54: Compra | DR54: Razão | DV54: Compra | DY54: =DW55*2.5% -> 0 | EC54: Compra | EE54: Razão | EI54: Compra | EL54: =EJ55*2.5% -> 0 | EP54: Compra | ER54: Razão | EV54: Compra | EY54: =EW55*2.5% -> 0 | FC54: Compra | FE54: Razão | FI54: Compra | FL54: =FJ55*2.5% -> 0 | FP54: Compra | FR54: Razão | FV54: Compra | FY54: =FW55*2.5% -> 0 | GC54: Compra | GE54: Razão | GI54: Compra | GL54: =GJ55*2.5% -> 0
B55: Faturamento | D55: CNPJ: | H55: Faturamento | O55: Faturamento | Q55: CNPJ: | U55: Faturamento | AB55: Faturamento | AD55: CNPJ: | AI55: Faturamento | AP55: Faturamento | AR55: CNPJ: | AV55: Faturamento | BC55: Faturamento | BE55: CNPJ: | BI55: Faturamento | BP55: Faturamento | BR55: CNPJ: | BV55: Faturamento | CC55: Faturamento | CE55: CNPJ: | CI55: Faturamento | CP55: Faturamento | CR55: CNPJ: | CV55: Faturamento | DC55: Faturamento | DE55: CNPJ: | DI55: Faturamento | DP55: Faturamento | DR55: CNPJ: | DV55: Faturamento | EC55: Faturamento | EE55: CNPJ: | EI55: Faturamento | EP55: Faturamento | ER55: CNPJ: | EV55: Faturamento | FC55: Faturamento | FE55: CNPJ: | FI55: Faturamento | FP55: Faturamento | FR55: CNPJ: | FV55: Faturamento | GC55: Faturamento | GE55: CNPJ: | GI55: Faturamento
B57: Compra | D57: Razão | H57: Compra | L57: =I58*5% -> 0 | O57: Compra | Q57: Razão | U57: Compra | Y57: =V58*5% -> 0 | AB57: Compra | AD57: Razão | AI57: Compra | AM57: =AJ58*5% -> 0 | AP57: Compra | AR57: Razão | AV57: Compra | AY57: =AW58*2.5% -> 0 | BC57: Compra | BE57: Razão | BI57: Compra | BL57: =BJ58*2.5% -> 0 | BP57: Compra | BR57: Razão | BV57: Compra | BY57: =BW58*2.5% -> 0 | CC57: Compra | CE57: Razão | CI57: Compra | CL57: =CJ58*2.5% -> 0 | CP57: Compra | CR57: Razão | CV57: Compra | CY57: =CW58*2.5% -> 0 | DC57: Compra | DE57: Razão | DI57: Compra | DL57: =DJ58*2.5% -> 0 | DP57: Compra | DR57: Razão | DV57: Compra | DY57: =DW58*2.5% -> 0 | EC57: Compra | EE57: Razão | EI57: Compra | EL57: =EJ58*2.5% -> 0 | EP57: Compra | ER57: Razão | EV57: Compra | EY57: =EW58*2.5% -> 0 | FC57: Compra | FE57: Razão | FI57: Compra | FL57: =FJ58*2.5% -> 0 | FP57: Compra | FR57: Razão | FV57: Compra | FY57: =FW58*2.5% -> 0 | GC57: Compra | GE57: Razão | GI57: Compra | GL57: =GJ58*2.5% -> 0
B58: Faturamento | D58: CNPJ: | H58: Faturamento | O58: Faturamento | Q58: CNPJ: | U58: Faturamento | AB58: Faturamento | AD58: CNPJ: | AI58: Faturamento | AP58: Faturamento | AR58: CNPJ: | AV58: Faturamento | BC58: Faturamento | BE58: CNPJ: | BI58: Faturamento | BP58: Faturamento | BR58: CNPJ: | BV58: Faturamento | CC58: Faturamento | CE58: CNPJ: | CI58: Faturamento | CP58: Faturamento | CR58: CNPJ: | CV58: Faturamento | DC58: Faturamento | DE58: CNPJ: | DI58: Faturamento | DP58: Faturamento | DR58: CNPJ: | DV58: Faturamento | EC58: Faturamento | EE58: CNPJ: | EI58: Faturamento | EP58: Faturamento | ER58: CNPJ: | EV58: Faturamento | FC58: Faturamento | FE58: CNPJ: | FI58: Faturamento | FP58: Faturamento | FR58: CNPJ: | FV58: Faturamento | GC58: Faturamento | GE58: CNPJ: | GI58: Faturamento
B60: Compra | D60: Razão | H60: Compra | L60: =I61*5% -> 0 | O60: Compra | Q60: Razão | U60: Compra | Y60: =V61*5% -> 0 | AB60: Compra | AD60: Razão | AI60: Compra | AM60: =AJ61*5% -> 0 | AP60: Compra | AR60: Razão | AV60: Compra | AY60: =AW61*2.5% -> 0 | BC60: Compra | BE60: Razão | BI60: Compra | BL60: =BJ61*2.5% -> 0 | BP60: Compra | BR60: Razão | BV60: Compra | BY60: =BW61*2.5% -> 0 | CC60: Compra | CE60: Razão | CI60: Compra | CL60: =CJ61*2.5% -> 0 | CP60: Compra | CR60: Razão | CV60: Compra | CY60: =CW61*2.5% -> 0 | DC60: Compra | DE60: Razão | DI60: Compra | DL60: =DJ61*2.5% -> 0 | DP60: Compra | DR60: Razão | DV60: Compra | DY60: =DW61*2.5% -> 0 | EC60: Compra | EE60: Razão | EI60: Compra | EL60: =EJ61*2.5% -> 0 | EP60: Compra | ER60: Razão | EV60: Compra | EY60: =EW61*2.5% -> 0 | FC60: Compra | FE60: Razão | FI60: Compra | FL60: =FJ61*2.5% -> 0 | FP60: Compra | FR60: Razão | FV60: Compra | FY60: =FW61*2.5% -> 0 | GC60: Compra | GE60: Razão | GI60: Compra | GL60: =GJ61*2.5% -> 0
B61: Faturamento | D61: CNPJ: | H61: Faturamento | O61: Faturamento | Q61: CNPJ: | U61: Faturamento | AB61: Faturamento | AD61: CNPJ: | AI61: Faturamento | AP61: Faturamento | AR61: CNPJ: | AV61: Faturamento | BC61: Faturamento | BE61: CNPJ: | BI61: Faturamento | BP61: Faturamento | BR61: CNPJ: | BV61: Faturamento | CC61: Faturamento | CE61: CNPJ: | CI61: Faturamento | CP61: Faturamento | CR61: CNPJ: | CV61: Faturamento | DC61: Faturamento | DE61: CNPJ: | DI61: Faturamento | DP61: Faturamento | DR61: CNPJ: | DV61: Faturamento | EC61: Faturamento | EE61: CNPJ: | EI61: Faturamento | EP61: Faturamento | ER61: CNPJ: | EV61: Faturamento | FC61: Faturamento | FE61: CNPJ: | FI61: Faturamento | FP61: Faturamento | FR61: CNPJ: | FV61: Faturamento | GC61: Faturamento | GE61: CNPJ: | GI61: Faturamento
AP63: Compra | AR63: Razão | AV63: Compra | AY63: =AW64*2.5% -> 0 | BC63: Compra | BE63: Razão | BI63: Compra | BL63: =BJ64*2.5% -> 0 | BP63: Compra | BR63: Razão | BV63: Compra | BY63: =BW64*2.5% -> 0 | CC63: Compra | CE63: Razão | CI63: Compra | CL63: =CJ64*2.5% -> 0 | CP63: Compra | CR63: Razão | CV63: Compra | CY63: =CW64*2.5% -> 0 | DC63: Compra | DE63: Razão | DI63: Compra | DL63: =DJ64*2.5% -> 0 | DP63: Compra | DR63: Razão | DV63: Compra | DY63: =DW64*2.5% -> 0 | EC63: Compra | EE63: Razão | EI63: Compra | EL63: =EJ64*2.5% -> 0 | EP63: Compra | ER63: Razão | EV63: Compra | EY63: =EW64*2.5% -> 0 | FC63: Compra | FE63: Razão | FI63: Compra | FL63: =FJ64*2.5% -> 0 | FP63: Compra | FR63: Razão | FV63: Compra | FY63: =FW64*2.5% -> 0 | GC63: Compra | GE63: Razão | GI63: Compra | GL63: =GJ64*2.5% -> 0
AP64: Faturamento | AR64: CNPJ: | AV64: Faturamento | BC64: Faturamento | BE64: CNPJ: | BI64: Faturamento | BP64: Faturamento | BR64: CNPJ: | BV64: Faturamento | CC64: Faturamento | CE64: CNPJ: | CI64: Faturamento | CP64: Faturamento | CR64: CNPJ: | CV64: Faturamento | DC64: Faturamento | DE64: CNPJ: | DI64: Faturamento | DP64: Faturamento | DR64: CNPJ: | DV64: Faturamento | EC64: Faturamento | EE64: CNPJ: | EI64: Faturamento | EP64: Faturamento | ER64: CNPJ: | EV64: Faturamento | FC64: Faturamento | FE64: CNPJ: | FI64: Faturamento | FP64: Faturamento | FR64: CNPJ: | FV64: Faturamento | GC64: Faturamento | GE64: CNPJ: | GI64: Faturamento
AP66: Compra | AR66: Razão | AV66: Compra | AY66: =AW67*2.5% -> 0 | BC66: Compra | BE66: Razão | BI66: Compra | BL66: =BJ67*2.5% -> 0 | BP66: Compra | BR66: Razão | BV66: Compra | BY66: =BW67*2.5% -> 0 | CC66: Compra | CE66: Razão | CI66: Compra | CL66: =CJ67*2.5% -> 0 | CP66: Compra | CR66: Razão | CV66: Compra | CY66: =CW67*2.5% -> 0 | DC66: Compra | DE66: Razão | DI66: Compra | DL66: =DJ67*2.5% -> 0 | DP66: Compra | DR66: Razão | DV66: Compra | DY66: =DW67*2.5% -> 0 | EC66: Compra | EE66: Razão | EI66: Compra | EL66: =EJ67*2.5% -> 0 | EP66: Compra | ER66: Razão | EV66: Compra | EY66: =EW67*2.5% -> 0 | FC66: Compra | FE66: Razão | FI66: Compra | FL66: =FJ67*2.5% -> 0 | FP66: Compra | FR66: Razão | FV66: Compra | FY66: =FW67*2.5% -> 0 | GC66: Compra | GE66: Razão | GI66: Compra | GL66: =GJ67*2.5% -> 0
AP67: Faturamento | AR67: CNPJ: | AV67: Faturamento | BC67: Faturamento | BE67: CNPJ: | BI67: Faturamento | BP67: Faturamento | BR67: CNPJ: | BV67: Faturamento | CC67: Faturamento | CE67: CNPJ: | CI67: Faturamento | CP67: Faturamento | CR67: CNPJ: | CV67: Faturamento | DC67: Faturamento | DE67: CNPJ: | DI67: Faturamento | DP67: Faturamento | DR67: CNPJ: | DV67: Faturamento | EC67: Faturamento | EE67: CNPJ: | EI67: Faturamento | EP67: Faturamento | ER67: CNPJ: | EV67: Faturamento | FC67: Faturamento | FE67: CNPJ: | FI67: Faturamento | FP67: Faturamento | FR67: CNPJ: | FV67: Faturamento | GC67: Faturamento | GE67: CNPJ: | GI67: Faturamento
AP69: Compra | AR69: Razão | AV69: Compra | AY69: =AW70*2.5% -> 0 | BC69: Compra | BE69: Razão | BI69: Compra | BL69: =BJ70*2.5% -> 0 | BP69: Compra | BR69: Razão | BV69: Compra | BY69: =BW70*2.5% -> 0 | CC69: Compra | CE69: Razão | CI69: Compra | CL69: =CJ70*2.5% -> 0 | CP69: Compra | CR69: Razão | CV69: Compra | CY69: =CW70*2.5% -> 0 | DC69: Compra | DE69: Razão | DI69: Compra | DL69: =DJ70*2.5% -> 0 | DP69: Compra | DR69: Razão | DV69: Compra | DY69: =DW70*2.5% -> 0 | EC69: Compra | EE69: Razão | EI69: Compra | EL69: =EJ70*2.5% -> 0 | EP69: Compra | ER69: Razão | EV69: Compra | EY69: =EW70*2.5% -> 0 | FC69: Compra | FE69: Razão | FI69: Compra | FL69: =FJ70*2.5% -> 0 | FP69: Compra | FR69: Razão | FV69: Compra | FY69: =FW70*2.5% -> 0 | GC69: Compra | GE69: Razão | GI69: Compra | GL69: =GJ70*2.5% -> 0
AP70: Faturamento | AR70: CNPJ: | AV70: Faturamento | BC70: Faturamento | BE70: CNPJ: | BI70: Faturamento | BP70: Faturamento | BR70: CNPJ: | BV70: Faturamento | CC70: Faturamento | CE70: CNPJ: | CI70: Faturamento | CP70: Faturamento | CR70: CNPJ: | CV70: Faturamento | DC70: Faturamento | DE70: CNPJ: | DI70: Faturamento | DP70: Faturamento | DR70: CNPJ: | DV70: Faturamento | EC70: Faturamento | EE70: CNPJ: | EI70: Faturamento | EP70: Faturamento | ER70: CNPJ: | EV70: Faturamento | FC70: Faturamento | FE70: CNPJ: | FI70: Faturamento | FP70: Faturamento | FR70: CNPJ: | FV70: Faturamento | GC70: Faturamento | GE70: CNPJ: | GI70: Faturamento
AP72: Compra | AR72: Razão | AV72: Compra | AY72: =AW73*2.5% -> 0 | BC72: Compra | BE72: Razão | BI72: Compra | BL72: =BJ73*2.5% -> 0 | BP72: Compra | BR72: Razão | BV72: Compra | BY72: =BW73*2.5% -> 0 | CC72: Compra | CE72: Razão | CI72: Compra | CL72: =CJ73*2.5% -> 0 | CP72: Compra | CR72: Razão | CV72: Compra | CY72: =CW73*2.5% -> 0 | DC72: Compra | DE72: Razão | DI72: Compra | DL72: =DJ73*2.5% -> 0 | DP72: Compra | DR72: Razão | DV72: Compra | DY72: =DW73*2.5% -> 0 | EC72: Compra | EE72: Razão | EI72: Compra | EL72: =EJ73*2.5% -> 0 | EP72: Compra | ER72: Razão | EV72: Compra | EY72: =EW73*2.5% -> 0 | FC72: Compra | FE72: Razão | FI72: Compra | FL72: =FJ73*2.5% -> 0 | FP72: Compra | FR72: Razão | FV72: Compra | FY72: =FW73*2.5% -> 0 | GC72: Compra | GE72: Razão | GI72: Compra | GL72: =GJ73*2.5% -> 0
AP73: Faturamento | AR73: CNPJ: | AV73: Faturamento | BC73: Faturamento | BE73: CNPJ: | BI73: Faturamento | BP73: Faturamento | BR73: CNPJ: | BV73: Faturamento | CC73: Faturamento | CE73: CNPJ: | CI73: Faturamento | CP73: Faturamento | CR73: CNPJ: | CV73: Faturamento | DC73: Faturamento | DE73: CNPJ: | DI73: Faturamento | DP73: Faturamento | DR73: CNPJ: | DV73: Faturamento | EC73: Faturamento | EE73: CNPJ: | EI73: Faturamento | EP73: Faturamento | ER73: CNPJ: | EV73: Faturamento | FC73: Faturamento | FE73: CNPJ: | FI73: Faturamento | FP73: Faturamento | FR73: CNPJ: | FV73: Faturamento | GC73: Faturamento | GE73: CNPJ: | GI73: Faturamento
AP75: Compra | AR75: Razão | AV75: Compra | AY75: =AW76*2.5% -> 0 | BC75: Compra | BE75: Razão | BI75: Compra | BL75: =BJ76*2.5% -> 0 | BP75: Compra | BR75: Razão | BV75: Compra | BY75: =BW76*2.5% -> 0 | CC75: Compra | CE75: Razão | CI75: Compra | CL75: =CJ76*2.5% -> 0 | CP75: Compra | CR75: Razão | CV75: Compra | CY75: =CW76*2.5% -> 0 | DC75: Compra | DE75: Razão | DI75: Compra | DL75: =DJ76*2.5% -> 0 | DP75: Compra | DR75: Razão | DV75: Compra | DY75: =DW76*2.5% -> 0 | EC75: Compra | EE75: Razão | EI75: Compra | EL75: =EJ76*2.5% -> 0 | EP75: Compra | ER75: Razão | EV75: Compra | EY75: =EW76*2.5% -> 0 | FC75: Compra | FE75: Razão | FI75: Compra | FL75: =FJ76*2.5% -> 0 | FP75: Compra | FR75: Razão | FV75: Compra | FY75: =FW76*2.5% -> 0 | GC75: Compra | GE75: Razão | GI75: Compra | GL75: =GJ76*2.5% -> 0
AP76: Faturamento | AR76: CNPJ: | AV76: Faturamento | BC76: Faturamento | BE76: CNPJ: | BI76: Faturamento | BP76: Faturamento | BR76: CNPJ: | BV76: Faturamento | CC76: Faturamento | CE76: CNPJ: | CI76: Faturamento | CP76: Faturamento | CR76: CNPJ: | CV76: Faturamento | DC76: Faturamento | DE76: CNPJ: | DI76: Faturamento | DP76: Faturamento | DR76: CNPJ: | DV76: Faturamento | EC76: Faturamento | EE76: CNPJ: | EI76: Faturamento | EP76: Faturamento | ER76: CNPJ: | EV76: Faturamento | FC76: Faturamento | FE76: CNPJ: | FI76: Faturamento | FP76: Faturamento | FR76: CNPJ: | FV76: Faturamento | GC76: Faturamento | GE76: CNPJ: | GI76: Faturamento
AP78: Compra | AR78: Razão | AV78: Compra | AY78: =AW79*2.5% -> 0 | BC78: Compra | BE78: Razão | BI78: Compra | BL78: =BJ79*2.5% -> 0 | BP78: Compra | BR78: Razão | BV78: Compra | BY78: =BW79*2.5% -> 0 | CC78: Compra | CE78: Razão | CI78: Compra | CL78: =CJ79*2.5% -> 0 | CP78: Compra | CR78: Razão | CV78: Compra | CY78: =CW79*2.5% -> 0 | DC78: Compra | DE78: Razão | DI78: Compra | DL78: =DJ79*2.5% -> 0 | DP78: Compra | DR78: Razão | DV78: Compra | DY78: =DW79*2.5% -> 0 | EC78: Compra | EE78: Razão | EI78: Compra | EL78: =EJ79*2.5% -> 0 | EP78: Compra | ER78: Razão | EV78: Compra | EY78: =EW79*2.5% -> 0 | FC78: Compra | FE78: Razão | FI78: Compra | FL78: =FJ79*2.5% -> 0 | FP78: Compra | FR78: Razão | FV78: Compra | FY78: =FW79*2.5% -> 0 | GC78: Compra | GE78: Razão | GI78: Compra | GL78: =GJ79*2.5% -> 0
AP79: Faturamento | AR79: CNPJ: | AV79: Faturamento | BC79: Faturamento | BE79: CNPJ: | BI79: Faturamento | BP79: Faturamento | BR79: CNPJ: | BV79: Faturamento | CC79: Faturamento | CE79: CNPJ: | CI79: Faturamento | CP79: Faturamento | CR79: CNPJ: | CV79: Faturamento | DC79: Faturamento | DE79: CNPJ: | DI79: Faturamento | DP79: Faturamento | DR79: CNPJ: | DV79: Faturamento | EC79: Faturamento | EE79: CNPJ: | EI79: Faturamento | EP79: Faturamento | ER79: CNPJ: | EV79: Faturamento | FC79: Faturamento | FE79: CNPJ: | FI79: Faturamento | FP79: Faturamento | FR79: CNPJ: | FV79: Faturamento | GC79: Faturamento | GE79: CNPJ: | GI79: Faturamento
AP81: Compra | AR81: Razão | AV81: Compra | AY81: =AW82*2.5% -> 0 | BC81: Compra | BE81: Razão | BI81: Compra | BL81: =BJ82*2.5% -> 0 | BP81: Compra | BR81: Razão | BV81: Compra | BY81: =BW82*2.5% -> 0 | CC81: Compra | CE81: Razão | CI81: Compra | CL81: =CJ82*2.5% -> 0 | CP81: Compra | CR81: Razão | CV81: Compra | CY81: =CW82*2.5% -> 0 | DC81: Compra | DE81: Razão | DI81: Compra | DL81: =DJ82*2.5% -> 0 | DP81: Compra | DR81: Razão | DV81: Compra | DY81: =DW82*2.5% -> 0 | EC81: Compra | EE81: Razão | EI81: Compra | EL81: =EJ82*2.5% -> 0 | EP81: Compra | ER81: Razão | EV81: Compra | EY81: =EW82*2.5% -> 0 | FC81: Compra | FE81: Razão | FI81: Compra | FL81: =FJ82*2.5% -> 0 | FP81: Compra | FR81: Razão | FV81: Compra | FY81: =FW82*2.5% -> 0 | GC81: Compra | GE81: Razão | GI81: Compra | GL81: =GJ82*2.5% -> 0
AP82: Faturamento | AR82: CNPJ: | AV82: Faturamento | BC82: Faturamento | BE82: CNPJ: | BI82: Faturamento | BP82: Faturamento | BR82: CNPJ: | BV82: Faturamento | CC82: Faturamento | CE82: CNPJ: | CI82: Faturamento | CP82: Faturamento | CR82: CNPJ: | CV82: Faturamento | DC82: Faturamento | DE82: CNPJ: | DI82: Faturamento | DP82: Faturamento | DR82: CNPJ: | DV82: Faturamento | EC82: Faturamento | EE82: CNPJ: | EI82: Faturamento | EP82: Faturamento | ER82: CNPJ: | EV82: Faturamento | FC82: Faturamento | FE82: CNPJ: | FI82: Faturamento | FP82: Faturamento | FR82: CNPJ: | FV82: Faturamento | GC82: Faturamento | GE82: CNPJ: | GI82: Faturamento
AP84: Compra | AR84: Razão | AV84: Compra | AY84: =AW85*2.5% -> 0 | BC84: Compra | BE84: Razão | BI84: Compra | BL84: =BJ85*2.5% -> 0 | BP84: Compra | BR84: Razão | BV84: Compra | BY84: =BW85*2.5% -> 0 | CC84: Compra | CE84: Razão | CI84: Compra | CL84: =CJ85*2.5% -> 0 | CP84: Compra | CR84: Razão | CV84: Compra | CY84: =CW85*2.5% -> 0 | DC84: Compra | DE84: Razão | DI84: Compra | DL84: =DJ85*2.5% -> 0 | DP84: Compra | DR84: Razão | DV84: Compra | DY84: =DW85*2.5% -> 0 | EC84: Compra | EE84: Razão | EI84: Compra | EL84: =EJ85*2.5% -> 0 | EP84: Compra | ER84: Razão | EV84: Compra | EY84: =EW85*2.5% -> 0 | FC84: Compra | FE84: Razão | FI84: Compra | FL84: =FJ85*2.5% -> 0 | FP84: Compra | FR84: Razão | FV84: Compra | FY84: =FW85*2.5% -> 0 | GC84: Compra | GE84: Razão | GI84: Compra | GL84: =GJ85*2.5% -> 0
AP85: Faturamento | AR85: CNPJ: | AV85: Faturamento | BC85: Faturamento | BE85: CNPJ: | BI85: Faturamento | BP85: Faturamento | BR85: CNPJ: | BV85: Faturamento | CC85: Faturamento | CE85: CNPJ: | CI85: Faturamento | CP85: Faturamento | CR85: CNPJ: | CV85: Faturamento | DC85: Faturamento | DE85: CNPJ: | DI85: Faturamento | DP85: Faturamento | DR85: CNPJ: | DV85: Faturamento | EC85: Faturamento | EE85: CNPJ: | EI85: Faturamento | EP85: Faturamento | ER85: CNPJ: | EV85: Faturamento | FC85: Faturamento | FE85: CNPJ: | FI85: Faturamento | FP85: Faturamento | FR85: CNPJ: | FV85: Faturamento | GC85: Faturamento | GE85: CNPJ: | GI85: Faturamento
AP87: Compra | AR87: Razão | AV87: Compra | AY87: =AW88*2.5% -> 0 | BC87: Compra | BE87: Razão | BI87: Compra | BL87: =BJ88*2.5% -> 0 | BP87: Compra | BR87: Razão | BV87: Compra | BY87: =BW88*2.5% -> 0 | CC87: Compra | CE87: Razão | CI87: Compra | CL87: =CJ88*2.5% -> 0 | CP87: Compra | CR87: Razão | CV87: Compra | CY87: =CW88*2.5% -> 0 | DC87: Compra | DE87: Razão | DI87: Compra | DL87: =DJ88*2.5% -> 0 | DP87: Compra | DR87: Razão | DV87: Compra | DY87: =DW88*2.5% -> 0 | EC87: Compra | EE87: Razão | EI87: Compra | EL87: =EJ88*2.5% -> 0 | EP87: Compra | ER87: Razão | EV87: Compra | EY87: =EW88*2.5% -> 0 | FC87: Compra | FE87: Razão | FI87: Compra | FL87: =FJ88*2.5% -> 0 | FP87: Compra | FR87: Razão | FV87: Compra | FY87: =FW88*2.5% -> 0 | GC87: Compra | GE87: Razão | GI87: Compra | GL87: =GJ88*2.5% -> 0
AP88: Faturamento | AR88: CNPJ: | AV88: Faturamento | BC88: Faturamento | BE88: CNPJ: | BI88: Faturamento | BP88: Faturamento | BR88: CNPJ: | BV88: Faturamento | CC88: Faturamento | CE88: CNPJ: | CI88: Faturamento | CP88: Faturamento | CR88: CNPJ: | CV88: Faturamento | DC88: Faturamento | DE88: CNPJ: | DI88: Faturamento | DP88: Faturamento | DR88: CNPJ: | DV88: Faturamento | EC88: Faturamento | EE88: CNPJ: | EI88: Faturamento | EP88: Faturamento | ER88: CNPJ: | EV88: Faturamento | FC88: Faturamento | FE88: CNPJ: | FI88: Faturamento | FP88: Faturamento | FR88: CNPJ: | FV88: Faturamento | GC88: Faturamento | GE88: CNPJ: | GI88: Faturamento
AP90: Compra | AR90: Razão | AV90: Compra | AY90: =AW91*2.5% -> 0 | BC90: Compra | BE90: Razão | BI90: Compra | BL90: =BJ91*2.5% -> 0 | BP90: Compra | BR90: Razão | BV90: Compra | BY90: =BW91*2.5% -> 0 | CC90: Compra | CE90: Razão | CI90: Compra | CL90: =CJ91*2.5% -> 0 | CP90: Compra | CR90: Razão | CV90: Compra | CY90: =CW91*2.5% -> 0 | DC90: Compra | DE90: Razão | DI90: Compra | DL90: =DJ91*2.5% -> 0 | DP90: Compra | DR90: Razão | DV90: Compra | DY90: =DW91*2.5% -> 0 | EC90: Compra | EE90: Razão | EI90: Compra | EL90: =EJ91*2.5% -> 0 | EP90: Compra | ER90: Razão | EV90: Compra | EY90: =EW91*2.5% -> 0 | FC90: Compra | FE90: Razão | FI90: Compra | FL90: =FJ91*2.5% -> 0 | FP90: Compra | FR90: Razão | FV90: Compra | FY90: =FW91*2.5% -> 0 | GC90: Compra | GE90: Razão | GI90: Compra | GL90: =GJ91*2.5% -> 0
AP91: Faturamento | AR91: CNPJ: | AV91: Faturamento | BC91: Faturamento | BE91: CNPJ: | BI91: Faturamento | BP91: Faturamento | BR91: CNPJ: | BV91: Faturamento | CC91: Faturamento | CE91: CNPJ: | CI91: Faturamento | CP91: Faturamento | CR91: CNPJ: | CV91: Faturamento | DC91: Faturamento | DE91: CNPJ: | DI91: Faturamento | DP91: Faturamento | DR91: CNPJ: | DV91: Faturamento | EC91: Faturamento | EE91: CNPJ: | EI91: Faturamento | EP91: Faturamento | ER91: CNPJ: | EV91: Faturamento | FC91: Faturamento | FE91: CNPJ: | FI91: Faturamento | FP91: Faturamento | FR91: CNPJ: | FV91: Faturamento | GC91: Faturamento | GE91: CNPJ: | GI91: Faturamento
AP93: Compra | AR93: Razão | AV93: Compra | AY93: =AW94*2.5% -> 0 | BC93: Compra | BE93: Razão | BI93: Compra | BL93: =BJ94*2.5% -> 0 | BP93: Compra | BR93: Razão | BV93: Compra | BY93: =BW94*2.5% -> 0 | CC93: Compra | CE93: Razão | CI93: Compra | CL93: =CJ94*2.5% -> 0 | CP93: Compra | CR93: Razão | CV93: Compra | CY93: =CW94*2.5% -> 0 | DC93: Compra | DE93: Razão | DI93: Compra | DL93: =DJ94*2.5% -> 0 | DP93: Compra | DR93: Razão | DV93: Compra | DY93: =DW94*2.5% -> 0 | EC93: Compra | EE93: Razão | EI93: Compra | EL93: =EJ94*2.5% -> 0 | EP93: Compra | ER93: Razão | EV93: Compra | EY93: =EW94*2.5% -> 0 | FC93: Compra | FE93: Razão | FI93: Compra | FL93: =FJ94*2.5% -> 0 | FP93: Compra | FR93: Razão | FV93: Compra | FY93: =FW94*2.5% -> 0 | GC93: Compra | GE93: Razão | GI93: Compra | GL93: =GJ94*2.5% -> 0
AP94: Faturamento | AR94: CNPJ: | AV94: Faturamento | BC94: Faturamento | BE94: CNPJ: | BI94: Faturamento | BP94: Faturamento | BR94: CNPJ: | BV94: Faturamento | CC94: Faturamento | CE94: CNPJ: | CI94: Faturamento | CP94: Faturamento | CR94: CNPJ: | CV94: Faturamento | DC94: Faturamento | DE94: CNPJ: | DI94: Faturamento | DP94: Faturamento | DR94: CNPJ: | DV94: Faturamento | EC94: Faturamento | EE94: CNPJ: | EI94: Faturamento | EP94: Faturamento | ER94: CNPJ: | EV94: Faturamento | FC94: Faturamento | FE94: CNPJ: | FI94: Faturamento | FP94: Faturamento | FR94: CNPJ: | FV94: Faturamento | GC94: Faturamento | GE94: CNPJ: | GI94: Faturamento
AP96: Compra | AR96: Razão | AV96: Compra | AY96: =AW97*2.5% -> 0 | BC96: Compra | BE96: Razão | BI96: Compra | BL96: =BJ97*2.5% -> 0 | BP96: Compra | BR96: Razão | BV96: Compra | BY96: =BW97*2.5% -> 0 | CC96: Compra | CE96: Razão | CI96: Compra | CL96: =CJ97*2.5% -> 0 | CP96: Compra | CR96: Razão | CV96: Compra | CY96: =CW97*2.5% -> 0 | DC96: Compra | DE96: Razão | DI96: Compra | DL96: =DJ97*2.5% -> 0 | DP96: Compra | DR96: Razão | DV96: Compra | DY96: =DW97*2.5% -> 0 | EC96: Compra | EE96: Razão | EI96: Compra | EL96: =EJ97*2.5% -> 0 | EP96: Compra | ER96: Razão | EV96: Compra | EY96: =EW97*2.5% -> 0 | FC96: Compra | FE96: Razão | FI96: Compra | FL96: =FJ97*2.5% -> 0 | FP96: Compra | FR96: Razão | FV96: Compra | FY96: =FW97*2.5% -> 0 | GC96: Compra | GE96: Razão | GI96: Compra | GL96: =GJ97*2.5% -> 0
AP97: Faturamento | AR97: CNPJ: | AV97: Faturamento | BC97: Faturamento | BE97: CNPJ: | BI97: Faturamento | BP97: Faturamento | BR97: CNPJ: | BV97: Faturamento | CC97: Faturamento | CE97: CNPJ: | CI97: Faturamento | CP97: Faturamento | CR97: CNPJ: | CV97: Faturamento | DC97: Faturamento | DE97: CNPJ: | DI97: Faturamento | DP97: Faturamento | DR97: CNPJ: | DV97: Faturamento | EC97: Faturamento | EE97: CNPJ: | EI97: Faturamento | EP97: Faturamento | ER97: CNPJ: | EV97: Faturamento | FC97: Faturamento | FE97: CNPJ: | FI97: Faturamento | FP97: Faturamento | FR97: CNPJ: | FV97: Faturamento | GC97: Faturamento | GE97: CNPJ: | GI97: Faturamento
AP99: Compra | AR99: Razão | AV99: Compra | AY99: =AW100*2.5% -> 0 | BC99: Compra | BE99: Razão | BI99: Compra | BL99: =BJ100*2.5% -> 0 | BP99: Compra | BR99: Razão | BV99: Compra | BY99: =BW100*2.5% -> 0 | CC99: Compra | CE99: Razão | CI99: Compra | CL99: =CJ100*2.5% -> 0 | CP99: Compra | CR99: Razão | CV99: Compra | CY99: =CW100*2.5% -> 0 | DC99: Compra | DE99: Razão | DI99: Compra | DL99: =DJ100*2.5% -> 0 | DP99: Compra | DR99: Razão | DV99: Compra | DY99: =DW100*2.5% -> 0 | EC99: Compra | EE99: Razão | EI99: Compra | EL99: =EJ100*2.5% -> 0 | EP99: Compra | ER99: Razão | EV99: Compra | EY99: =EW100*2.5% -> 0 | FC99: Compra | FE99: Razão | FI99: Compra | FL99: =FJ100*2.5% -> 0 | FP99: Compra | FR99: Razão | FV99: Compra | FY99: =FW100*2.5% -> 0 | GC99: Compra | GE99: Razão | GI99: Compra | GL99: =GJ100*2.5% -> 0
AP100: Faturamento | AR100: CNPJ: | AV100: Faturamento | BC100: Faturamento | BE100: CNPJ: | BI100: Faturamento | BP100: Faturamento | BR100: CNPJ: | BV100: Faturamento | CC100: Faturamento | CE100: CNPJ: | CI100: Faturamento | CP100: Faturamento | CR100: CNPJ: | CV100: Faturamento | DC100: Faturamento | DE100: CNPJ: | DI100: Faturamento | DP100: Faturamento | DR100: CNPJ: | DV100: Faturamento | EC100: Faturamento | EE100: CNPJ: | EI100: Faturamento | EP100: Faturamento | ER100: CNPJ: | EV100: Faturamento | FC100: Faturamento | FE100: CNPJ: | FI100: Faturamento | FP100: Faturamento | FR100: CNPJ: | FV100: Faturamento | GC100: Faturamento | GE100: CNPJ: | GI100: Faturamento
AT104: VALOR VENDA | AV104: =AW4+AW7+AW10+AW13+AW16+AW19+AW22+AW25+AW28+AW31+AW34+AW37+AW40+AW43+AW46+AW49+AW52+AW55+AW58+AW61+AW64+AW67+AW70+AW73+AW76+AW79+AW82+AW85+AW88+AW91+AW94+AW97+AW100 -> 0 | AX104: VALOR COMISSÃO | AZ104: =AY3+AY6+AY9+AY12+AY15+AY18+AY21+AY24+AY27+AY30+AY33+AY36+AY39+AY42+AY45+AY48+AY51+AY54+AY57+AY60+AY63+AY66+AY69+AY72+AY75+AY78+AY81+AY84+AY87+AY90+AY93+AY96+AY99 -> 0 | BG104: VALOR VENDA | BI104: =BJ4+BJ7+BJ10+BJ13+BJ16+BJ19+BJ22+BJ25+BJ28+BJ31+BJ34+BJ37+BJ40+BJ43+BJ46+BJ49+BJ52+BJ55+BJ58+BJ61+BJ64+BJ67+BJ70+BJ73+BJ76+BJ79+BJ82+BJ85+BJ88+BJ91+BJ94+BJ97+BJ100 -> 0 | BK104: VALOR COMISSÃO | BM104: =BL3+BL6+BL9+BL12+BL15+BL18+BL21+BL24+BL27+BL30+BL33+BL36+BL39+BL42+BL45+BL48+BL51+BL54+BL57+BL60+BL63+BL66+BL69+BL72+BL75+BL78+BL81+BL84+BL87+BL90+BL93+BL96+BL99 -> 0 | BT104: VALOR VENDA | BV104: =BW4+BW7+BW10+BW13+BW16+BW19+BW22+BW25+BW28+BW31+BW34+BW37+BW40+BW43+BW46+BW49+BW52+BW55+BW58+BW61+BW64+BW67+BW70+BW73+BW76+BW79+BW82+BW85+BW88+BW91+BW94+BW97+BW100 -> 0 | BX104: VALOR COMISSÃO | BZ104: =BY3+BY6+BY9+BY12+BY15+BY18+BY21+BY24+BY27+BY30+BY33+BY36+BY39+BY42+BY45+BY48+BY51+BY54+BY57+BY60+BY63+BY66+BY69+BY72+BY75+BY78+BY81+BY84+BY87+BY90+BY93+BY96+BY99 -> 0 | CG104: VALOR VENDA | CI104: =CJ4+CJ7+CJ10+CJ13+CJ16+CJ19+CJ22+CJ25+CJ28+CJ31+CJ34+CJ37+CJ40+CJ43+CJ46+CJ49+CJ52+CJ55+CJ58+CJ61+CJ64+CJ67+CJ70+CJ73+CJ76+CJ79+CJ82+CJ85+CJ88+CJ91+CJ94+CJ97+CJ100 -> 0 | CK104: VALOR COMISSÃO | CM104: =CL3+CL6+CL9+CL12+CL15+CL18+CL21+CL24+CL27+CL30+CL33+CL36+CL39+CL42+CL45+CL48+CL51+CL54+CL57+CL60+CL63+CL66+CL69+CL72+CL75+CL78+CL81+CL84+CL87+CL90+CL93+CL96+CL99 -> 0 | CT104: VALOR VENDA | CV104: =CW4+CW7+CW10+CW13+CW16+CW19+CW22+CW25+CW28+CW31+CW34+CW37+CW40+CW43+CW46+CW49+CW52+CW55+CW58+CW61+CW64+CW67+CW70+CW73+CW76+CW79+CW82+CW85+CW88+CW91+CW94+CW97+CW100 -> 0 | CX104: VALOR COMISSÃO | CZ104: =CY3+CY6+CY9+CY12+CY15+CY18+CY21+CY24+CY27+CY30+CY33+CY36+CY39+CY42+CY45+CY48+CY51+CY54+CY57+CY60+CY63+CY66+CY69+CY72+CY75+CY78+CY81+CY84+CY87+CY90+CY93+CY96+CY99 -> 0 | DG104: VALOR VENDA | DI104: =DJ4+DJ7+DJ10+DJ13+DJ16+DJ19+DJ22+DJ25+DJ28+DJ31+DJ34+DJ37+DJ40+DJ43+DJ46+DJ49+DJ52+DJ55+DJ58+DJ61+DJ64+DJ67+DJ70+DJ73+DJ76+DJ79+DJ82+DJ85+DJ88+DJ91+DJ94+DJ97+DJ100 -> 0 | DK104: VALOR COMISSÃO | DM104: =DL3+DL6+DL9+DL12+DL15+DL18+DL21+DL24+DL27+DL30+DL33+DL36+DL39+DL42+DL45+DL48+DL51+DL54+DL57+DL60+DL63+DL66+DL69+DL72+DL75+DL78+DL81+DL84+DL87+DL90+DL93+DL96+DL99 -> 0 | DT104: VALOR VENDA | DV104: =DW4+DW7+DW10+DW13+DW16+DW19+DW22+DW25+DW28+DW31+DW34+DW37+DW40+DW43+DW46+DW49+DW52+DW55+DW58+DW61+DW64+DW67+DW70+DW73+DW76+DW79+DW82+DW85+DW88+DW91+DW94+DW97+DW100 -> 0 | DX104: VALOR COMISSÃO | DZ104: =DY3+DY6+DY9+DY12+DY15+DY18+DY21+DY24+DY27+DY30+DY33+DY36+DY39+DY42+DY45+DY48+DY51+DY54+DY57+DY60+DY63+DY66+DY69+DY72+DY75+DY78+DY81+DY84+DY87+DY90+DY93+DY96+DY99 -> 0 | EG104: VALOR VENDA | EI104: =EJ4+EJ7+EJ10+EJ13+EJ16+EJ19+EJ22+EJ25+EJ28+EJ31+EJ34+EJ37+EJ40+EJ43+EJ46+EJ49+EJ52+EJ55+EJ58+EJ61+EJ64+EJ67+EJ70+EJ73+EJ76+EJ79+EJ82+EJ85+EJ88+EJ91+EJ94+EJ97+EJ100 -> 0 | EK104: VALOR COMISSÃO | EM104: =EL3+EL6+EL9+EL12+EL15+EL18+EL21+EL24+EL27+EL30+EL33+EL36+EL39+EL42+EL45+EL48+EL51+EL54+EL57+EL60+EL63+EL66+EL69+EL72+EL75+EL78+EL81+EL84+EL87+EL90+EL93+EL96+EL99 -> 0 | ET104: VALOR VENDA | EV104: =EW4+EW7+EW10+EW13+EW16+EW19+EW22+EW25+EW28+EW31+EW34+EW37+EW40+EW43+EW46+EW49+EW52+EW55+EW58+EW61+EW64+EW67+EW70+EW73+EW76+EW79+EW82+EW85+EW88+EW91+EW94+EW97+EW100 -> 0 | EX104: VALOR COMISSÃO | EZ104: =EY3+EY6+EY9+EY12+EY15+EY18+EY21+EY24+EY27+EY30+EY33+EY36+EY39+EY42+EY45+EY48+EY51+EY54+EY57+EY60+EY63+EY66+EY69+EY72+EY75+EY78+EY81+EY84+EY87+EY90+EY93+EY96+EY99 -> 0 | FG104: VALOR VENDA | FI104: =FJ4+FJ7+FJ10+FJ13+FJ16+FJ19+FJ22+FJ25+FJ28+FJ31+FJ34+FJ37+FJ40+FJ43+FJ46+FJ49+FJ52+FJ55+FJ58+FJ61+FJ64+FJ67+FJ70+FJ73+FJ76+FJ79+FJ82+FJ85+FJ88+FJ91+FJ94+FJ97+FJ100 -> 0 | FK104: VALOR COMISSÃO | FM104: =FL3+FL6+FL9+FL12+FL15+FL18+FL21+FL24+FL27+FL30+FL33+FL36+FL39+FL42+FL45+FL48+FL51+FL54+FL57+FL60+FL63+FL66+FL69+FL72+FL75+FL78+FL81+FL84+FL87+FL90+FL93+FL96+FL99 -> 0 | FT104: VALOR VENDA | FV104: =FW4+FW7+FW10+FW13+FW16+FW19+FW22+FW25+FW28+FW31+FW34+FW37+FW40+FW43+FW46+FW49+FW52+FW55+FW58+FW61+FW64+FW67+FW70+FW73+FW76+FW79+FW82+FW85+FW88+FW91+FW94+FW97+FW100 -> 0 | FX104: VALOR COMISSÃO | FZ104: =FY3+FY6+FY9+FY12+FY15+FY18+FY21+FY24+FY27+FY30+FY33+FY36+FY39+FY42+FY45+FY48+FY51+FY54+FY57+FY60+FY63+FY66+FY69+FY72+FY75+FY78+FY81+FY84+FY87+FY90+FY93+FY96+FY99 -> 0 | GG104: VALOR VENDA | GI104: =GJ4+GJ7+GJ10+GJ13+GJ16+GJ19+GJ22+GJ25+GJ28+GJ31+GJ34+GJ37+GJ40+GJ43+GJ46+GJ49+GJ52+GJ55+GJ58+GJ61+GJ64+GJ67+GJ70+GJ73+GJ76+GJ79+GJ82+GJ85+GJ88+GJ91+GJ94+GJ97+GJ100 -> 0 | GK104: VALOR COMISSÃO | GM104: =GL3+GL6+GL9+GL12+GL15+GL18+GL21+GL24+GL27+GL30+GL33+GL36+GL39+GL42+GL45+GL48+GL51+GL54+GL57+GL60+GL63+GL66+GL69+GL72+GL75+GL78+GL81+GL84+GL87+GL90+GL93+GL96+GL99 -> 0

Sheet ISANOG
B1: JUNHO | M1: Voltar ao Inicio | O1: JULHO | Z1: Voltar ao Inicio | AB1: AGOSTO | AN1: Voltar ao Inicio | AP1: Janeiro | BA1: Voltar ao Inicio | BC1: Fevereiro | BN1: Voltar ao Inicio | BP1: Março | CA1: Voltar ao Inicio | CC1: Abril | CN1: Voltar ao Inicio | CP1: Maio | DA1: Voltar ao Inicio | DC1: Junho | DN1: Voltar ao Inicio | DP1: Julho | EA1: Voltar ao Inicio | EC1: Agosto | EN1: Voltar ao Inicio | EP1: Setembro | FA1: Voltar ao Inicio | FC1: Outubro | FN1: Voltar ao Inicio | FP1: Novembro | GA1: Voltar ao Inicio | GC1: Dezembro | GN1: Voltar ao Inicio
B2: Data | D2: CLIENTE | F2: Pedido | G2: NFE | H2: Valor | J2: TABELA | K2: PRAZO | L2: Comissão | M2: Situação Pedido | O2: Data | Q2: CLIENTE | S2: Pedido | T2: NFE | U2: Valor | W2: TABELA | X2: PRAZO | Y2: Comissão | Z2: Situação Pedido | AB2: Data | AD2: CLIENTE | AF2: Pedido | AG2: FORNECEDOR | AH2: NFE | AI2: Valor | AK2: TABELA | AL2: PRAZO | AM2: Comissão | AN2: Situação Pedido | AP2: Data | AR2: CLIENTE | AT2: Pedido | AU2: NFE | AV2: Valor | AX2: TABELA | AY2: Comissão | AZ2: Vendedor | BA2: Situação Pedido | BC2: Data | BE2: CLIENTE | BG2: Pedido | BH2: NFE | BI2: Valor | BK2: TABELA | BL2: Comissão | BM2: Vendedor | BN2: Situação Pedido | BP2: Data | BR2: CLIENTE | BT2: Pedido | BU2: NFE | BV2: Valor | BX2: TABELA | BY2: Comissão | BZ2: Vendedor | CA2: Situação Pedido | CC2: Data | CE2: CLIENTE | CG2: Pedido | CH2: NFE | CI2: Valor | CK2: TABELA | CL2: Comissão | CM2: Vendedor | CN2: Situação Pedido | CP2: Data | CR2: CLIENTE | CT2: Pedido | CU2: NFE | CV2: Valor | CX2: TABELA | CY2: Comissão | CZ2: Vendedor | DA2: Situação Pedido | DC2: Data | DE2: CLIENTE | DG2: Pedido | DH2: NFE | DI2: Valor | DK2: TABELA | DL2: Comissão | DM2: Vendedor | DN2: Situação Pedido | DP2: Data | DR2: CLIENTE | DT2: Pedido | DU2: NFE | DV2: Valor | DX2: TABELA | DY2: Comissão | DZ2: Vendedor | EA2: Situação Pedido | EC2: Data | EE2: CLIENTE | EG2: Pedido | EH2: NFE | EI2: Valor | EK2: TABELA | EL2: Comissão | EM2: Vendedor | EN2: Situação Pedido | EP2: Data | ER2: CLIENTE | ET2: Pedido | EU2: NFE | EV2: Valor | EX2: TABELA | EY2: Comissão | EZ2: Vendedor | FA2: Situação Pedido | FC2: Data | FE2: CLIENTE | FG2: Pedido | FH2: NFE | FI2: Valor | FK2: TABELA | FL2: Comissão | FM2: Vendedor | FN2: Situação Pedido | FP2: Data | FR2: CLIENTE | FT2: Pedido | FU2: NFE | FV2: Valor | FX2: TABELA | FY2: Comissão | FZ2: Vendedor | GA2: Situação Pedido | GC2: Data | GE2: CLIENTE | GG2: Pedido | GH2: NFE | GI2: Valor | GK2: TABELA | GL2: Comissão | GM2: Vendedor | GN2: Situação Pedido
B3: Compra | C3: 45811 | D3: Razão | E3: DECAZZA COM | F3: 250602172053470 | G3: 1441 | H3: Compra | I3: 755.44 | J3: 2 | K3: PIX | L3: =I4*5% -> 37.772 | M3: PAGO | O3: Compra | P3: 45846 | Q3: Razão | R3: DECAZZA COM | S3: 250708135238581 | T3: 187 | U3: Compra | V3: 10891.96 | W3: 2 | X3: PIX | Y3: =V4*5% -> 544.598 | Z3: FATURADO | AB3: Compra | AD3: Razão | AI3: Compra | AL3: PIX | AN3: PAGO | AP3: Compra | AR3: Razão | AV3: Compra | AY3: =AW4*2.5% -> 0 | BC3: Compra | BE3: Razão | BI3: Compra | BL3: =BJ4*2.5% -> 0 | BP3: Compra | BR3: Razão | BV3: Compra | BY3: =BW4*2.5% -> 0 | CC3: Compra | CE3: Razão | CI3: Compra | CL3: =CJ4*2.5% -> 0 | CP3: Compra | CR3: Razão | CV3: Compra | CY3: =CW4*2.5% -> 0 | DC3: Compra | DE3: Razão | DI3: Compra | DL3: =DJ4*2.5% -> 0 | DP3: Compra | DR3: Razão | DV3: Compra | DY3: =DW4*2.5% -> 0 | EC3: Compra | EE3: Razão | EI3: Compra | EL3: =EJ4*2.5% -> 0 | EP3: Compra | ER3: Razão | EV3: Compra | EY3: =EW4*2.5% -> 0 | FC3: Compra | FE3: Razão | FI3: Compra | FL3: =FJ4*2.5% -> 0 | FP3: Compra | FR3: Razão | FV3: Compra | FY3: =FW4*2.5% -> 0 | GC3: Compra | GE3: Razão | GI3: Compra | GL3: =GJ4*2.5% -> 0
B4: Faturamento | C4: 45812 | D4: CNPJ: | E4: 43.967.691/0001-00 | H4: Faturamento | I4: 755.44 | O4: Faturamento | P4: 45848 | Q4: CNPJ: | R4: 43.967.691/0001-00 | U4: Faturamento | V4: 10891.96 | AB4: Faturamento | AD4: CNPJ: | AI4: Faturamento | AP4: Faturamento | AR4: CNPJ: | AV4: Faturamento | BC4: Faturamento | BE4: CNPJ: | BI4: Faturamento | BP4: Faturamento | BR4: CNPJ: | BV4: Faturamento | CC4: Faturamento | CE4: CNPJ: | CI4: Faturamento | CP4: Faturamento | CR4: CNPJ: | CV4: Faturamento | DC4: Faturamento | DE4: CNPJ: | DI4: Faturamento | DP4: Faturamento | DR4: CNPJ: | DV4: Faturamento | EC4: Faturamento | EE4: CNPJ: | EI4: Faturamento | EP4: Faturamento | ER4: CNPJ: | EV4: Faturamento | FC4: Faturamento | FE4: CNPJ: | FI4: Faturamento | FP4: Faturamento | FR4: CNPJ: | FV4: Faturamento | GC4: Faturamento | GE4: CNPJ: | GI4: Faturamento
B6: Compra | C6: 45813 | D6: Razão | E6: EMBALEME | F6: 250604123701560 | G6: 1447 | H6: Compra | I6: 4110.14 | J6: 2 | K6: PRAZO | L6: =I7*5% -> 205.508 | M6: FATURADO | O6: Compra | P6: 45852 | Q6: Razão | R6: DECAZZA COM | S6: 3508 | T6: 218 | U6: Compra | V6: 71547.78 | W6: 2 | Y6: =V7*3.5% -> 2107.9968 | Z6: FATURADO | AB6: Compra | AD6: Razão | AI6: Compra | AM6: =AJ7*5% -> 0 | AN6: FATURADO | AP6: Compra | AR6: Razão | AV6: Compra | AY6: =AW7*2.5% -> 0 | BC6: Compra | BE6: Razão | BI6: Compra | BL6: =BJ7*2.5% -> 0 | BP6: Compra | BR6: Razão | BV6: Compra | BY6: =BW7*2.5% -> 0 | CC6: Compra | CE6: Razão | CI6: Compra | CL6: =CJ7*2.5% -> 0 | CP6: Compra | CR6: Razão | CV6: Compra | CY6: =CW7*2.5% -> 0 | DC6: Compra | DE6: Razão | DI6: Compra | DL6: =DJ7*2.5% -> 0 | DP6: Compra | DR6: Razão | DV6: Compra | DY6: =DW7*2.5% -> 0 | EC6: Compra | EE6: Razão | EI6: Compra | EL6: =EJ7*2.5% -> 0 | EP6: Compra | ER6: Razão | EV6: Compra | EY6: =EW7*2.5% -> 0 | FC6: Compra | FE6: Razão | FI6: Compra | FL6: =FJ7*2.5% -> 0 | FP6: Compra | FR6: Razão | FV6: Compra | FY6: =FW7*2.5% -> 0 | GC6: Compra | GE6: Razão | GI6: Compra | GL6: =GJ7*2.5% -> 0
B7: Faturamento | C7: 45817 | D7: CNPJ: | E7: 00.458.459/0001-33 | H7: Faturamento | I7: 4110.16 | O7: Faturamento | P7: 45855 | Q7: CNPJ: | R7: 43.967.691/0001-00 | U7: Faturamento | V7: 60228.48 | AB7: Faturamento | AD7: CNPJ: | AI7: Faturamento | AP7: Faturamento | AR7: CNPJ: | AV7: Faturamento | BC7: Faturamento | BE7: CNPJ: | BI7: Faturamento | BP7: Faturamento | BR7: CNPJ: | BV7: Faturamento | CC7: Faturamento | CE7: CNPJ: | CI7: Faturamento | CP7: Faturamento | CR7: CNPJ: | CV7: Faturamento | DC7: Faturamento | DE7: CNPJ: | DI7: Faturamento | DP7: Faturamento | DR7: CNPJ: | DV7: Faturamento | EC7: Faturamento | EE7: CNPJ: | EI7: Faturamento | EP7: Faturamento | ER7: CNPJ: | EV7: Faturamento | FC7: Faturamento | FE7: CNPJ: | FI7: Faturamento | FP7: Faturamento | FR7: CNPJ: | FV7: Faturamento | GC7: Faturamento | GE7: CNPJ: | GI7: Faturamento
B9: Compra | C9: 45819 | D9: Razão | E9: DECAZZA COMERCIAL | F9: 3062 | H9: Compra | I9: 7548 | J9: 2 | K9: PIX | L9: =I10*5% -> 377.4 | M9: PAGO | O9: Compra | P9: 45861 | Q9: Razão | R9: DECAZZA COM | S9: 250723143208488 | T9: 266 | U9: Compra | V9: 46645.2 | W9: 2 | Y9: =V10*4% -> 1865.808 | Z9: FATURADO | AB9: Compra | AD9: Razão | AI9: Compra | AM9: =AJ10*6% -> 0 | AN9: FATURADO | AP9: Compra | AR9: Razão | AV9: Compra | AY9: =AW10*2.5% -> 0 | BC9: Compra | BE9: Razão | BI9: Compra | BL9: =BJ10*2.5% -> 0 | BP9: Compra | BR9: Razão | BV9: Compra | BY9: =BW10*2.5% -> 0 | CC9: Compra | CE9: Razão | CI9: Compra | CL9: =CJ10*2.5% -> 0 | CP9: Compra | CR9: Razão | CV9: Compra | CY9: =CW10*2.5% -> 0 | DC9: Compra | DE9: Razão | DI9: Compra | DL9: =DJ10*2.5% -> 0 | DP9: Compra | DR9: Razão | DV9: Compra | DY9: =DW10*2.5% -> 0 | EC9: Compra | EE9: Razão | EI9: Compra | EL9: =EJ10*2.5% -> 0 | EP9: Compra | ER9: Razão | EV9: Compra | EY9: =EW10*2.5% -> 0 | FC9: Compra | FE9: Razão | FI9: Compra | FL9: =FJ10*2.5% -> 0 | FP9: Compra | FR9: Razão | FV9: Compra | FY9: =FW10*2.5% -> 0 | GC9: Compra | GE9: Razão | GI9: Compra | GL9: =GJ10*2.5% -> 0
B10: Faturamento | C10: 45820 | D10: CNPJ: | E10: 43.967.691/0001-00 | G10: 1457 | H10: Faturamento | I10: 7548 | O10: Faturamento | P10: 45862 | Q10: CNPJ: | R10: 43.967.691/0001-00 | U10: Faturamento | V10: 46645.2 | AB10: Faturamento | AD10: CNPJ: | AI10: Faturamento | AP10: Faturamento | AR10: CNPJ: | AV10: Faturamento | BC10: Faturamento | BE10: CNPJ: | BI10: Faturamento | BP10: Faturamento | BR10: CNPJ: | BV10: Faturamento | CC10: Faturamento | CE10: CNPJ: | CI10: Faturamento | CP10: Faturamento | CR10: CNPJ: | CV10: Faturamento | DC10: Faturamento | DE10: CNPJ: | DI10: Faturamento | DP10: Faturamento | DR10: CNPJ: | DV10: Faturamento | EC10: Faturamento | EE10: CNPJ: | EI10: Faturamento | EP10: Faturamento | ER10: CNPJ: | EV10: Faturamento | FC10: Faturamento | FE10: CNPJ: | FI10: Faturamento | FP10: Faturamento | FR10: CNPJ: | FV10: Faturamento | GC10: Faturamento | GE10: CNPJ: | GI10: Faturamento
B12: Compra | C12: 45813 | D12: Razão | E12: CELL SOLLUTION | F12: 250605154601006 | G12: 104 | H12: Compra | I12: 13749.56 | J12: 2 | K12: PIX | L12: =I13*5% -> 687.478 | M12: PAGO | O12: Compra | Q12: Razão | U12: Compra | Y12: =V13*5% -> 0 | AB12: Compra | AD12: Razão | AI12: Compra | AM12: =AJ13*5% -> 0 | AP12: Compra | AR12: Razão | AV12: Compra | AY12: =AW13*2.5% -> 0 | BC12: Compra | BE12: Razão | BI12: Compra | BL12: =BJ13*2.5% -> 0 | BP12: Compra | BR12: Razão | BV12: Compra | BY12: =BW13*2.5% -> 0 | CC12: Compra | CE12: Razão | CI12: Compra | CL12: =CJ13*2.5% -> 0 | CP12: Compra | CR12: Razão | CV12: Compra | CY12: =CW13*2.5% -> 0 | DC12: Compra | DE12: Razão | DI12: Compra | DL12: =DJ13*2.5% -> 0 | DP12: Compra | DR12: Razão | DV12: Compra | DY12: =DW13*2.5% -> 0 | EC12: Compra | EE12: Razão | EI12: Compra | EL12: =EJ13*2.5% -> 0 | EP12: Compra | ER12: Razão | EV12: Compra | EY12: =EW13*2.5% -> 0 | FC12: Compra | FE12: Razão | FI12: Compra | FL12: =FJ13*2.5% -> 0 | FP12: Compra | FR12: Razão | FV12: Compra | FY12: =FW13*2.5% -> 0 | GC12: Compra | GE12: Razão | GI12: Compra | GL12: =GJ13*2.5% -> 0
B13: Faturamento | C13: 45824 | D13: CNPJ: | E13: 20.963.243/0001-01 | H13: Faturamento | I13: 13749.56 | O13: Faturamento | Q13: CNPJ: | U13: Faturamento | AB13: Faturamento | AD13: CNPJ: | AI13: Faturamento | AP13: Faturamento | AR13: CNPJ: | AV13: Faturamento | BC13: Faturamento | BE13: CNPJ: | BI13: Faturamento | BP13: Faturamento | BR13: CNPJ: | BV13: Faturamento | CC13: Faturamento | CE13: CNPJ: | CI13: Faturamento | CP13: Faturamento | CR13: CNPJ: | CV13: Faturamento | DC13: Faturamento | DE13: CNPJ: | DI13: Faturamento | DP13: Faturamento | DR13: CNPJ: | DV13: Faturamento | EC13: Faturamento | EE13: CNPJ: | EI13: Faturamento | EP13: Faturamento | ER13: CNPJ: | EV13: Faturamento | FC13: Faturamento | FE13: CNPJ: | FI13: Faturamento | FP13: Faturamento | FR13: CNPJ: | FV13: Faturamento | GC13: Faturamento | GE13: CNPJ: | GI13: Faturamento
B15: Compra | C15: 45813 | D15: Razão | E15: CELL SOLLUTION | F15: 250605154107945 | G15: 1465 | H15: Compra | I15: 6256.2 | J15: 2 | K15: PIX | L15: =I16*5% -> 312.81 | M15: PAGO | O15: Compra | Q15: Razão | U15: Compra | Y15: =V16*5% -> 0 | AB15: Compra | AD15: Razão | AI15: Compra | AM15: =AJ16*5% -> 0 | AP15: Compra | AR15: Razão | AV15: Compra | AY15: =AW16*2.5% -> 0 | BC15: Compra | BE15: Razão | BI15: Compra | BL15: =BJ16*2.5% -> 0 | BP15: Compra | BR15: Razão | BV15: Compra | BY15: =BW16*2.5% -> 0 | CC15: Compra | CE15: Razão | CI15: Compra | CL15: =CJ16*2.5% -> 0 | CP15: Compra | CR15: Razão | CV15: Compra | CY15: =CW16*2.5% -> 0 | DC15: Compra | DE15: Razão | DI15: Compra | DL15: =DJ16*2.5% -> 0 | DP15: Compra | DR15: Razão | DV15: Compra | DY15: =DW16*2.5% -> 0 | EC15: Compra | EE15: Razão | EI15: Compra | EL15: =EJ16*2.5% -> 0 | EP15: Compra | ER15: Razão | EV15: Compra | EY15: =EW16*2.5% -> 0 | FC15: Compra | FE15: Razão | FI15: Compra | FL15: =FJ16*2.5% -> 0 | FP15: Compra | FR15: Razão | FV15: Compra | FY15: =FW16*2.5% -> 0 | GC15: Compra | GE15: Razão | GI15: Compra | GL15: =GJ16*2.5% -> 0
B16: Faturamento | C16: 45824 | D16: CNPJ: | E16: 20.963.243/0001-01 | H16: Faturamento | I16: 6256.2 | O16: Faturamento | Q16: CNPJ: | U16: Faturamento | AB16: Faturamento | AD16: CNPJ: | AI16: Faturamento | AP16: Faturamento | AR16: CNPJ: | AV16: Faturamento | BC16: Faturamento | BE16: CNPJ: | BI16: Faturamento | BP16: Faturamento | BR16: CNPJ: | BV16: Faturamento | CC16: Faturamento | CE16: CNPJ: | CI16: Faturamento | CP16: Faturamento | CR16: CNPJ: | CV16: Faturamento | DC16: Faturamento | DE16: CNPJ: | DI16: Faturamento | DP16: Faturamento | DR16: CNPJ: | DV16: Faturamento | EC16: Faturamento | EE16: CNPJ: | EI16: Faturamento | EP16: Faturamento | ER16: CNPJ: | EV16: Faturamento | FC16: Faturamento | FE16: CNPJ: | FI16: Faturamento | FP16: Faturamento | FR16: CNPJ: | FV16: Faturamento | GC16: Faturamento | GE16: CNPJ: | GI16: Faturamento
B18: Compra | C18: 45832 | D18: Razão | E18: COMERCIAL MARTINS E MARTINS | F18: 250624104438099 | G18: 1471 | H18: Compra | I18: 16124.42 | J18: 2 | K18: PRAZO | L18: =I19*5% -> 806.221 | M18: FATURADO | O18: Compra | Q18: Razão | U18: Compra | Y18: =V19*5% -> 0 | AB18: Compra | AD18: Razão | AI18: Compra | AM18: =AJ19*5% -> 0 | AP18: Compra | AR18: Razão | AV18: Compra | AY18: =AW19*2.5% -> 0 | BC18: Compra | BE18: Razão | BI18: Compra | BL18: =BJ19*2.5% -> 0 | BP18: Compra | BR18: Razão | BV18: Compra | BY18: =BW19*2.5% -> 0 | CC18: Compra | CE18: Razão | CI18: Compra | CL18: =CJ19*2.5% -> 0 | CP18: Compra | CR18: Razão | CV18: Compra | CY18: =CW19*2.5% -> 0 | DC18: Compra | DE18: Razão | DI18: Compra | DL18: =DJ19*2.5% -> 0 | DP18: Compra | DR18: Razão | DV18: Compra | DY18: =DW19*2.5% -> 0 | EC18: Compra | EE18: Razão | EI18: Compra | EL18: =EJ19*2.5% -> 0 | EP18: Compra | ER18: Razão | EV18: Compra | EY18: =EW19*2.5% -> 0 | FC18: Compra | FE18: Razão | FI18: Compra | FL18: =FJ19*2.5% -> 0 | FP18: Compra | FR18: Razão | FV18: Compra | FY18: =FW19*2.5% -> 0 | GC18: Compra | GE18: Razão | GI18: Compra | GL18: =GJ19*2.5% -> 0
B19: Faturamento | C19: 45833 | D19: CNPJ: | E19: 01.679.699/0001-20 | H19: Faturamento | I19: 16124.42 | O19: Faturamento | Q19: CNPJ: | U19: Faturamento | AB19: Faturamento | AD19: CNPJ: | AI19: Faturamento | AP19: Faturamento | AR19: CNPJ: | AV19: Faturamento | BC19: Faturamento | BE19: CNPJ: | BI19: Faturamento | BP19: Faturamento | BR19: CNPJ: | BV19: Faturamento | CC19: Faturamento | CE19: CNPJ: | CI19: Faturamento | CP19: Faturamento | CR19: CNPJ: | CV19: Faturamento | DC19: Faturamento | DE19: CNPJ: | DI19: Faturamento | DP19: Faturamento | DR19: CNPJ: | DV19: Faturamento | EC19: Faturamento | EE19: CNPJ: | EI19: Faturamento | EP19: Faturamento | ER19: CNPJ: | EV19: Faturamento | FC19: Faturamento | FE19: CNPJ: | FI19: Faturamento | FP19: Faturamento | FR19: CNPJ: | FV19: Faturamento | GC19: Faturamento | GE19: CNPJ: | GI19: Faturamento
B21: Compra | D21: Razão | H21: Compra | L21: =I22*5% -> 0 | O21: Compra | Q21: Razão | U21: Compra | Y21: =V22*5% -> 0 | AB21: Compra | AD21: Razão | AI21: Compra | AM21: =AJ22*5% -> 0 | AP21: Compra | AR21: Razão | AV21: Compra | AY21: =AW22*2.5% -> 0 | BC21: Compra | BE21: Razão | BI21: Compra | BL21: =BJ22*2.5% -> 0 | BP21: Compra | BR21: Razão | BV21: Compra | BY21: =BW22*2.5% -> 0 | CC21: Compra | CE21: Razão | CI21: Compra | CL21: =CJ22*2.5% -> 0 | CP21: Compra | CR21: Razão | CV21: Compra | CY21: =CW22*2.5% -> 0 | DC21: Compra | DE21: Razão | DI21: Compra | DL21: =DJ22*2.5% -> 0 | DP21: Compra | DR21: Razão | DV21: Compra | DY21: =DW22*2.5% -> 0 | EC21: Compra | EE21: Razão | EI21: Compra | EL21: =EJ22*2.5% -> 0 | EP21: Compra | ER21: Razão | EV21: Compra | EY21: =EW22*2.5% -> 0 | FC21: Compra | FE21: Razão | FI21: Compra | FL21: =FJ22*2.5% -> 0 | FP21: Compra | FR21: Razão | FV21: Compra | FY21: =FW22*2.5% -> 0 | GC21: Compra | GE21: Razão | GI21: Compra | GL21: =GJ22*2.5% -> 0
B22: Faturamento | D22: CNPJ: | H22: Faturamento | O22: Faturamento | Q22: CNPJ: | U22: Faturamento | AB22: Faturamento | AD22: CNPJ: | AI22: Faturamento | AP22: Faturamento | AR22: CNPJ: | AV22: Faturamento | BC22: Faturamento | BE22: CNPJ: | BI22: Faturamento | BP22: Faturamento | BR22: CNPJ: | BV22: Faturamento | CC22: Faturamento | CE22: CNPJ: | CI22: Faturamento | CP22: Faturamento | CR22: CNPJ: | CV22: Faturamento | DC22: Faturamento | DE22: CNPJ: | DI22: Faturamento | DP22: Faturamento | DR22: CNPJ: | DV22: Faturamento | EC22: Faturamento | EE22: CNPJ: | EI22: Faturamento | EP22: Faturamento | ER22: CNPJ: | EV22: Faturamento | FC22: Faturamento | FE22: CNPJ: | FI22: Faturamento | FP22: Faturamento | FR22: CNPJ: | FV22: Faturamento | GC22: Faturamento | GE22: CNPJ: | GI22: Faturamento
B24: Compra | D24: Razão | H24: Compra | L24: =I25*5% -> 0 | O24: Compra | Q24: Razão | U24: Compra | Y24: =V25*5% -> 0 | AB24: Compra | AD24: Razão | AI24: Compra | AM24: =AJ25*5% -> 0 | AP24: Compra | AR24: Razão | AV24: Compra | AY24: =AW25*2.5% -> 0 | BC24: Compra | BE24: Razão | BI24: Compra | BL24: =BJ25*2.5% -> 0 | BP24: Compra | BR24: Razão | BV24: Compra | BY24: =BW25*2.5% -> 0 | CC24: Compra | CE24: Razão | CI24: Compra | CL24: =CJ25*2.5% -> 0 | CP24: Compra | CR24: Razão | CV24: Compra | CY24: =CW25*2.5% -> 0 | DC24: Compra | DE24: Razão | DI24: Compra | DL24: =DJ25*2.5% -> 0 | DP24: Compra | DR24: Razão | DV24: Compra | DY24: =DW25*2.5% -> 0 | EC24: Compra | EE24: Razão | EI24: Compra | EL24: =EJ25*2.5% -> 0 | EP24: Compra | ER24: Razão | EV24: Compra | EY24: =EW25*2.5% -> 0 | FC24: Compra | FE24: Razão | FI24: Compra | FL24: =FJ25*2.5% -> 0 | FP24: Compra | FR24: Razão | FV24: Compra | FY24: =FW25*2.5% -> 0 | GC24: Compra | GE24: Razão | GI24: Compra | GL24: =GJ25*2.5% -> 0
B25: Faturamento | D25: CNPJ: | H25: Faturamento | O25: Faturamento | Q25: CNPJ: | U25: Faturamento | AB25: Faturamento | AD25: CNPJ: | AI25: Faturamento | AP25: Faturamento | AR25: CNPJ: | AV25: Faturamento | BC25: Faturamento | BE25: CNPJ: | BI25: Faturamento | BP25: Faturamento | BR25: CNPJ: | BV25: Faturamento | CC25: Faturamento | CE25: CNPJ: | CI25: Faturamento | CP25: Faturamento | CR25: CNPJ: | CV25: Faturamento | DC25: Faturamento | DE25: CNPJ: | DI25: Faturamento | DP25: Faturamento | DR25: CNPJ: | DV25: Faturamento | EC25: Faturamento | EE25: CNPJ: | EI25: Faturamento | EP25: Faturamento | ER25: CNPJ: | EV25: Faturamento | FC25: Faturamento | FE25: CNPJ: | FI25: Faturamento | FP25: Faturamento | FR25: CNPJ: | FV25: Faturamento | GC25: Faturamento | GE25: CNPJ: | GI25: Faturamento
B27: Compra | D27: Razão | H27: Compra | L27: =I28*5% -> 0 | O27: Compra | Q27: Razão | U27: Compra | Y27: =V28*5% -> 0 | AB27: Compra | AD27: Razão | AI27: Compra | AM27: =AJ28*5% -> 0 | AP27: Compra | AR27: Razão | AV27: Compra | AY27: =AW28*2.5% -> 0 | BC27: Compra | BE27: Razão | BI27: Compra | BL27: =BJ28*2.5% -> 0 | BP27: Compra | BR27: Razão | BV27: Compra | BY27: =BW28*2.5% -> 0 | CC27: Compra | CE27: Razão | CI27: Compra | CL27: =CJ28*2.5% -> 0 | CP27: Compra | CR27: Razão | CV27: Compra | CY27: =CW28*2.5% -> 0 | DC27: Compra | DE27: Razão | DI27: Compra | DL27: =DJ28*2.5% -> 0 | DP27: Compra | DR27: Razão | DV27: Compra | DY27: =DW28*2.5% -> 0 | EC27: Compra | EE27: Razão | EI27: Compra | EL27: =EJ28*2.5% -> 0 | EP27: Compra | ER27: Razão | EV27: Compra | EY27: =EW28*2.5% -> 0 | FC27: Compra | FE27: Razão | FI27: Compra | FL27: =FJ28*2.5% -> 0 | FP27: Compra | FR27: Razão | FV27: Compra | FY27: =FW28*2.5% -> 0 | GC27: Compra | GE27: Razão | GI27: Compra | GL27: =GJ28*2.5% -> 0
B28: Faturamento | D28: CNPJ: | H28: Faturamento | O28: Faturamento | Q28: CNPJ: | U28: Faturamento | AB28: Faturamento | AD28: CNPJ: | AI28: Faturamento | AP28: Faturamento | AR28: CNPJ: | AV28: Faturamento | BC28: Faturamento | BE28: CNPJ: | BI28: Faturamento | BP28: Faturamento | BR28: CNPJ: | BV28: Faturamento | CC28: Faturamento | CE28: CNPJ: | CI28: Faturamento | CP28: Faturamento | CR28: CNPJ: | CV28: Faturamento | DC28: Faturamento | DE28: CNPJ: | DI28: Faturamento | DP28: Faturamento | DR28: CNPJ: | DV28: Faturamento | EC28: Faturamento | EE28: CNPJ: | EI28: Faturamento | EP28: Faturamento | ER28: CNPJ: | EV28: Faturamento | FC28: Faturamento | FE28: CNPJ: | FI28: Faturamento | FP28: Faturamento | FR28: CNPJ: | FV28: Faturamento | GC28: Faturamento | GE28: CNPJ: | GI28: Faturamento
B30: Compra | D30: Razão | H30: Compra | L30: =I31*5% -> 0 | O30: Compra | Q30: Razão | U30: Compra | Y30: =V31*5% -> 0 | AB30: Compra | AD30: Razão | AI30: Compra | AM30: =AJ31*5% -> 0 | AP30: Compra | AR30: Razão | AV30: Compra | AY30: =AW31*2.5% -> 0 | BC30: Compra | BE30: Razão | BI30: Compra | BL30: =BJ31*2.5% -> 0 | BP30: Compra | BR30: Razão | BV30: Compra | BY30: =BW31*2.5% -> 0 | CC30: Compra | CE30: Razão | CI30: Compra | CL30: =CJ31*2.5% -> 0 | CP30: Compra | CR30: Razão | CV30: Compra | CY30: =CW31*2.5% -> 0 | DC30: Compra | DE30: Razão | DI30: Compra | DL30: =DJ31*2.5% -> 0 | DP30: Compra | DR30: Razão | DV30: Compra | DY30: =DW31*2.5% -> 0 | EC30: Compra | EE30: Razão | EI30: Compra | EL30: =EJ31*2.5% -> 0 | EP30: Compra | ER30: Razão | EV30: Compra | EY30: =EW31*2.5% -> 0 | FC30: Compra | FE30: Razão | FI30: Compra | FL30: =FJ31*2.5% -> 0 | FP30: Compra | FR30: Razão | FV30: Compra | FY30: =FW31*2.5% -> 0 | GC30: Compra | GE30: Razão | GI30: Compra | GL30: =GJ31*2.5% -> 0
B31: Faturamento | D31: CNPJ: | H31: Faturamento | O31: Faturamento | Q31: CNPJ: | U31: Faturamento | AB31: Faturamento | AD31: CNPJ: | AI31: Faturamento | AP31: Faturamento | AR31: CNPJ: | AV31: Faturamento | BC31: Faturamento | BE31: CNPJ: | BI31: Faturamento | BP31: Faturamento | BR31: CNPJ: | BV31: Faturamento | CC31: Faturamento | CE31: CNPJ: | CI31: Faturamento | CP31: Faturamento | CR31: CNPJ: | CV31: Faturamento | DC31: Faturamento | DE31: CNPJ: | DI31: Faturamento | DP31: Faturamento | DR31: CNPJ: | DV31: Faturamento | EC31: Faturamento | EE31: CNPJ: | EI31: Faturamento | EP31: Faturamento | ER31: CNPJ: | EV31: Faturamento | FC31: Faturamento | FE31: CNPJ: | FI31: Faturamento | FP31: Faturamento | FR31: CNPJ: | FV31: Faturamento | GC31: Faturamento | GE31: CNPJ: | GI31: Faturamento
B33: Compra | D33: Razão | H33: Compra | L33: =I34*5% -> 0 | O33: Compra | Q33: Razão | U33: Compra | Y33: =V34*5% -> 0 | AB33: Compra | AD33: Razão | AI33: Compra | AM33: =AJ34*5% -> 0 | AP33: Compra | AR33: Razão | AV33: Compra | AY33: =AW34*2.5% -> 0 | BC33: Compra | BE33: Razão | BI33: Compra | BL33: =BJ34*2.5% -> 0 | BP33: Compra | BR33: Razão | BV33: Compra | BY33: =BW34*2.5% -> 0 | CC33: Compra | CE33: Razão | CI33: Compra | CL33: =CJ34*2.5% -> 0 | CP33: Compra | CR33: Razão | CV33: Compra | CY33: =CW34*2.5% -> 0 | DC33: Compra | DE33: Razão | DI33: Compra | DL33: =DJ34*2.5% -> 0 | DP33: Compra | DR33: Razão | DV33: Compra | DY33: =DW34*2.5% -> 0 | EC33: Compra | EE33: Razão | EI33: Compra | EL33: =EJ34*2.5% -> 0 | EP33: Compra | ER33: Razão | EV33: Compra | EY33: =EW34*2.5% -> 0 | FC33: Compra | FE33: Razão | FI33: Compra | FL33: =FJ34*2.5% -> 0 | FP33: Compra | FR33: Razão | FV33: Compra | FY33: =FW34*2.5% -> 0 | GC33: Compra | GE33: Razão | GI33: Compra | GL33: =GJ34*2.5% -> 0
B34: Faturamento | D34: CNPJ: | H34: Faturamento | O34: Faturamento | Q34: CNPJ: | U34: Faturamento | AB34: Faturamento | AD34: CNPJ: | AI34: Faturamento | AP34: Faturamento | AR34: CNPJ: | AV34: Faturamento | BC34: Faturamento | BE34: CNPJ: | BI34: Faturamento | BP34: Faturamento | BR34: CNPJ: | BV34: Faturamento | CC34: Faturamento | CE34: CNPJ: | CI34: Faturamento | CP34: Faturamento | CR34: CNPJ: | CV34: Faturamento | DC34: Faturamento | DE34: CNPJ: | DI34: Faturamento | DP34: Faturamento | DR34: CNPJ: | DV34: Faturamento | EC34: Faturamento | EE34: CNPJ: | EI34: Faturamento | EP34: Faturamento | ER34: CNPJ: | EV34: Faturamento | FC34: Faturamento | FE34: CNPJ: | FI34: Faturamento | FP34: Faturamento | FR34: CNPJ: | FV34: Faturamento | GC34: Faturamento | GE34: CNPJ: | GI34: Faturamento
B36: Compra | D36: Razão | H36: Compra | L36: =I37*5% -> 0 | O36: Compra | Q36: Razão | U36: Compra | Y36: =V37*5% -> 0 | AB36: Compra | AD36: Razão | AI36: Compra | AM36: =AJ37*5% -> 0 | AP36: Compra | AR36: Razão | AV36: Compra | AY36: =AW37*2.5% -> 0 | BC36: Compra | BE36: Razão | BI36: Compra | BL36: =BJ37*2.5% -> 0 | BP36: Compra | BR36: Razão | BV36: Compra | BY36: =BW37*2.5% -> 0 | CC36: Compra | CE36: Razão | CI36: Compra | CL36: =CJ37*2.5% -> 0 | CP36: Compra | CR36: Razão | CV36: Compra | CY36: =CW37*2.5% -> 0 | DC36: Compra | DE36: Razão | DI36: Compra | DL36: =DJ37*2.5% -> 0 | DP36: Compra | DR36: Razão | DV36: Compra | DY36: =DW37*2.5% -> 0 | EC36: Compra | EE36: Razão | EI36: Compra | EL36: =EJ37*2.5% -> 0 | EP36: Compra | ER36: Razão | EV36: Compra | EY36: =EW37*2.5% -> 0 | FC36: Compra | FE36: Razão | FI36: Compra | FL36: =FJ37*2.5% -> 0 | FP36: Compra | FR36: Razão | FV36: Compra | FY36: =FW37*2.5% -> 0 | GC36: Compra | GE36: Razão | GI36: Compra | GL36: =GJ37*2.5% -> 0
B37: Faturamento | D37: CNPJ: | H37: Faturamento | O37: Faturamento | Q37: CNPJ: | U37: Faturamento | AB37: Faturamento | AD37: CNPJ: | AI37: Faturamento | AP37: Faturamento | AR37: CNPJ: | AV37: Faturamento | BC37: Faturamento | BE37: CNPJ: | BI37: Faturamento | BP37: Faturamento | BR37: CNPJ: | BV37: Faturamento | CC37: Faturamento | CE37: CNPJ: | CI37: Faturamento | CP37: Faturamento | CR37: CNPJ: | CV37: Faturamento | DC37: Faturamento | DE37: CNPJ: | DI37: Faturamento | DP37: Faturamento | DR37: CNPJ: | DV37: Faturamento | EC37: Faturamento | EE37: CNPJ: | EI37: Faturamento | EP37: Faturamento | ER37: CNPJ: | EV37: Faturamento | FC37: Faturamento | FE37: CNPJ: | FI37: Faturamento | FP37: Faturamento | FR37: CNPJ: | FV37: Faturamento | GC37: Faturamento | GE37: CNPJ: | GI37: Faturamento
B39: Compra | D39: Razão | H39: Compra | L39: =I40*5% -> 0 | O39: Compra | Q39: Razão | U39: Compra | Y39: =V40*5% -> 0 | AB39: Compra | AD39: Razão | AI39: Compra | AM39: =AJ40*5% -> 0 | AP39: Compra | AR39: Razão | AV39: Compra | AY39: =AW40*2.5% -> 0 | BC39: Compra | BE39: Razão | BI39: Compra | BL39: =BJ40*2.5% -> 0 | BP39: Compra | BR39: Razão | BV39: Compra | BY39: =BW40*2.5% -> 0 | CC39: Compra | CE39: Razão | CI39: Compra | CL39: =CJ40*2.5% -> 0 | CP39: Compra | CR39: Razão | CV39: Compra | CY39: =CW40*2.5% -> 0 | DC39: Compra | DE39: Razão | DI39: Compra | DL39: =DJ40*2.5% -> 0 | DP39: Compra | DR39: Razão | DV39: Compra | DY39: =DW40*2.5% -> 0 | EC39: Compra | EE39: Razão | EI39: Compra | EL39: =EJ40*2.5% -> 0 | EP39: Compra | ER39: Razão | EV39: Compra | EY39: =EW40*2.5% -> 0 | FC39: Compra | FE39: Razão | FI39: Compra | FL39: =FJ40*2.5% -> 0 | FP39: Compra | FR39: Razão | FV39: Compra | FY39: =FW40*2.5% -> 0 | GC39: Compra | GE39: Razão | GI39: Compra | GL39: =GJ40*2.5% -> 0
B40: Faturamento | D40: CNPJ: | H40: Faturamento | O40: Faturamento | Q40: CNPJ: | U40: Faturamento | AB40: Faturamento | AD40: CNPJ: | AI40: Faturamento | AP40: Faturamento | AR40: CNPJ: | AV40: Faturamento | BC40: Faturamento | BE40: CNPJ: | BI40: Faturamento | BP40: Faturamento | BR40: CNPJ: | BV40: Faturamento | CC40: Faturamento | CE40: CNPJ: | CI40: Faturamento | CP40: Faturamento | CR40: CNPJ: | CV40: Faturamento | DC40: Faturamento | DE40: CNPJ: | DI40: Faturamento | DP40: Faturamento | DR40: CNPJ: | DV40: Faturamento | EC40: Faturamento | EE40: CNPJ: | EI40: Faturamento | EP40: Faturamento | ER40: CNPJ: | EV40: Faturamento | FC40: Faturamento | FE40: CNPJ: | FI40: Faturamento | FP40: Faturamento | FR40: CNPJ: | FV40: Faturamento | GC40: Faturamento | GE40: CNPJ: | GI40: Faturamento
B42: Compra | D42: Razão | H42: Compra | L42: =I43*5% -> 0 | O42: Compra | Q42: Razão | U42: Compra | Y42: =V43*5% -> 0 | AB42: Compra | AD42: Razão | AI42: Compra | AM42: =AJ43*5% -> 0 | AP42: Compra | AR42: Razão | AV42: Compra | AY42: =AW43*2.5% -> 0 | BC42: Compra | BE42: Razão | BI42: Compra | BL42: =BJ43*2.5% -> 0 | BP42: Compra | BR42: Razão | BV42: Compra | BY42: =BW43*2.5% -> 0 | CC42: Compra | CE42: Razão | CI42: Compra | CL42: =CJ43*2.5% -> 0 | CP42: Compra | CR42: Razão | CV42: Compra | CY42: =CW43*2.5% -> 0 | DC42: Compra | DE42: Razão | DI42: Compra | DL42: =DJ43*2.5% -> 0 | DP42: Compra | DR42: Razão | DV42: Compra | DY42: =DW43*2.5% -> 0 | EC42: Compra | EE42: Razão | EI42: Compra | EL42: =EJ43*2.5% -> 0 | EP42: Compra | ER42: Razão | EV42: Compra | EY42: =EW43*2.5% -> 0 | FC42: Compra | FE42: Razão | FI42: Compra | FL42: =FJ43*2.5% -> 0 | FP42: Compra | FR42: Razão | FV42: Compra | FY42: =FW43*2.5% -> 0 | GC42: Compra | GE42: Razão | GI42: Compra | GL42: =GJ43*2.5% -> 0
B43: Faturamento | D43: CNPJ: | H43: Faturamento | O43: Faturamento | Q43: CNPJ: | U43: Faturamento | AB43: Faturamento | AD43: CNPJ: | AI43: Faturamento | AP43: Faturamento | AR43: CNPJ: | AV43: Faturamento | BC43: Faturamento | BE43: CNPJ: | BI43: Faturamento | BP43: Faturamento | BR43: CNPJ: | BV43: Faturamento | CC43: Faturamento | CE43: CNPJ: | CI43: Faturamento | CP43: Faturamento | CR43: CNPJ: | CV43: Faturamento | DC43: Faturamento | DE43: CNPJ: | DI43: Faturamento | DP43: Faturamento | DR43: CNPJ: | DV43: Faturamento | EC43: Faturamento | EE43: CNPJ: | EI43: Faturamento | EP43: Faturamento | ER43: CNPJ: | EV43: Faturamento | FC43: Faturamento | FE43: CNPJ: | FI43: Faturamento | FP43: Faturamento | FR43: CNPJ: | FV43: Faturamento | GC43: Faturamento | GE43: CNPJ: | GI43: Faturamento
B45: Compra | D45: Razão | H45: Compra | L45: =I46*5% -> 0 | O45: Compra | Q45: Razão | U45: Compra | Y45: =V46*5% -> 0 | AB45: Compra | AD45: Razão | AI45: Compra | AM45: =AJ46*5% -> 0 | AP45: Compra | AR45: Razão | AV45: Compra | AY45: =AW46*2.5% -> 0 | BC45: Compra | BE45: Razão | BI45: Compra | BL45: =BJ46*2.5% -> 0 | BP45: Compra | BR45: Razão | BV45: Compra | BY45: =BW46*2.5% -> 0 | CC45: Compra | CE45: Razão | CI45: Compra | CL45: =CJ46*2.5% -> 0 | CP45: Compra | CR45: Razão | CV45: Compra | CY45: =CW46*2.5% -> 0 | DC45: Compra | DE45: Razão | DI45: Compra | DL45: =DJ46*2.5% -> 0 | DP45: Compra | DR45: Razão | DV45: Compra | DY45: =DW46*2.5% -> 0 | EC45: Compra | EE45: Razão | EI45: Compra | EL45: =EJ46*2.5% -> 0 | EP45: Compra | ER45: Razão | EV45: Compra | EY45: =EW46*2.5% -> 0 | FC45: Compra | FE45: Razão | FI45: Compra | FL45: =FJ46*2.5% -> 0 | FP45: Compra | FR45: Razão | FV45: Compra | FY45: =FW46*2.5% -> 0 | GC45: Compra | GE45: Razão | GI45: Compra | GL45: =GJ46*2.5% -> 0
B46: Faturamento | D46: CNPJ: | H46: Faturamento | O46: Faturamento | Q46: CNPJ: | U46: Faturamento | AB46: Faturamento | AD46: CNPJ: | AI46: Faturamento | AP46: Faturamento | AR46: CNPJ: | AV46: Faturamento | BC46: Faturamento | BE46: CNPJ: | BI46: Faturamento | BP46: Faturamento | BR46: CNPJ: | BV46: Faturamento | CC46: Faturamento | CE46: CNPJ: | CI46: Faturamento | CP46: Faturamento | CR46: CNPJ: | CV46: Faturamento | DC46: Faturamento | DE46: CNPJ: | DI46: Faturamento | DP46: Faturamento | DR46: CNPJ: | DV46: Faturamento | EC46: Faturamento | EE46: CNPJ: | EI46: Faturamento | EP46: Faturamento | ER46: CNPJ: | EV46: Faturamento | FC46: Faturamento | FE46: CNPJ: | FI46: Faturamento | FP46: Faturamento | FR46: CNPJ: | FV46: Faturamento | GC46: Faturamento | GE46: CNPJ: | GI46: Faturamento
B48: Compra | D48: Razão | H48: Compra | L48: =I49*5% -> 0 | O48: Compra | Q48: Razão | U48: Compra | Y48: =V49*5% -> 0 | AB48: Compra | AD48: Razão | AI48: Compra | AM48: =AJ49*5% -> 0 | AP48: Compra | AR48: Razão | AV48: Compra | AY48: =AW49*2.5% -> 0 | BC48: Compra | BE48: Razão | BI48: Compra | BL48: =BJ49*2.5% -> 0 | BP48: Compra | BR48: Razão | BV48: Compra | BY48: =BW49*2.5% -> 0 | CC48: Compra | CE48: Razão | CI48: Compra | CL48: =CJ49*2.5% -> 0 | CP48: Compra | CR48: Razão | CV48: Compra | CY48: =CW49*2.5% -> 0 | DC48: Compra | DE48: Razão | DI48: Compra | DL48: =DJ49*2.5% -> 0 | DP48: Compra | DR48: Razão | DV48: Compra | DY48: =DW49*2.5% -> 0 | EC48: Compra | EE48: Razão | EI48: Compra | EL48: =EJ49*2.5% -> 0 | EP48: Compra | ER48: Razão | EV48: Compra | EY48: =EW49*2.5% -> 0 | FC48: Compra | FE48: Razão | FI48: Compra | FL48: =FJ49*2.5% -> 0 | FP48: Compra | FR48: Razão | FV48: Compra | FY48: =FW49*2.5% -> 0 | GC48: Compra | GE48: Razão | GI48: Compra | GL48: =GJ49*2.5% -> 0
B49: Faturamento | D49: CNPJ: | H49: Faturamento | O49: Faturamento | Q49: CNPJ: | U49: Faturamento | AB49: Faturamento | AD49: CNPJ: | AI49: Faturamento | AP49: Faturamento | AR49: CNPJ: | AV49: Faturamento | BC49: Faturamento | BE49: CNPJ: | BI49: Faturamento | BP49: Faturamento | BR49: CNPJ: | BV49: Faturamento | CC49: Faturamento | CE49: CNPJ: | CI49: Faturamento | CP49: Faturamento | CR49: CNPJ: | CV49: Faturamento | DC49: Faturamento | DE49: CNPJ: | DI49: Faturamento | DP49: Faturamento | DR49: CNPJ: | DV49: Faturamento | EC49: Faturamento | EE49: CNPJ: | EI49: Faturamento | EP49: Faturamento | ER49: CNPJ: | EV49: Faturamento | FC49: Faturamento | FE49: CNPJ: | FI49: Faturamento | FP49: Faturamento | FR49: CNPJ: | FV49: Faturamento | GC49: Faturamento | GE49: CNPJ: | GI49: Faturamento
B51: Compra | D51: Razão | H51: Compra | L51: =I52*5% -> 0 | O51: Compra | Q51: Razão | U51: Compra | Y51: =V52*5% -> 0 | AB51: Compra | AD51: Razão | AI51: Compra | AM51: =AJ52*5% -> 0 | AP51: Compra | AR51: Razão | AV51: Compra | AY51: =AW52*2.5% -> 0 | BC51: Compra | BE51: Razão | BI51: Compra | BL51: =BJ52*2.5% -> 0 | BP51: Compra | BR51: Razão | BV51: Compra | BY51: =BW52*2.5% -> 0 | CC51: Compra | CE51: Razão | CI51: Compra | CL51: =CJ52*2.5% -> 0 | CP51: Compra | CR51: Razão | CV51: Compra | CY51: =CW52*2.5% -> 0 | DC51: Compra | DE51: Razão | DI51: Compra | DL51: =DJ52*2.5% -> 0 | DP51: Compra | DR51: Razão | DV51: Compra | DY51: =DW52*2.5% -> 0 | EC51: Compra | EE51: Razão | EI51: Compra | EL51: =EJ52*2.5% -> 0 | EP51: Compra | ER51: Razão | EV51: Compra | EY51: =EW52*2.5% -> 0 | FC51: Compra | FE51: Razão | FI51: Compra | FL51: =FJ52*2.5% -> 0 | FP51: Compra | FR51: Razão | FV51: Compra | FY51: =FW52*2.5% -> 0 | GC51: Compra | GE51: Razão | GI51: Compra | GL51: =GJ52*2.5% -> 0
B52: Faturamento | D52: CNPJ: | H52: Faturamento | O52: Faturamento | Q52: CNPJ: | U52: Faturamento | AB52: Faturamento | AD52: CNPJ: | AI52: Faturamento | AP52: Faturamento | AR52: CNPJ: | AV52: Faturamento | BC52: Faturamento | BE52: CNPJ: | BI52: Faturamento | BP52: Faturamento | BR52: CNPJ: | BV52: Faturamento | CC52: Faturamento | CE52: CNPJ: | CI52: Faturamento | CP52: Faturamento | CR52: CNPJ: | CV52: Faturamento | DC52: Faturamento | DE52: CNPJ: | DI52: Faturamento | DP52: Faturamento | DR52: CNPJ: | DV52: Faturamento | EC52: Faturamento | EE52: CNPJ: | EI52: Faturamento | EP52: Faturamento | ER52: CNPJ: | EV52: Faturamento | FC52: Faturamento | FE52: CNPJ: | FI52: Faturamento | FP52: Faturamento | FR52: CNPJ: | FV52: Faturamento | GC52: Faturamento | GE52: CNPJ: | GI52: Faturamento
B54: Compra | D54: Razão | H54: Compra | L54: =I55*5% -> 0 | O54: Compra | Q54: Razão | U54: Compra | Y54: =V55*5% -> 0 | AB54: Compra | AD54: Razão | AI54: Compra | AM54: =AJ55*5% -> 0 | AP54: Compra | AR54: Razão | AV54: Compra | AY54: =AW55*2.5% -> 0 | BC54: Compra | BE54: Razão | BI54: Compra | BL54: =BJ55*2.5% -> 0 | BP54: Compra | BR54: Razão | BV54: Compra | BY54: =BW55*2.5% -> 0 | CC54: Compra | CE54: Razão | CI54: Compra | CL54: =CJ55*2.5% -> 0 | CP54: Compra | CR54: Razão | CV54: Compra | CY54: =CW55*2.5% -> 0 | DC54: Compra | DE54: Razão | DI54: Compra | DL54: =DJ55*2.5% -> 0 | DP54: Compra | DR54: Razão | DV54: Compra | DY54: =DW55*2.5% -> 0 | EC54: Compra | EE54: Razão | EI54: Compra | EL54: =EJ55*2.5% -> 0 | EP54: Compra | ER54: Razão | EV54: Compra | EY54: =EW55*2.5% -> 0 | FC54: Compra | FE54: Razão | FI54: Compra | FL54: =FJ55*2.5% -> 0 | FP54: Compra | FR54: Razão | FV54: Compra | FY54: =FW55*2.5% -> 0 | GC54: Compra | GE54: Razão | GI54: Compra | GL54: =GJ55*2.5% -> 0
B55: Faturamento | D55: CNPJ: | H55: Faturamento | O55: Faturamento | Q55: CNPJ: | U55: Faturamento | AB55: Faturamento | AD55: CNPJ: | AI55: Faturamento | AP55: Faturamento | AR55: CNPJ: | AV55: Faturamento | BC55: Faturamento | BE55: CNPJ: | BI55: Faturamento | BP55: Faturamento | BR55: CNPJ: | BV55: Faturamento | CC55: Faturamento | CE55: CNPJ: | CI55: Faturamento | CP55: Faturamento | CR55: CNPJ: | CV55: Faturamento | DC55: Faturamento | DE55: CNPJ: | DI55: Faturamento | DP55: Faturamento | DR55: CNPJ: | DV55: Faturamento | EC55: Faturamento | EE55: CNPJ: | EI55: Faturamento | EP55: Faturamento | ER55: CNPJ: | EV55: Faturamento | FC55: Faturamento | FE55: CNPJ: | FI55: Faturamento | FP55: Faturamento | FR55: CNPJ: | FV55: Faturamento | GC55: Faturamento | GE55: CNPJ: | GI55: Faturamento
B57: Compra | D57: Razão | H57: Compra | L57: =I58*5% -> 0 | O57: Compra | Q57: Razão | U57: Compra | Y57: =V58*5% -> 0 | AB57: Compra | AD57: Razão | AI57: Compra | AM57: =AJ58*5% -> 0 | AP57: Compra | AR57: Razão | AV57: Compra | AY57: =AW58*2.5% -> 0 | BC57: Compra | BE57: Razão | BI57: Compra | BL57: =BJ58*2.5% -> 0 | BP57: Compra | BR57: Razão | BV57: Compra | BY57: =BW58*2.5% -> 0 | CC57: Compra | CE57: Razão | CI57: Compra | CL57: =CJ58*2.5% -> 0 | CP57: Compra | CR57: Razão | CV57: Compra | CY57: =CW58*2.5% -> 0 | DC57: Compra | DE57: Razão | DI57: Compra | DL57: =DJ58*2.5% -> 0 | DP57: Compra | DR57: Razão | DV57: Compra | DY57: =DW58*2.5% -> 0 | EC57: Compra | EE57: Razão | EI57: Compra | EL57: =EJ58*2.5% -> 0 | EP57: Compra | ER57: Razão | EV57: Compra | EY57: =EW58*2.5% -> 0 | FC57: Compra | FE57: Razão | FI57: Compra | FL57: =FJ58*2.5% -> 0 | FP57: Compra | FR57: Razão | FV57: Compra | FY57: =FW58*2.5% -> 0 | GC57: Compra | GE57: Razão | GI57: Compra | GL57: =GJ58*2.5% -> 0
B58: Faturamento | D58: CNPJ: | H58: Faturamento | O58: Faturamento | Q58: CNPJ: | U58: Faturamento | AB58: Faturamento | AD58: CNPJ: | AI58: Faturamento | AP58: Faturamento | AR58: CNPJ: | AV58: Faturamento | BC58: Faturamento | BE58: CNPJ: | BI58: Faturamento | BP58: Faturamento | BR58: CNPJ: | BV58: Faturamento | CC58: Faturamento | CE58: CNPJ: | CI58: Faturamento | CP58: Faturamento | CR58: CNPJ: | CV58: Faturamento | DC58: Faturamento | DE58: CNPJ: | DI58: Faturamento | DP58: Faturamento | DR58: CNPJ: | DV58: Faturamento | EC58: Faturamento | EE58: CNPJ: | EI58: Faturamento | EP58: Faturamento | ER58: CNPJ: | EV58: Faturamento | FC58: Faturamento | FE58: CNPJ: | FI58: Faturamento | FP58: Faturamento | FR58: CNPJ: | FV58: Faturamento | GC58: Faturamento | GE58: CNPJ: | GI58: Faturamento
B60: Compra | D60: Razão | H60: Compra | L60: =I61*5% -> 0 | O60: Compra | Q60: Razão | U60: Compra | Y60: =V61*5% -> 0 | AB60: Compra | AD60: Razão | AI60: Compra | AM60: =AJ61*5% -> 0 | AP60: Compra | AR60: Razão | AV60: Compra | AY60: =AW61*2.5% -> 0 | BC60: Compra | BE60: Razão | BI60: Compra | BL60: =BJ61*2.5% -> 0 | BP60: Compra | BR60: Razão | BV60: Compra | BY60: =BW61*2.5% -> 0 | CC60: Compra | CE60: Razão | CI60: Compra | CL60: =CJ61*2.5% -> 0 | CP60: Compra | CR60: Razão | CV60: Compra | CY60: =CW61*2.5% -> 0 | DC60: Compra | DE60: Razão | DI60: Compra | DL60: =DJ61*2.5% -> 0 | DP60: Compra | DR60: Razão | DV60: Compra | DY60: =DW61*2.5% -> 0 | EC60: Compra | EE60: Razão | EI60: Compra | EL60: =EJ61*2.5% -> 0 | EP60: Compra | ER60: Razão | EV60: Compra | EY60: =EW61*2.5% -> 0 | FC60: Compra | FE60: Razão | FI60: Compra | FL60: =FJ61*2.5% -> 0 | FP60: Compra | FR60: Razão | FV60: Compra | FY60: =FW61*2.5% -> 0 | GC60: Compra | GE60: Razão | GI60: Compra | GL60: =GJ61*2.5% -> 0
B61: Faturamento | D61: CNPJ: | H61: Faturamento | O61: Faturamento | Q61: CNPJ: | U61: Faturamento | AB61: Faturamento | AD61: CNPJ: | AI61: Faturamento | AP61: Faturamento | AR61: CNPJ: | AV61: Faturamento | BC61: Faturamento | BE61: CNPJ: | BI61: Faturamento | BP61: Faturamento | BR61: CNPJ: | BV61: Faturamento | CC61: Faturamento | CE61: CNPJ: | CI61: Faturamento | CP61: Faturamento | CR61: CNPJ: | CV61: Faturamento | DC61: Faturamento | DE61: CNPJ: | DI61: Faturamento | DP61: Faturamento | DR61: CNPJ: | DV61: Faturamento | EC61: Faturamento | EE61: CNPJ: | EI61: Faturamento | EP61: Faturamento | ER61: CNPJ: | EV61: Faturamento | FC61: Faturamento | FE61: CNPJ: | FI61: Faturamento | FP61: Faturamento | FR61: CNPJ: | FV61: Faturamento | GC61: Faturamento | GE61: CNPJ: | GI61: Faturamento
AP63: Compra | AR63: Razão | AV63: Compra | AY63: =AW64*2.5% -> 0 | BC63: Compra | BE63: Razão | BI63: Compra | BL63: =BJ64*2.5% -> 0 | BP63: Compra | BR63: Razão | BV63: Compra | BY63: =BW64*2.5% -> 0 | CC63: Compra | CE63: Razão | CI63: Compra | CL63: =CJ64*2.5% -> 0 | CP63: Compra | CR63: Razão | CV63: Compra | CY63: =CW64*2.5% -> 0 | DC63: Compra | DE63: Razão | DI63: Compra | DL63: =DJ64*2.5% -> 0 | DP63: Compra | DR63: Razão | DV63: Compra | DY63: =DW64*2.5% -> 0 | EC63: Compra | EE63: Razão | EI63: Compra | EL63: =EJ64*2.5% -> 0 | EP63: Compra | ER63: Razão | EV63: Compra | EY63: =EW64*2.5% -> 0 | FC63: Compra | FE63: Razão | FI63: Compra | FL63: =FJ64*2.5% -> 0 | FP63: Compra | FR63: Razão | FV63: Compra | FY63: =FW64*2.5% -> 0 | GC63: Compra | GE63: Razão | GI63: Compra | GL63: =GJ64*2.5% -> 0
AP64: Faturamento | AR64: CNPJ: | AV64: Faturamento | BC64: Faturamento | BE64: CNPJ: | BI64: Faturamento | BP64: Faturamento | BR64: CNPJ: | BV64: Faturamento | CC64: Faturamento | CE64: CNPJ: | CI64: Faturamento | CP64: Faturamento | CR64: CNPJ: | CV64: Faturamento | DC64: Faturamento | DE64: CNPJ: | DI64: Faturamento | DP64: Faturamento | DR64: CNPJ: | DV64: Faturamento | EC64: Faturamento | EE64: CNPJ: | EI64: Faturamento | EP64: Faturamento | ER64: CNPJ: | EV64: Faturamento | FC64: Faturamento | FE64: CNPJ: | FI64: Faturamento | FP64: Faturamento | FR64: CNPJ: | FV64: Faturamento | GC64: Faturamento | GE64: CNPJ: | GI64: Faturamento
AP66: Compra | AR66: Razão | AV66: Compra | AY66: =AW67*2.5% -> 0 | BC66: Compra | BE66: Razão | BI66: Compra | BL66: =BJ67*2.5% -> 0 | BP66: Compra | BR66: Razão | BV66: Compra | BY66: =BW67*2.5% -> 0 | CC66: Compra | CE66: Razão | CI66: Compra | CL66: =CJ67*2.5% -> 0 | CP66: Compra | CR66: Razão | CV66: Compra | CY66: =CW67*2.5% -> 0 | DC66: Compra | DE66: Razão | DI66: Compra | DL66: =DJ67*2.5% -> 0 | DP66: Compra | DR66: Razão | DV66: Compra | DY66: =DW67*2.5% -> 0 | EC66: Compra | EE66: Razão | EI66: Compra | EL66: =EJ67*2.5% -> 0 | EP66: Compra | ER66: Razão | EV66: Compra | EY66: =EW67*2.5% -> 0 | FC66: Compra | FE66: Razão | FI66: Compra | FL66: =FJ67*2.5% -> 0 | FP66: Compra | FR66: Razão | FV66: Compra | FY66: =FW67*2.5% -> 0 | GC66: Compra | GE66: Razão | GI66: Compra | GL66: =GJ67*2.5% -> 0
AP67: Faturamento | AR67: CNPJ: | AV67: Faturamento | BC67: Faturamento | BE67: CNPJ: | BI67: Faturamento | BP67: Faturamento | BR67: CNPJ: | BV67: Faturamento | CC67: Faturamento | CE67: CNPJ: | CI67: Faturamento | CP67: Faturamento | CR67: CNPJ: | CV67: Faturamento | DC67: Faturamento | DE67: CNPJ: | DI67: Faturamento | DP67: Faturamento | DR67: CNPJ: | DV67: Faturamento | EC67: Faturamento | EE67: CNPJ: | EI67: Faturamento | EP67: Faturamento | ER67: CNPJ: | EV67: Faturamento | FC67: Faturamento | FE67: CNPJ: | FI67: Faturamento | FP67: Faturamento | FR67: CNPJ: | FV67: Faturamento | GC67: Faturamento | GE67: CNPJ: | GI67: Faturamento
AP69: Compra | AR69: Razão | AV69: Compra | AY69: =AW70*2.5% -> 0 | BC69: Compra | BE69: Razão | BI69: Compra | BL69: =BJ70*2.5% -> 0 | BP69: Compra | BR69: Razão | BV69: Compra | BY69: =BW70*2.5% -> 0 | CC69: Compra | CE69: Razão | CI69: Compra | CL69: =CJ70*2.5% -> 0 | CP69: Compra | CR69: Razão | CV69: Compra | CY69: =CW70*2.5% -> 0 | DC69: Compra | DE69: Razão | DI69: Compra | DL69: =DJ70*2.5% -> 0 | DP69: Compra | DR69: Razão | DV69: Compra | DY69: =DW70*2.5% -> 0 | EC69: Compra | EE69: Razão | EI69: Compra | EL69: =EJ70*2.5% -> 0 | EP69: Compra | ER69: Razão | EV69: Compra | EY69: =EW70*2.5% -> 0 | FC69: Compra | FE69: Razão | FI69: Compra | FL69: =FJ70*2.5% -> 0 | FP69: Compra | FR69: Razão | FV69: Compra | FY69: =FW70*2.5% -> 0 | GC69: Compra | GE69: Razão | GI69: Compra | GL69: =GJ70*2.5% -> 0
AP70: Faturamento | AR70: CNPJ: | AV70: Faturamento | BC70: Faturamento | BE70: CNPJ: | BI70: Faturamento | BP70: Faturamento | BR70: CNPJ: | BV70: Faturamento | CC70: Faturamento | CE70: CNPJ: | CI70: Faturamento | CP70: Faturamento | CR70: CNPJ: | CV70: Faturamento | DC70: Faturamento | DE70: CNPJ: | DI70: Faturamento | DP70: Faturamento | DR70: CNPJ: | DV70: Faturamento | EC70: Faturamento | EE70: CNPJ: | EI70: Faturamento | EP70: Faturamento | ER70: CNPJ: | EV70: Faturamento | FC70: Faturamento | FE70: CNPJ: | FI70: Faturamento | FP70: Faturamento | FR70: CNPJ: | FV70: Faturamento | GC70: Faturamento | GE70: CNPJ: | GI70: Faturamento
AP72: Compra | AR72: Razão | AV72: Compra | AY72: =AW73*2.5% -> 0 | BC72: Compra | BE72: Razão | BI72: Compra | BL72: =BJ73*2.5% -> 0 | BP72: Compra | BR72: Razão | BV72: Compra | BY72: =BW73*2.5% -> 0 | CC72: Compra | CE72: Razão | CI72: Compra | CL72: =CJ73*2.5% -> 0 | CP72: Compra | CR72: Razão | CV72: Compra | CY72: =CW73*2.5% -> 0 | DC72: Compra | DE72: Razão | DI72: Compra | DL72: =DJ73*2.5% -> 0 | DP72: Compra | DR72: Razão | DV72: Compra | DY72: =DW73*2.5% -> 0 | EC72: Compra | EE72: Razão | EI72: Compra | EL72: =EJ73*2.5% -> 0 | EP72: Compra | ER72: Razão | EV72: Compra | EY72: =EW73*2.5% -> 0 | FC72: Compra | FE72: Razão | FI72: Compra | FL72: =FJ73*2.5% -> 0 | FP72: Compra | FR72: Razão | FV72: Compra | FY72: =FW73*2.5% -> 0 | GC72: Compra | GE72: Razão | GI72: Compra | GL72: =GJ73*2.5% -> 0
AP73: Faturamento | AR73: CNPJ: | AV73: Faturamento | BC73: Faturamento | BE73: CNPJ: | BI73: Faturamento | BP73: Faturamento | BR73: CNPJ: | BV73: Faturamento | CC73: Faturamento | CE73: CNPJ: | CI73: Faturamento | CP73: Faturamento | CR73: CNPJ: | CV73: Faturamento | DC73: Faturamento | DE73: CNPJ: | DI73: Faturamento | DP73: Faturamento | DR73: CNPJ: | DV73: Faturamento | EC73: Faturamento | EE73: CNPJ: | EI73: Faturamento | EP73: Faturamento | ER73: CNPJ: | EV73: Faturamento | FC73: Faturamento | FE73: CNPJ: | FI73: Faturamento | FP73: Faturamento | FR73: CNPJ: | FV73: Faturamento | GC73: Faturamento | GE73: CNPJ: | GI73: Faturamento
AP75: Compra | AR75: Razão | AV75: Compra | AY75: =AW76*2.5% -> 0 | BC75: Compra | BE75: Razão | BI75: Compra | BL75: =BJ76*2.5% -> 0 | BP75: Compra | BR75: Razão | BV75: Compra | BY75: =BW76*2.5% -> 0 | CC75: Compra | CE75: Razão | CI75: Compra | CL75: =CJ76*2.5% -> 0 | CP75: Compra | CR75: Razão | CV75: Compra | CY75: =CW76*2.5% -> 0 | DC75: Compra | DE75: Razão | DI75: Compra | DL75: =DJ76*2.5% -> 0 | DP75: Compra | DR75: Razão | DV75: Compra | DY75: =DW76*2.5% -> 0 | EC75: Compra | EE75: Razão | EI75: Compra | EL75: =EJ76*2.5% -> 0 | EP75: Compra | ER75: Razão | EV75: Compra | EY75: =EW76*2.5% -> 0 | FC75: Compra | FE75: Razão | FI75: Compra | FL75: =FJ76*2.5% -> 0 | FP75: Compra | FR75: Razão | FV75: Compra | FY75: =FW76*2.5% -> 0 | GC75: Compra | GE75: Razão | GI75: Compra | GL75: =GJ76*2.5% -> 0
AP76: Faturamento | AR76: CNPJ: | AV76: Faturamento | BC76: Faturamento | BE76: CNPJ: | BI76: Faturamento | BP76: Faturamento | BR76: CNPJ: | BV76: Faturamento | CC76: Faturamento | CE76: CNPJ: | CI76: Faturamento | CP76: Faturamento | CR76: CNPJ: | CV76: Faturamento | DC76: Faturamento | DE76: CNPJ: | DI76: Faturamento | DP76: Faturamento | DR76: CNPJ: | DV76: Faturamento | EC76: Faturamento | EE76: CNPJ: | EI76: Faturamento | EP76: Faturamento | ER76: CNPJ: | EV76: Faturamento | FC76: Faturamento | FE76: CNPJ: | FI76: Faturamento | FP76: Faturamento | FR76: CNPJ: | FV76: Faturamento | GC76: Faturamento | GE76: CNPJ: | GI76: Faturamento
AP78: Compra | AR78: Razão | AV78: Compra | AY78: =AW79*2.5% -> 0 | BC78: Compra | BE78: Razão | BI78: Compra | BL78: =BJ79*2.5% -> 0 | BP78: Compra | BR78: Razão | BV78: Compra | BY78: =BW79*2.5% -> 0 | CC78: Compra | CE78: Razão | CI78: Compra | CL78: =CJ79*2.5% -> 0 | CP78: Compra | CR78: Razão | CV78: Compra | CY78: =CW79*2.5% -> 0 | DC78: Compra | DE78: Razão | DI78: Compra | DL78: =DJ79*2.5% -> 0 | DP78: Compra | DR78: Razão | DV78: Compra | DY78: =DW79*2.5% -> 0 | EC78: Compra | EE78: Razão | EI78: Compra | EL78: =EJ79*2.5% -> 0 | EP78: Compra | ER78: Razão | EV78: Compra | EY78: =EW79*2.5% -> 0 | FC78: Compra | FE78: Razão | FI78: Compra | FL78: =FJ79*2.5% -> 0 | FP78: Compra | FR78: Razão | FV78: Compra | FY78: =FW79*2.5% -> 0 | GC78: Compra | GE78: Razão | GI78: Compra | GL78: =GJ79*2.5% -> 0
AP79: Faturamento | AR79: CNPJ: | AV79: Faturamento | BC79: Faturamento | BE79: CNPJ: | BI79: Faturamento | BP79: Faturamento | BR79: CNPJ: | BV79: Faturamento | CC79: Faturamento | CE79: CNPJ: | CI79: Faturamento | CP79: Faturamento | CR79: CNPJ: | CV79: Faturamento | DC79: Faturamento | DE79: CNPJ: | DI79: Faturamento | DP79: Faturamento | DR79: CNPJ: | DV79: Faturamento | EC79: Faturamento | EE79: CNPJ: | EI79: Faturamento | EP79: Faturamento | ER79: CNPJ: | EV79: Faturamento | FC79: Faturamento | FE79: CNPJ: | FI79: Faturamento | FP79: Faturamento | FR79: CNPJ: | FV79: Faturamento | GC79: Faturamento | GE79: CNPJ: | GI79: Faturamento
AP81: Compra | AR81: Razão | AV81: Compra | AY81: =AW82*2.5% -> 0 | BC81: Compra | BE81: Razão | BI81: Compra | BL81: =BJ82*2.5% -> 0 | BP81: Compra | BR81: Razão | BV81: Compra | BY81: =BW82*2.5% -> 0 | CC81: Compra | CE81: Razão | CI81: Compra | CL81: =CJ82*2.5% -> 0 | CP81: Compra | CR81: Razão | CV81: Compra | CY81: =CW82*2.5% -> 0 | DC81: Compra | DE81: Razão | DI81: Compra | DL81: =DJ82*2.5% -> 0 | DP81: Compra | DR81: Razão | DV81: Compra | DY81: =DW82*2.5% -> 0 | EC81: Compra | EE81: Razão | EI81: Compra | EL81: =EJ82*2.5% -> 0 | EP81: Compra | ER81: Razão | EV81: Compra | EY81: =EW82*2.5% -> 0 | FC81: Compra | FE81: Razão | FI81: Compra | FL81: =FJ82*2.5% -> 0 | FP81: Compra | FR81: Razão | FV81: Compra | FY81: =FW82*2.5% -> 0 | GC81: Compra | GE81: Razão | GI81: Compra | GL81: =GJ82*2.5% -> 0
AP82: Faturamento | AR82: CNPJ: | AV82: Faturamento | BC82: Faturamento | BE82: CNPJ: | BI82: Faturamento | BP82: Faturamento | BR82: CNPJ: | BV82: Faturamento | CC82: Faturamento | CE82: CNPJ: | CI82: Faturamento | CP82: Faturamento | CR82: CNPJ: | CV82: Faturamento | DC82: Faturamento | DE82: CNPJ: | DI82: Faturamento | DP82: Faturamento | DR82: CNPJ: | DV82: Faturamento | EC82: Faturamento | EE82: CNPJ: | EI82: Faturamento | EP82: Faturamento | ER82: CNPJ: | EV82: Faturamento | FC82: Faturamento | FE82: CNPJ: | FI82: Faturamento | FP82: Faturamento | FR82: CNPJ: | FV82: Faturamento | GC82: Faturamento | GE82: CNPJ: | GI82: Faturamento
AP84: Compra | AR84: Razão | AV84: Compra | AY84: =AW85*2.5% -> 0 | BC84: Compra | BE84: Razão | BI84: Compra | BL84: =BJ85*2.5% -> 0 | BP84: Compra | BR84: Razão | BV84: Compra | BY84: =BW85*2.5% -> 0 | CC84: Compra | CE84: Razão | CI84: Compra | CL84: =CJ85*2.5% -> 0 | CP84: Compra | CR84: Razão | CV84: Compra | CY84: =CW85*2.5% -> 0 | DC84: Compra | DE84: Razão | DI84: Compra | DL84: =DJ85*2.5% -> 0 | DP84: Compra | DR84: Razão | DV84: Compra | DY84: =DW85*2.5% -> 0 | EC84: Compra | EE84: Razão | EI84: Compra | EL84: =EJ85*2.5% -> 0 | EP84: Compra | ER84: Razão | EV84: Compra | EY84: =EW85*2.5% -> 0 | FC84: Compra | FE84: Razão | FI84: Compra | FL84: =FJ85*2.5% -> 0 | FP84: Compra | FR84: Razão | FV84: Compra | FY84: =FW85*2.5% -> 0 | GC84: Compra | GE84: Razão | GI84: Compra | GL84: =GJ85*2.5% -> 0
AP85: Faturamento | AR85: CNPJ: | AV85: Faturamento | BC85: Faturamento | BE85: CNPJ: | BI85: Faturamento | BP85: Faturamento | BR85: CNPJ: | BV85: Faturamento | CC85: Faturamento | CE85: CNPJ: | CI85: Faturamento | CP85: Faturamento | CR85: CNPJ: | CV85: Faturamento | DC85: Faturamento | DE85: CNPJ: | DI85: Faturamento | DP85: Faturamento | DR85: CNPJ: | DV85: Faturamento | EC85: Faturamento | EE85: CNPJ: | EI85: Faturamento | EP85: Faturamento | ER85: CNPJ: | EV85: Faturamento | FC85: Faturamento | FE85: CNPJ: | FI85: Faturamento | FP85: Faturamento | FR85: CNPJ: | FV85: Faturamento | GC85: Faturamento | GE85: CNPJ: | GI85: Faturamento
AP87: Compra | AR87: Razão | AV87: Compra | AY87: =AW88*2.5% -> 0 | BC87: Compra | BE87: Razão | BI87: Compra | BL87: =BJ88*2.5% -> 0 | BP87: Compra | BR87: Razão | BV87: Compra | BY87: =BW88*2.5% -> 0 | CC87: Compra | CE87: Razão | CI87: Compra | CL87: =CJ88*2.5% -> 0 | CP87: Compra | CR87: Razão | CV87: Compra | CY87: =CW88*2.5% -> 0 | DC87: Compra | DE87: Razão | DI87: Compra | DL87: =DJ88*2.5% -> 0 | DP87: Compra | DR87: Razão | DV87: Compra | DY87: =DW88*2.5% -> 0 | EC87: Compra | EE87: Razão | EI87: Compra | EL87: =EJ88*2.5% -> 0 | EP87: Compra | ER87: Razão | EV87: Compra | EY87: =EW88*2.5% -> 0 | FC87: Compra | FE87: Razão | FI87: Compra | FL87: =FJ88*2.5% -> 0 | FP87: Compra | FR87: Razão | FV87: Compra | FY87: =FW88*2.5% -> 0 | GC87: Compra | GE87: Razão | GI87: Compra | GL87: =GJ88*2.5% -> 0
AP88: Faturamento | AR88: CNPJ: | AV88: Faturamento | BC88: Faturamento | BE88: CNPJ: | BI88: Faturamento | BP88: Faturamento | BR88: CNPJ: | BV88: Faturamento | CC88: Faturamento | CE88: CNPJ: | CI88: Faturamento | CP88: Faturamento | CR88: CNPJ: | CV88: Faturamento | DC88: Faturamento | DE88: CNPJ: | DI88: Faturamento | DP88: Faturamento | DR88: CNPJ: | DV88: Faturamento | EC88: Faturamento | EE88: CNPJ: | EI88: Faturamento | EP88: Faturamento | ER88: CNPJ: | EV88: Faturamento | FC88: Faturamento | FE88: CNPJ: | FI88: Faturamento | FP88: Faturamento | FR88: CNPJ: | FV88: Faturamento | GC88: Faturamento | GE88: CNPJ: | GI88: Faturamento
AP90: Compra | AR90: Razão | AV90: Compra | AY90: =AW91*2.5% -> 0 | BC90: Compra | BE90: Razão | BI90: Compra | BL90: =BJ91*2.5% -> 0 | BP90: Compra | BR90: Razão | BV90: Compra | BY90: =BW91*2.5% -> 0 | CC90: Compra | CE90: Razão | CI90: Compra | CL90: =CJ91*2.5% -> 0 | CP90: Compra | CR90: Razão | CV90: Compra | CY90: =CW91*2.5% -> 0 | DC90: Compra | DE90: Razão | DI90: Compra | DL90: =DJ91*2.5% -> 0 | DP90: Compra | DR90: Razão | DV90: Compra | DY90: =DW91*2.5% -> 0 | EC90: Compra | EE90: Razão | EI90: Compra | EL90: =EJ91*2.5% -> 0 | EP90: Compra | ER90: Razão | EV90: Compra | EY90: =EW91*2.5% -> 0 | FC90: Compra | FE90: Razão | FI90: Compra | FL90: =FJ91*2.5% -> 0 | FP90: Compra | FR90: Razão | FV90: Compra | FY90: =FW91*2.5% -> 0 | GC90: Compra | GE90: Razão | GI90: Compra | GL90: =GJ91*2.5% -> 0
AP91: Faturamento | AR91: CNPJ: | AV91: Faturamento | BC91: Faturamento | BE91: CNPJ: | BI91: Faturamento | BP91: Faturamento | BR91: CNPJ: | BV91: Faturamento | CC91: Faturamento | CE91: CNPJ: | CI91: Faturamento | CP91: Faturamento | CR91: CNPJ: | CV91: Faturamento | DC91: Faturamento | DE91: CNPJ: | DI91: Faturamento | DP91: Faturamento | DR91: CNPJ: | DV91: Faturamento | EC91: Faturamento | EE91: CNPJ: | EI91: Faturamento | EP91: Faturamento | ER91: CNPJ: | EV91: Faturamento | FC91: Faturamento | FE91: CNPJ: | FI91: Faturamento | FP91: Faturamento | FR91: CNPJ: | FV91: Faturamento | GC91: Faturamento | GE91: CNPJ: | GI91: Faturamento
AP93: Compra | AR93: Razão | AV93: Compra | AY93: =AW94*2.5% -> 0 | BC93: Compra | BE93: Razão | BI93: Compra | BL93: =BJ94*2.5% -> 0 | BP93: Compra | BR93: Razão | BV93: Compra | BY93: =BW94*2.5% -> 0 | CC93: Compra | CE93: Razão | CI93: Compra | CL93: =CJ94*2.5% -> 0 | CP93: Compra | CR93: Razão | CV93: Compra | CY93: =CW94*2.5% -> 0 | DC93: Compra | DE93: Razão | DI93: Compra | DL93: =DJ94*2.5% -> 0 | DP93: Compra | DR93: Razão | DV93: Compra | DY93: =DW94*2.5% -> 0 | EC93: Compra | EE93: Razão | EI93: Compra | EL93: =EJ94*2.5% -> 0 | EP93: Compra | ER93: Razão | EV93: Compra | EY93: =EW94*2.5% -> 0 | FC93: Compra | FE93: Razão | FI93: Compra | FL93: =FJ94*2.5% -> 0 | FP93: Compra | FR93: Razão | FV93: Compra | FY93: =FW94*2.5% -> 0 | GC93: Compra | GE93: Razão | GI93: Compra | GL93: =GJ94*2.5% -> 0
AP94: Faturamento | AR94: CNPJ: | AV94: Faturamento | BC94: Faturamento | BE94: CNPJ: | BI94: Faturamento | BP94: Faturamento | BR94: CNPJ: | BV94: Faturamento | CC94: Faturamento | CE94: CNPJ: | CI94: Faturamento | CP94: Faturamento | CR94: CNPJ: | CV94: Faturamento | DC94: Faturamento | DE94: CNPJ: | DI94: Faturamento | DP94: Faturamento | DR94: CNPJ: | DV94: Faturamento | EC94: Faturamento | EE94: CNPJ: | EI94: Faturamento | EP94: Faturamento | ER94: CNPJ: | EV94: Faturamento | FC94: Faturamento | FE94: CNPJ: | FI94: Faturamento | FP94: Faturamento | FR94: CNPJ: | FV94: Faturamento | GC94: Faturamento | GE94: CNPJ: | GI94: Faturamento
AP96: Compra | AR96: Razão | AV96: Compra | AY96: =AW97*2.5% -> 0 | BC96: Compra | BE96: Razão | BI96: Compra | BL96: =BJ97*2.5% -> 0 | BP96: Compra | BR96: Razão | BV96: Compra | BY96: =BW97*2.5% -> 0 | CC96: Compra | CE96: Razão | CI96: Compra | CL96: =CJ97*2.5% -> 0 | CP96: Compra | CR96: Razão | CV96: Compra | CY96: =CW97*2.5% -> 0 | DC96: Compra | DE96: Razão | DI96: Compra | DL96: =DJ97*2.5% -> 0 | DP96: Compra | DR96: Razão | DV96: Compra | DY96: =DW97*2.5% -> 0 | EC96: Compra | EE96: Razão | EI96: Compra | EL96: =EJ97*2.5% -> 0 | EP96: Compra | ER96: Razão | EV96: Compra | EY96: =EW97*2.5% -> 0 | FC96: Compra | FE96: Razão | FI96: Compra | FL96: =FJ97*2.5% -> 0 | FP96: Compra | FR96: Razão | FV96: Compra | FY96: =FW97*2.5% -> 0 | GC96: Compra | GE96: Razão | GI96: Compra | GL96: =GJ97*2.5% -> 0
AP97: Faturamento | AR97: CNPJ: | AV97: Faturamento | BC97: Faturamento | BE97: CNPJ: | BI97: Faturamento | BP97: Faturamento | BR97: CNPJ: | BV97: Faturamento | CC97: Faturamento | CE97: CNPJ: | CI97: Faturamento | CP97: Faturamento | CR97: CNPJ: | CV97: Faturamento | DC97: Faturamento | DE97: CNPJ: | DI97: Faturamento | DP97: Faturamento | DR97: CNPJ: | DV97: Faturamento | EC97: Faturamento | EE97: CNPJ: | EI97: Faturamento | EP97: Faturamento | ER97: CNPJ: | EV97: Faturamento | FC97: Faturamento | FE97: CNPJ: | FI97: Faturamento | FP97: Faturamento | FR97: CNPJ: | FV97: Faturamento | GC97: Faturamento | GE97: CNPJ: | GI97: Faturamento
AP99: Compra | AR99: Razão | AV99: Compra | AY99: =AW100*2.5% -> 0 | BC99: Compra | BE99: Razão | BI99: Compra | BL99: =BJ100*2.5% -> 0 | BP99: Compra | BR99: Razão | BV99: Compra | BY99: =BW100*2.5% -> 0 | CC99: Compra | CE99: Razão | CI99: Compra | CL99: =CJ100*2.5% -> 0 | CP99: Compra | CR99: Razão | CV99: Compra | CY99: =CW100*2.5% -> 0 | DC99: Compra | DE99: Razão | DI99: Compra | DL99: =DJ100*2.5% -> 0 | DP99: Compra | DR99: Razão | DV99: Compra | DY99: =DW100*2.5% -> 0 | EC99: Compra | EE99: Razão | EI99: Compra | EL99: =EJ100*2.5% -> 0 | EP99: Compra | ER99: Razão | EV99: Compra | EY99: =EW100*2.5% -> 0 | FC99: Compra | FE99: Razão | FI99: Compra | FL99: =FJ100*2.5% -> 0 | FP99: Compra | FR99: Razão | FV99: Compra | FY99: =FW100*2.5% -> 0 | GC99: Compra | GE99: Razão | GI99: Compra | GL99: =GJ100*2.5% -> 0
AP100: Faturamento | AR100: CNPJ: | AV100: Faturamento | BC100: Faturamento | BE100: CNPJ: | BI100: Faturamento | BP100: Faturamento | BR100: CNPJ: | BV100: Faturamento | CC100: Faturamento | CE100: CNPJ: | CI100: Faturamento | CP100: Faturamento | CR100: CNPJ: | CV100: Faturamento | DC100: Faturamento | DE100: CNPJ: | DI100: Faturamento | DP100: Faturamento | DR100: CNPJ: | DV100: Faturamento | EC100: Faturamento | EE100: CNPJ: | EI100: Faturamento | EP100: Faturamento | ER100: CNPJ: | EV100: Faturamento | FC100: Faturamento | FE100: CNPJ: | FI100: Faturamento | FP100: Faturamento | FR100: CNPJ: | FV100: Faturamento | GC100: Faturamento | GE100: CNPJ: | GI100: Faturamento
AT104: VALOR VENDA | AV104: =AW4+AW7+AW10+AW13+AW16+AW19+AW22+AW25+AW28+AW31+AW34+AW37+AW40+AW43+AW46+AW49+AW52+AW55+AW58+AW61+AW64+AW67+AW70+AW73+AW76+AW79+AW82+AW85+AW88+AW91+AW94+AW97+AW100 -> 0 | AX104: VALOR COMISSÃO | AZ104: =AY3+AY6+AY9+AY12+AY15+AY18+AY21+AY24+AY27+AY30+AY33+AY36+AY39+AY42+AY45+AY48+AY51+AY54+AY57+AY60+AY63+AY66+AY69+AY72+AY75+AY78+AY81+AY84+AY87+AY90+AY93+AY96+AY99 -> 0 | BG104: VALOR VENDA | BI104: =BJ4+BJ7+BJ10+BJ13+BJ16+BJ19+BJ22+BJ25+BJ28+BJ31+BJ34+BJ37+BJ40+BJ43+BJ46+BJ49+BJ52+BJ55+BJ58+BJ61+BJ64+BJ67+BJ70+BJ73+BJ76+BJ79+BJ82+BJ85+BJ88+BJ91+BJ94+BJ97+BJ100 -> 0 | BK104: VALOR COMISSÃO | BM104: =BL3+BL6+BL9+BL12+BL15+BL18+BL21+BL24+BL27+BL30+BL33+BL36+BL39+BL42+BL45+BL48+BL51+BL54+BL57+BL60+BL63+BL66+BL69+BL72+BL75+BL78+BL81+BL84+BL87+BL90+BL93+BL96+BL99 -> 0 | BT104: VALOR VENDA | BV104: =BW4+BW7+BW10+BW13+BW16+BW19+BW22+BW25+BW28+BW31+BW34+BW37+BW40+BW43+BW46+BW49+BW52+BW55+BW58+BW61+BW64+BW67+BW70+BW73+BW76+BW79+BW82+BW85+BW88+BW91+BW94+BW97+BW100 -> 0 | BX104: VALOR COMISSÃO | BZ104: =BY3+BY6+BY9+BY12+BY15+BY18+BY21+BY24+BY27+BY30+BY33+BY36+BY39+BY42+BY45+BY48+BY51+BY54+BY57+BY60+BY63+BY66+BY69+BY72+BY75+BY78+BY81+BY84+BY87+BY90+BY93+BY96+BY99 -> 0 | CG104: VALOR VENDA | CI104: =CJ4+CJ7+CJ10+CJ13+CJ16+CJ19+CJ22+CJ25+CJ28+CJ31+CJ34+CJ37+CJ40+CJ43+CJ46+CJ49+CJ52+CJ55+CJ58+CJ61+CJ64+CJ67+CJ70+CJ73+CJ76+CJ79+CJ82+CJ85+CJ88+CJ91+CJ94+CJ97+CJ100 -> 0 | CK104: VALOR COMISSÃO | CM104: =CL3+CL6+CL9+CL12+CL15+CL18+CL21+CL24+CL27+CL30+CL33+CL36+CL39+CL42+CL45+CL48+CL51+CL54+CL57+CL60+CL63+CL66+CL69+CL72+CL75+CL78+CL81+CL84+CL87+CL90+CL93+CL96+CL99 -> 0 | CT104: VALOR VENDA | CV104: =CW4+CW7+CW10+CW13+CW16+CW19+CW22+CW25+CW28+CW31+CW34+CW37+CW40+CW43+CW46+CW49+CW52+CW55+CW58+CW61+CW64+CW67+CW70+CW73+CW76+CW79+CW82+CW85+CW88+CW91+CW94+CW97+CW100 -> 0 | CX104: VALOR COMISSÃO | CZ104: =CY3+CY6+CY9+CY12+CY15+CY18+CY21+CY24+CY27+CY30+CY33+CY36+CY39+CY42+CY45+CY48+CY51+CY54+CY57+CY60+CY63+CY66+CY69+CY72+CY75+CY78+CY81+CY84+CY87+CY90+CY93+CY96+CY99 -> 0 | DG104: VALOR VENDA | DI104: =DJ4+DJ7+DJ10+DJ13+DJ16+DJ19+DJ22+DJ25+DJ28+DJ31+DJ34+DJ37+DJ40+DJ43+DJ46+DJ49+DJ52+DJ55+DJ58+DJ61+DJ64+DJ67+DJ70+DJ73+DJ76+DJ79+DJ82+DJ85+DJ88+DJ91+DJ94+DJ97+DJ100 -> 0 | DK104: VALOR COMISSÃO | DM104: =DL3+DL6+DL9+DL12+DL15+DL18+DL21+DL24+DL27+DL30+DL33+DL36+DL39+DL42+DL45+DL48+DL51+DL54+DL57+DL60+DL63+DL66+DL69+DL72+DL75+DL78+DL81+DL84+DL87+DL90+DL93+DL96+DL99 -> 0 | DT104: VALOR VENDA | DV104: =DW4+DW7+DW10+DW13+DW16+DW19+DW22+DW25+DW28+DW31+DW34+DW37+DW40+DW43+DW46+DW49+DW52+DW55+DW58+DW61+DW64+DW67+DW70+DW73+DW76+DW79+DW82+DW85+DW88+DW91+DW94+DW97+DW100 -> 0 | DX104: VALOR COMISSÃO | DZ104: =DY3+DY6+DY9+DY12+DY15+DY18+DY21+DY24+DY27+DY30+DY33+DY36+DY39+DY42+DY45+DY48+DY51+DY54+DY57+DY60+DY63+DY66+DY69+DY72+DY75+DY78+DY81+DY84+DY87+DY90+DY93+DY96+DY99 -> 0 | EG104: VALOR VENDA | EI104: =EJ4+EJ7+EJ10+EJ13+EJ16+EJ19+EJ22+EJ25+EJ28+EJ31+EJ34+EJ37+EJ40+EJ43+EJ46+EJ49+EJ52+EJ55+EJ58+EJ61+EJ64+EJ67+EJ70+EJ73+EJ76+EJ79+EJ82+EJ85+EJ88+EJ91+EJ94+EJ97+EJ100 -> 0 | EK104: VALOR COMISSÃO | EM104: =EL3+EL6+EL9+EL12+EL15+EL18+EL21+EL24+EL27+EL30+EL33+EL36+EL39+EL42+EL45+EL48+EL51+EL54+EL57+EL60+EL63+EL66+EL69+EL72+EL75+EL78+EL81+EL84+EL87+EL90+EL93+EL96+EL99 -> 0 | ET104: VALOR VENDA | EV104: =EW4+EW7+EW10+EW13+EW16+EW19+EW22+EW25+EW28+EW31+EW34+EW37+EW40+EW43+EW46+EW49+EW52+EW55+EW58+EW61+EW64+EW67+EW70+EW73+EW76+EW79+EW82+EW85+EW88+EW91+EW94+EW97+EW100 -> 0 | EX104: VALOR COMISSÃO | EZ104: =EY3+EY6+EY9+EY12+EY15+EY18+EY21+EY24+EY27+EY30+EY33+EY36+EY39+EY42+EY45+EY48+EY51+EY54+EY57+EY60+EY63+EY66+EY69+EY72+EY75+EY78+EY81+EY84+EY87+EY90+EY93+EY96+EY99 -> 0 | FG104: VALOR VENDA | FI104: =FJ4+FJ7+FJ10+FJ13+FJ16+FJ19+FJ22+FJ25+FJ28+FJ31+FJ34+FJ37+FJ40+FJ43+FJ46+FJ49+FJ52+FJ55+FJ58+FJ61+FJ64+FJ67+FJ70+FJ73+FJ76+FJ79+FJ82+FJ85+FJ88+FJ91+FJ94+FJ97+FJ100 -> 0 | FK104: VALOR COMISSÃO | FM104: =FL3+FL6+FL9+FL12+FL15+FL18+FL21+FL24+FL27+FL30+FL33+FL36+FL39+FL42+FL45+FL48+FL51+FL54+FL57+FL60+FL63+FL66+FL69+FL72+FL75+FL78+FL81+FL84+FL87+FL90+FL93+FL96+FL99 -> 0 | FT104: VALOR VENDA | FV104: =FW4+FW7+FW10+FW13+FW16+FW19+FW22+FW25+FW28+FW31+FW34+FW37+FW40+FW43+FW46+FW49+FW52+FW55+FW58+FW61+FW64+FW67+FW70+FW73+FW76+FW79+FW82+FW85+FW88+FW91+FW94+FW97+FW100 -> 0 | FX104: VALOR COMISSÃO | FZ104: =FY3+FY6+FY9+FY12+FY15+FY18+FY21+FY24+FY27+FY30+FY33+FY36+FY39+FY42+FY45+FY48+FY51+FY54+FY57+FY60+FY63+FY66+FY69+FY72+FY75+FY78+FY81+FY84+FY87+FY90+FY93+FY96+FY99 -> 0 | GG104: VALOR VENDA | GI104: =GJ4+GJ7+GJ10+GJ13+GJ16+GJ19+GJ22+GJ25+GJ28+GJ31+GJ34+GJ37+GJ40+GJ43+GJ46+GJ49+GJ52+GJ55+GJ58+GJ61+GJ64+GJ67+GJ70+GJ73+GJ76+GJ79+GJ82+GJ85+GJ88+GJ91+GJ94+GJ97+GJ100 -> 0 | GK104: VALOR COMISSÃO | GM104: =GL3+GL6+GL9+GL12+GL15+GL18+GL21+GL24+GL27+GL30+GL33+GL36+GL39+GL42+GL45+GL48+GL51+GL54+GL57+GL60+GL63+GL66+GL69+GL72+GL75+GL78+GL81+GL84+GL87+GL90+GL93+GL96+GL99 -> 0

Sheet DECOR MART
B1: JUNHO | M1: Voltar ao Inicio | O1: JULHO | Z1: Voltar ao Inicio | AB1: AGOSTO | AN1: Voltar ao Inicio | AP1: Janeiro | BA1: Voltar ao Inicio | BC1: Fevereiro | BN1: Voltar ao Inicio | BP1: Março | CA1: Voltar ao Inicio | CC1: Abril | CN1: Voltar ao Inicio | CP1: Maio | DA1: Voltar ao Inicio | DC1: Junho | DN1: Voltar ao Inicio | DP1: Julho | EA1: Voltar ao Inicio | EC1: Agosto | EN1: Voltar ao Inicio | EP1: Setembro | FA1: Voltar ao Inicio | FC1: Outubro | FN1: Voltar ao Inicio | FP1: Novembro | GA1: Voltar ao Inicio | GC1: Dezembro | GN1: Voltar ao Inicio
B2: Data | D2: CLIENTE | F2: Pedido | G2: NFE | H2: Valor | J2: TABELA | K2: PRAZO | L2: Comissão | M2: Situação Pedido | O2: Data | Q2: CLIENTE | S2: Pedido | T2: NFE | U2: Valor | W2: TABELA | X2: PRAZO | Y2: Comissão | Z2: Situação Pedido | AB2: Data | AD2: CLIENTE | AF2: Pedido | AG2: FORNECEDOR | AH2: NFE | AI2: Valor | AK2: TABELA | AL2: PRAZO | AM2: Comissão | AN2: Situação Pedido | AP2: Data | AR2: CLIENTE | AT2: Pedido | AU2: NFE | AV2: Valor | AX2: TABELA | AY2: Comissão | AZ2: Vendedor | BA2: Situação Pedido | BC2: Data | BE2: CLIENTE | BG2: Pedido | BH2: NFE | BI2: Valor | BK2: TABELA | BL2: Comissão | BM2: Vendedor | BN2: Situação Pedido | BP2: Data | BR2: CLIENTE | BT2: Pedido | BU2: NFE | BV2: Valor | BX2: TABELA | BY2: Comissão | BZ2: Vendedor | CA2: Situação Pedido | CC2: Data | CE2: CLIENTE | CG2: Pedido | CH2: NFE | CI2: Valor | CK2: TABELA | CL2: Comissão | CM2: Vendedor | CN2: Situação Pedido | CP2: Data | CR2: CLIENTE | CT2: Pedido | CU2: NFE | CV2: Valor | CX2: TABELA | CY2: Comissão | CZ2: Vendedor | DA2: Situação Pedido | DC2: Data | DE2: CLIENTE | DG2: Pedido | DH2: NFE | DI2: Valor | DK2: TABELA | DL2: Comissão | DM2: Vendedor | DN2: Situação Pedido | DP2: Data | DR2: CLIENTE | DT2: Pedido | DU2: NFE | DV2: Valor | DX2: TABELA | DY2: Comissão | DZ2: Vendedor | EA2: Situação Pedido | EC2: Data | EE2: CLIENTE | EG2: Pedido | EH2: NFE | EI2: Valor | EK2: TABELA | EL2: Comissão | EM2: Vendedor | EN2: Situação Pedido | EP2: Data | ER2: CLIENTE | ET2: Pedido | EU2: NFE | EV2: Valor | EX2: TABELA | EY2: Comissão | EZ2: Vendedor | FA2: Situação Pedido | FC2: Data | FE2: CLIENTE | FG2: Pedido | FH2: NFE | FI2: Valor | FK2: TABELA | FL2: Comissão | FM2: Vendedor | FN2: Situação Pedido | FP2: Data | FR2: CLIENTE | FT2: Pedido | FU2: NFE | FV2: Valor | FX2: TABELA | FY2: Comissão | FZ2: Vendedor | GA2: Situação Pedido | GC2: Data | GE2: CLIENTE | GG2: Pedido | GH2: NFE | GI2: Valor | GK2: TABELA | GL2: Comissão | GM2: Vendedor | GN2: Situação Pedido
B3: Compra | C3: 45811 | D3: Razão | E3: DECAZZA COM | F3: 250602172053470 | G3: 1441 | H3: Compra | I3: 755.44 | J3: 2 | K3: PIX | L3: =I4*5% -> 37.772 | M3: PAGO | O3: Compra | P3: 45846 | Q3: Razão | R3: DECAZZA COM | S3: 250708135238581 | T3: 187 | U3: Compra | V3: 10891.96 | W3: 2 | X3: PIX | Y3: =V4*5% -> 544.598 | Z3: FATURADO | AB3: Compra | AD3: Razão | AI3: Compra | AL3: PIX | AN3: PAGO | AP3: Compra | AR3: Razão | AV3: Compra | AY3: =AW4*2.5% -> 0 | BC3: Compra | BE3: Razão | BI3: Compra | BK3: 3 | BL3: =BJ4*5% -> 0 | BM3: RENAN | BP3: Compra | BR3: Razão | BV3: Compra | BY3: =BW4*2.5% -> 0 | CC3: Compra | CE3: Razão | CI3: Compra | CL3: =CJ4*2.5% -> 0 | CP3: Compra | CR3: Razão | CV3: Compra | CY3: =CW4*2.5% -> 0 | DC3: Compra | DE3: Razão | DI3: Compra | DL3: =DJ4*2.5% -> 0 | DP3: Compra | DR3: Razão | DV3: Compra | DY3: =DW4*2.5% -> 0 | EC3: Compra | EE3: Razão | EI3: Compra | EL3: =EJ4*2.5% -> 0 | EP3: Compra | ER3: Razão | EV3: Compra | EY3: =EW4*2.5% -> 0 | FC3: Compra | FE3: Razão | FI3: Compra | FL3: =FJ4*2.5% -> 0 | FP3: Compra | FR3: Razão | FV3: Compra | FY3: =FW4*2.5% -> 0 | GC3: Compra | GE3: Razão | GI3: Compra | GL3: =GJ4*2.5% -> 0
B4: Faturamento | C4: 45812 | D4: CNPJ: | E4: 43.967.691/0001-00 | H4: Faturamento | I4: 755.44 | O4: Faturamento | P4: 45848 | Q4: CNPJ: | R4: 43.967.691/0001-00 | U4: Faturamento | V4: 10891.96 | AB4: Faturamento | AD4: CNPJ: | AI4: Faturamento | AP4: Faturamento | AR4: CNPJ: | AV4: Faturamento | BC4: Faturamento | BE4: CNPJ: | BI4: Faturamento | BP4: Faturamento | BR4: CNPJ: | BV4: Faturamento | CC4: Faturamento | CE4: CNPJ: | CI4: Faturamento | CP4: Faturamento | CR4: CNPJ: | CV4: Faturamento | DC4: Faturamento | DE4: CNPJ: | DI4: Faturamento | DP4: Faturamento | DR4: CNPJ: | DV4: Faturamento | EC4: Faturamento | EE4: CNPJ: | EI4: Faturamento | EP4: Faturamento | ER4: CNPJ: | EV4: Faturamento | FC4: Faturamento | FE4: CNPJ: | FI4: Faturamento | FP4: Faturamento | FR4: CNPJ: | FV4: Faturamento | GC4: Faturamento | GE4: CNPJ: | GI4: Faturamento
